Workbook

Sheet Read Me
A1: Urban Integrated Municipal ERP: GWMC project plan
A2: Hake Technologies | Version 0.1 draft | 23 October 2026 | Based on product SRS v0.35 and Technical Architecture v0.1
A4: What is in this workbook
A5: Assumptions: project start date, contingency, holidays and optional day rates. Yellow cells are yours to change; everything else recalculates.
A6: Project Plan: phases, tasks and subtasks with start offset, duration, dates, predecessors, effort in person-days by team role, and a monthly Gantt.
A7: Team Summary: effort by phase and by module for each team role, with contingency and optional cost.
A8: Resource Loading: full-time staff needed per role per month, from the Gantt allocation.
A9: Milestones: phase go-lives and sign-offs with dates.
A10: Planner Import: one row per subtask (title, bucket, start, due, label, effort, notes) for Microsoft Planner in Teams.
A11: MS Project Import: ID, name, outline level, duration, start, finish, predecessors and work, for the Microsoft Project import wizard.
A12: Risks: top delivery risks with owners and mitigations.
A14: How to edit
... A27: These are planning estimates for a first plan. Refine them with the module teams after the Phase 1 design workshops.

Sheet Assumptions
A1: Assumptions and inputs
A3: Item | C3: Value | D3: Note | F3: Holidays (enter GWMC / Telangana holidays)
A4: Project start date (Monday) | C4: 46328 | D4: Assumed; set to the agreed start
A5: Contingency on effort | C5: 0.15 | D5: Assumed 15% for estimation uncertainty
A6: Working hours per person-day | C6: 8 | D6: Standard day
A7: Currency for optional costing | C7: INR | D7: Day rates below are optional
A10: Team roles and optional day rates
A11: Code | B11: Role | C11: Day rate (optional)
A12: PM | B12: Project manager | C12: 0
A13: BA | B13: Business analyst | C13: 0
A14: ARC | B14: Solution / technical architect | C14: 0
A15: BE | B15: Backend developer | C15: 0
A16: FE | B16: Frontend developer | C16: 0
A17: MOB | B17: Mobile developer | C17: 0
A18: GIS | B18: GIS engineer | C18: 0
A19: DEV | B19: DevOps / infrastructure | C19: 0
A20: QA | B20: QA / test engineer | C20: 0
A21: DATA | B21: Data migration engineer | C21: 0
A22: TRN | B22: Trainer / change manager | C22: 0

Sheet Project Plan
A1: Project plan: Urban ERP for GWMC (all phases)
A2: Blue = editable estimates. Dates use working days from the start date and holidays on the Assumptions sheet. Gantt cells show the share of each subtask falling in that month.
AF3: Gantt (share of subtask effort per month)
A4: ID | B4: WBS | C4: Level | D4: Type | E4: Task / subtask | F4: Phase | G4: Module | H4: Lead team | I4: Start offset (wd) | J4: Duration (wd) | K4: Start | L4: Finish | M4: Predecessors (ID) | N4: PM | O4: BA | P4: ARC | Q4: BE | R4: FE | S4: MOB | T4: GIS | U4: DEV | V4: QA | W4: DATA | X4: TRN | Y4: Total effort (pd) | Z4: Effort + contingency (pd) | AA4: Deliverable / reference | AB4: Status | AC4: Owner | AD4: % complete | AF4: =EDATE(DATE(YEAR(Assumptions!$C$4),MONTH(Assumptions!$C$4),1),0) -> 46327 | AG4: =EDATE(DATE(YEAR(Assumptions!$C$4),MONTH(Assumptions!$C$4),1),1) -> 46357 | AH4: =EDATE(DATE(YEAR(Assumptions!$C$4),MONTH(Assumptions!$C$4),1),2) -> 46388 | AI4: =EDATE(DATE(YEAR(Assumptions!$C$4),MONTH(Assumptions!$C$4),1),3) -> 46419 | AJ4: =EDATE(DATE(YEAR(Assumptions!$C$4),MONTH(Assumptions!$C$4),1),4) -> 46447 | AK4: =EDATE(DATE(YEAR(Assumptions!$C$4),MONTH(Assumptions!$C$4),1),5) -> 46478 | AL4: =EDATE(DATE(YEAR(Assumptions!$C$4),MONTH(Assumptions!$C$4),1),6) -> 46508 | AM4: =EDATE(DATE(YEAR(Assumptions!$C$4),MONTH(Assumptions!$C$4),1),7) -> 46539 | AN4: =EDATE(DATE(YEAR(Assumptions!$C$4),MONTH(Assumptions!$C$4),1),8) -> 46569 | AO4: =EDATE(DATE(YEAR(Assumptions!$C$4),MONTH(Assumptions!$C$4),1),9) -> 46600 | AP4: =EDATE(DATE(YEAR(Assumptions!$C$4),MONTH(Assumptions!$C$4),1),10) -> 46631 | AQ4: =EDATE(DATE(YEAR(Assumptions!$C$4),MONTH(Assumptions!$C$4),1),11) -> 46661 | AR4: =EDATE(DATE(YEAR(Assumptions!$C$4),MONTH(Assumptions!$C$4),1),12) -> 46692 | AS4: =EDATE(DATE(YEAR(Assumptions!$C$4),MONTH(Assumptions!$C$4),1),13) -> 46722 | AT4: =EDATE(DATE(YEAR(Assumptions!$C$4),MONTH(Assumptions!$C$4),1),14) -> 46753 | AU4: =EDATE(DATE(YEAR(Assumptions!$C$4),MONTH(Assumptions!$C$4),1),15) -> 46784 | AV4: =EDATE(DATE(YEAR(Assumptions!$C$4),MONTH(Assumptions!$C$4),1),16) -> 46813 | AW4: =EDATE(DATE(YEAR(Assumptions!$C$4),MONTH(Assumptions!$C$4),1),17) -> 46844 | AX4: =EDATE(DATE(YEAR(Assumptions!$C$4),MONTH(Assumptions!$C$4),1),18) -> 46874 | AY4: =EDATE(DATE(YEAR(Assumptions!$C$4),MONTH(Assumptions!$C$4),1),19) -> 46905 | AZ4: =EDATE(DATE(YEAR(Assumptions!$C$4),MONTH(Assumptions!$C$4),1),20) -> 46935 | BA4: =EDATE(DATE(YEAR(Assumptions!$C$4),MONTH(Assumptions!$C$4),1),21) -> 46966 | BB4: =EDATE(DATE(YEAR(Assumptions!$C$4),MONTH(Assumptions!$C$4),1),22) -> 46997 | BC4: =EDATE(DATE(YEAR(Assumptions!$C$4),MONTH(Assumptions!$C$4),1),23) -> 47027
A5: 1 | B5: 1 | C5: 1 | D5: Phase | E5: Programme management and governance | F5: All | J5: =NETWORKDAYS(K5,L5,Assumptions!$F$4:$F$44) -> 440 | K5: =MIN(K6:K14) -> 46328 | L5: =MAX(L6:L14) -> 46941 | N5: =SUMPRODUCT(($C$6:$C$14=3)*(N6:N14)) -> 345 | O5: =SUMPRODUCT(($C$6:$C$14=3)*(O6:O14)) -> 30 | P5: =SUMPRODUCT(($C$6:$C$14=3)*(P6:P14)) -> 89 | Q5: =SUMPRODUCT(($C$6:$C$14=3)*(Q6:Q14)) -> 30 | R5: =SUMPRODUCT(($C$6:$C$14=3)*(R6:R14)) -> 0 | S5: =SUMPRODUCT(($C$6:$C$14=3)*(S6:S14)) -> 0 | T5: =SUMPRODUCT(($C$6:$C$14=3)*(T6:T14)) -> 0 | U5: =SUMPRODUCT(($C$6:$C$14=3)*(U6:U14)) -> 15 | ... X5: =SUMPRODUCT(($C$6:$C$14=3)*(X6:X14)) -> 10 | Y5: =SUM(N5:X5) -> 527 | Z5: =Y5*(1+Assumptions!$C$5) -> 606.05 | AF5: 0 | AG5: 0 | AH5: 0 | AI5: 0 | AJ5: 0 | AK5: 0 | AL5: 0 | AM5: 0 | AN5: 0 | AO5: 0 | AP5: 0 | AQ5: 0 | AR5: 0 | AS5: 0 | AT5: 0 | AU5: 0 | AV5: 0 | AW5: 0 | AX5: 0 | AY5: 0 | AZ5: 0 | BA5: 0 | BB5: 0 | BC5: 0
A6: 2 | B6: 1.1 | C6: 2 | D6: Task | E6: Project governance and PMO | F6: All | J6: =NETWORKDAYS(K6,L6,Assumptions!$F$4:$F$44) -> 440 | K6: =MIN(K7:K11) -> 46328 | L6: =MAX(L7:L11) -> 46941 | N6: =SUMPRODUCT(($C$7:$C$11=3)*(N7:N11)) -> 313 | O6: =SUMPRODUCT(($C$7:$C$11=3)*(O7:O11)) -> 10 | P6: =SUMPRODUCT(($C$7:$C$11=3)*(P7:P11)) -> 71 | Q6: =SUMPRODUCT(($C$7:$C$11=3)*(Q7:Q11)) -> 30 | R6: =SUMPRODUCT(($C$7:$C$11=3)*(R7:R11)) -> 0 | S6: =SUMPRODUCT(($C$7:$C$11=3)*(S7:S11)) -> 0 | T6: =SUMPRODUCT(($C$7:$C$11=3)*(T7:T11)) -> 0 | U6: =SUMPRODUCT(($C$7:$C$11=3)*(U7:U11)) -> 15 | ... X6: =SUMPRODUCT(($C$7:$C$11=3)*(X7:X11)) -> 10 | Y6: =SUM(N6:X6) -> 449 | Z6: =Y6*(1+Assumptions!$C$5) -> 516.35 | AF6: 0 | AG6: 0 | AH6: 0 | AI6: 0 | AJ6: 0 | AK6: 0 | AL6: 0 | AM6: 0 | AN6: 0 | AO6: 0 | AP6: 0 | AQ6: 0 | AR6: 0 | AS6: 0 | AT6: 0 | AU6: 0 | AV6: 0 | AW6: 0 | AX6: 0 | AY6: 0 | AZ6: 0 | BA6: 0 | BB6: 0 | BC6: 0
A7: 3 | B7: 1.1.1 | C7: 3 | D7: Subtask | E7: PMO, planning, status reporting and steering committee: Phase 1 | F7: All | H7: PM | I7: 0 | J7: 140 | K7: =WORKDAY(Assumptions!$C$4,I7,Assumptions!$F$4:$F$44) -> 46328 | L7: =IF(J7=0,K7,WORKDAY(K7,J7-1,Assumptions!$F$4:$F$44)) -> 46521 | N7: 70 | O7: 0 | P7: 14 | Q7: 0 | R7: 0 | S7: 0 | T7: 0 | U7: 0 | V7: 0 | W7: 0 | X7: 0 | Y7: =SUM(N7:X7) -> 84 | Z7: =Y7*(1+Assumptions!$C$5) -> 96.6 | AA7: Weekly status, monthly steering minutes, RAID log | AB7: Not started | AD7: 0 | AF7: =IF($J7=0,0,MAX(0,NETWORKDAYS(MAX($K7,AF$4),MIN($L7,EOMONTH(AF$4,0)),Assumptions!$F$4:$F$44))/NETWORKDAYS($K7,$L7,Assumptions!$F$4:$F$44)) -> 0.15 | AG7: =IF($J7=0,0,MAX(0,NETWORKDAYS(MAX($K7,AG$4),MIN($L7,EOMONTH(AG$4,0)),Assumptions!$F$4:$F$44))/NETWORKDAYS($K7,$L7,Assumptions!$F$4:$F$44)) -> 0.16428571 | AH7: =IF($J7=0,0,MAX(0,NETWORKDAYS(MAX($K7,AH$4),MIN($L7,EOMONTH(AH$4,0)),Assumptions!$F$4:$F$44))/NETWORKDAYS($K7,$L7,Assumptions!$F$4:$F$44)) -> 0.15 | AI7: =IF($J7=0,0,MAX(0,NETWORKDAYS(MAX($K7,AI$4),MIN($L7,EOMONTH(AI$4,0)),Assumptions!$F$4:$F$44))/NETWORKDAYS($K7,$L7,Assumptions!$F$4:$F$44)) -> 0.14285714 | AJ7: =IF($J7=0,0,MAX(0,NETWORKDAYS(MAX($K7,AJ$4),MIN($L7,EOMONTH(AJ$4,0)),Assumptions!$F$4:$F$44))/NETWORKDAYS($K7,$L7,Assumptions!$F$4:$F$44)) -> 0.16428571 | AK7: =IF($J7=0,0,MAX(0,NETWORKDAYS(MAX($K7,AK$4),MIN($L7,EOMONTH(AK$4,0)),Assumptions!$F$4:$F$44))/NETWORKDAYS($K7,$L7,Assumptions!$F$4:$F$44)) -> 0.15714286 | AL7: =IF($J7=0,0,MAX(0,NETWORKDAYS(MAX($K7,AL$4),MIN($L7,EOMONTH(AL$4,0)),Assumptions!$F$4:$F$44))/NETWORKDAYS($K7,$L7,Assumptions!$F$4:$F$44)) -> 0.071428571 | AM7: =IF($J7=0,0,MAX(0,NETWORKDAYS(MAX($K7,AM$4),MIN($L7,EOMONTH(AM$4,0)),Assumptions!$F$4:$F$44))/NETWORKDAYS($K7,$L7,Assumptions!$F$4:$F$44)) -> 0 | ... BC7: =IF($J7=0,0,MAX(0,NETWORKDAYS(MAX($K7,BC$4),MIN($L7,EOMONTH(BC$4,0)),Assumptions!$F$4:$F$44))/NETWORKDAYS($K7,$L7,Assumptions!$F$4:$F$44)) -> 0
A8: 4 | B8: 1.1.2 | C8: 3 | D8: Subtask | E8: PMO, planning, status reporting and steering committee: Phase 2 | F8: All | H8: PM | I8: 88 | J8: 141 | K8: =WORKDAY(Assumptions!$C$4,I8,Assumptions!$F$4:$F$44) -> 46450 | L8: =IF(J8=0,K8,WORKDAY(K8,J8-1,Assumptions!$F$4:$F$44)) -> 46646 | N8: 71 | O8: 0 | P8: 14 | Q8: 0 | R8: 0 | S8: 0 | T8: 0 | U8: 0 | V8: 0 | W8: 0 | X8: 0 | Y8: =SUM(N8:X8) -> 85 | Z8: =Y8*(1+Assumptions!$C$5) -> 97.75 | AA8: Weekly status, monthly steering minutes, RAID log | AB8: Not started | AD8: 0 | AF8: =IF($J8=0,0,MAX(0,NETWORKDAYS(MAX($K8,AF$4),MIN($L8,EOMONTH(AF$4,0)),Assumptions!$F$4:$F$44))/NETWORKDAYS($K8,$L8,Assumptions!$F$4:$F$44)) -> 0 | AG8: =IF($J8=0,0,MAX(0,NETWORKDAYS(MAX($K8,AG$4),MIN($L8,EOMONTH(AG$4,0)),Assumptions!$F$4:$F$44))/NETWORKDAYS($K8,$L8,Assumptions!$F$4:$F$44)) -> 0 | AH8: =IF($J8=0,0,MAX(0,NETWORKDAYS(MAX($K8,AH$4),MIN($L8,EOMONTH(AH$4,0)),Assumptions!$F$4:$F$44))/NETWORKDAYS($K8,$L8,Assumptions!$F$4:$F$44)) -> 0 | AI8: =IF($J8=0,0,MAX(0,NETWORKDAYS(MAX($K8,AI$4),MIN($L8,EOMONTH(AI$4,0)),Assumptions!$F$4:$F$44))/NETWORKDAYS($K8,$L8,Assumptions!$F$4:$F$44)) -> 0 | AJ8: =IF($J8=0,0,MAX(0,NETWORKDAYS(MAX($K8,AJ$4),MIN($L8,EOMONTH(AJ$4,0)),Assumptions!$F$4:$F$44))/NETWORKDAYS($K8,$L8,Assumptions!$F$4:$F$44)) -> 0.14184397 | AK8: =IF($J8=0,0,MAX(0,NETWORKDAYS(MAX($K8,AK$4),MIN($L8,EOMONTH(AK$4,0)),Assumptions!$F$4:$F$44))/NETWORKDAYS($K8,$L8,Assumptions!$F$4:$F$44)) -> 0.15602837 | AL8: =IF($J8=0,0,MAX(0,NETWORKDAYS(MAX($K8,AL$4),MIN($L8,EOMONTH(AL$4,0)),Assumptions!$F$4:$F$44))/NETWORKDAYS($K8,$L8,Assumptions!$F$4:$F$44)) -> 0.14893617 | AM8: =IF($J8=0,0,MAX(0,NETWORKDAYS(MAX($K8,AM$4),MIN($L8,EOMONTH(AM$4,0)),Assumptions!$F$4:$F$44))/NETWORKDAYS($K8,$L8,Assumptions!$F$4:$F$44)) -> 0.15602837 | ... BC8: =IF($J8=0,0,MAX(0,NETWORKDAYS(MAX($K8,BC$4),MIN($L8,EOMONTH(BC$4,0)),Assumptions!$F$4:$F$44))/NETWORKDAYS($K8,$L8,Assumptions!$F$4:$F$44)) -> 0
A9: 5 | B9: 1.1.3 | C9: 3 | D9: Subtask | E9: PMO, planning, status reporting and steering committee: Phase 3 | F9: All | H9: PM | I9: 176 | J9: 141 | K9: =WORKDAY(Assumptions!$C$4,I9,Assumptions!$F$4:$F$44) -> 46574 | L9: =IF(J9=0,K9,WORKDAY(K9,J9-1,Assumptions!$F$4:$F$44)) -> 46770 | N9: 71 | O9: 0 | P9: 14 | Q9: 0 | R9: 0 | S9: 0 | T9: 0 | U9: 0 | V9: 0 | W9: 0 | X9: 0 | Y9: =SUM(N9:X9) -> 85 | Z9: =Y9*(1+Assumptions!$C$5) -> 97.75 | AA9: Weekly status, monthly steering minutes, RAID log | AB9: Not started | AD9: 0 | AF9: =IF($J9=0,0,MAX(0,NETWORKDAYS(MAX($K9,AF$4),MIN($L9,EOMONTH(AF$4,0)),Assumptions!$F$4:$F$44))/NETWORKDAYS($K9,$L9,Assumptions!$F$4:$F$44)) -> 0 | AG9: =IF($J9=0,0,MAX(0,NETWORKDAYS(MAX($K9,AG$4),MIN($L9,EOMONTH(AG$4,0)),Assumptions!$F$4:$F$44))/NETWORKDAYS($K9,$L9,Assumptions!$F$4:$F$44)) -> 0 | AH9: =IF($J9=0,0,MAX(0,NETWORKDAYS(MAX($K9,AH$4),MIN($L9,EOMONTH(AH$4,0)),Assumptions!$F$4:$F$44))/NETWORKDAYS($K9,$L9,Assumptions!$F$4:$F$44)) -> 0 | AI9: =IF($J9=0,0,MAX(0,NETWORKDAYS(MAX($K9,AI$4),MIN($L9,EOMONTH(AI$4,0)),Assumptions!$F$4:$F$44))/NETWORKDAYS($K9,$L9,Assumptions!$F$4:$F$44)) -> 0 | AJ9: =IF($J9=0,0,MAX(0,NETWORKDAYS(MAX($K9,AJ$4),MIN($L9,EOMONTH(AJ$4,0)),Assumptions!$F$4:$F$44))/NETWORKDAYS($K9,$L9,Assumptions!$F$4:$F$44)) -> 0 | AK9: =IF($J9=0,0,MAX(0,NETWORKDAYS(MAX($K9,AK$4),MIN($L9,EOMONTH(AK$4,0)),Assumptions!$F$4:$F$44))/NETWORKDAYS($K9,$L9,Assumptions!$F$4:$F$44)) -> 0 | AL9: =IF($J9=0,0,MAX(0,NETWORKDAYS(MAX($K9,AL$4),MIN($L9,EOMONTH(AL$4,0)),Assumptions!$F$4:$F$44))/NETWORKDAYS($K9,$L9,Assumptions!$F$4:$F$44)) -> 0 | AM9: =IF($J9=0,0,MAX(0,NETWORKDAYS(MAX($K9,AM$4),MIN($L9,EOMONTH(AM$4,0)),Assumptions!$F$4:$F$44))/NETWORKDAYS($K9,$L9,Assumptions!$F$4:$F$44)) -> 0 | ... BC9: =IF($J9=0,0,MAX(0,NETWORKDAYS(MAX($K9,BC$4),MIN($L9,EOMONTH(BC$4,0)),Assumptions!$F$4:$F$44))/NETWORKDAYS($K9,$L9,Assumptions!$F$4:$F$44)) -> 0
A10: 6 | B10: 1.1.4 | C10: 3 | D10: Subtask | E10: PMO, planning, status reporting and steering committee: Phase 4 | F10: All | H10: PM | I10: 264 | J10: 141 | K10: =WORKDAY(Assumptions!$C$4,I10,Assumptions!$F$4:$F$44) -> 46696 | L10: =IF(J10=0,K10,WORKDAY(K10,J10-1,Assumptions!$F$4:$F$44)) -> 46892 | N10: 71 | O10: 0 | P10: 14 | Q10: 0 | R10: 0 | S10: 0 | T10: 0 | U10: 0 | V10: 0 | W10: 0 | X10: 0 | Y10: =SUM(N10:X10) -> 85 | Z10: =Y10*(1+Assumptions!$C$5) -> 97.75 | AA10: Weekly status, monthly steering minutes, RAID log | AB10: Not started | AD10: 0 | AF10: =IF($J10=0,0,MAX(0,NETWORKDAYS(MAX($K10,AF$4),MIN($L10,EOMONTH(AF$4,0)),Assumptions!$F$4:$F$44))/NETWORKDAYS($K10,$L10,Assumptions!$F$4:$F$44)) -> 0 | AG10: =IF($J10=0,0,MAX(0,NETWORKDAYS(MAX($K10,AG$4),MIN($L10,EOMONTH(AG$4,0)),Assumptions!$F$4:$F$44))/NETWORKDAYS($K10,$L10,Assumptions!$F$4:$F$44)) -> 0 | AH10: =IF($J10=0,0,MAX(0,NETWORKDAYS(MAX($K10,AH$4),MIN($L10,EOMONTH(AH$4,0)),Assumptions!$F$4:$F$44))/NETWORKDAYS($K10,$L10,Assumptions!$F$4:$F$44)) -> 0 | AI10: =IF($J10=0,0,MAX(0,NETWORKDAYS(MAX($K10,AI$4),MIN($L10,EOMONTH(AI$4,0)),Assumptions!$F$4:$F$44))/NETWORKDAYS($K10,$L10,Assumptions!$F$4:$F$44)) -> 0 | AJ10: =IF($J10=0,0,MAX(0,NETWORKDAYS(MAX($K10,AJ$4),MIN($L10,EOMONTH(AJ$4,0)),Assumptions!$F$4:$F$44))/NETWORKDAYS($K10,$L10,Assumptions!$F$4:$F$44)) -> 0 | AK10: =IF($J10=0,0,MAX(0,NETWORKDAYS(MAX($K10,AK$4),MIN($L10,EOMONTH(AK$4,0)),Assumptions!$F$4:$F$44))/NETWORKDAYS($K10,$L10,Assumptions!$F$4:$F$44)) -> 0 | AL10: =IF($J10=0,0,MAX(0,NETWORKDAYS(MAX($K10,AL$4),MIN($L10,EOMONTH(AL$4,0)),Assumptions!$F$4:$F$44))/NETWORKDAYS($K10,$L10,Assumptions!$F$4:$F$44)) -> 0 | AM10: =IF($J10=0,0,MAX(0,NETWORKDAYS(MAX($K10,AM$4),MIN($L10,EOMONTH(AM$4,0)),Assumptions!$F$4:$F$44))/NETWORKDAYS($K10,$L10,Assumptions!$F$4:$F$44)) -> 0 | ... BC10: =IF($J10=0,0,MAX(0,NETWORKDAYS(MAX($K10,BC$4),MIN($L10,EOMONTH(BC$4,0)),Assumptions!$F$4:$F$44))/NETWORKDAYS($K10,$L10,Assumptions!$F$4:$F$44)) -> 0
A11: 7 | B11: 1.1.5 | C11: 3 | D11: Subtask | E11: Final stabilisation, knowledge transfer and handover | F11: All | H11: PM | I11: 400 | J11: 40 | K11: =WORKDAY(Assumptions!$C$4,I11,Assumptions!$F$4:$F$44) -> 46888 | L11: =IF(J11=0,K11,WORKDAY(K11,J11-1,Assumptions!$F$4:$F$44)) -> 46941 | N11: 30 | O11: 10 | P11: 15 | Q11: 30 | R11: 0 | S11: 0 | T11: 0 | U11: 15 | V11: 0 | W11: 0 | X11: 10 | Y11: =SUM(N11:X11) -> 110 | Z11: =Y11*(1+Assumptions!$C$5) -> 126.5 | AA11: Handover pack, runbooks, KT sign-off | AB11: Not started | AD11: 0 | AF11: =IF($J11=0,0,MAX(0,NETWORKDAYS(MAX($K11,AF$4),MIN($L11,EOMONTH(AF$4,0)),Assumptions!$F$4:$F$44))/NETWORKDAYS($K11,$L11,Assumptions!$F$4:$F$44)) -> 0 | AG11: =IF($J11=0,0,MAX(0,NETWORKDAYS(MAX($K11,AG$4),MIN($L11,EOMONTH(AG$4,0)),Assumptions!$F$4:$F$44))/NETWORKDAYS($K11,$L11,Assumptions!$F$4:$F$44)) -> 0 | AH11: =IF($J11=0,0,MAX(0,NETWORKDAYS(MAX($K11,AH$4),MIN($L11,EOMONTH(AH$4,0)),Assumptions!$F$4:$F$44))/NETWORKDAYS($K11,$L11,Assumptions!$F$4:$F$44)) -> 0 | AI11: =IF($J11=0,0,MAX(0,NETWORKDAYS(MAX($K11,AI$4),MIN($L11,EOMONTH(AI$4,0)),Assumptions!$F$4:$F$44))/NETWORKDAYS($K11,$L11,Assumptions!$F$4:$F$44)) -> 0 | AJ11: =IF($J11=0,0,MAX(0,NETWORKDAYS(MAX($K11,AJ$4),MIN($L11,EOMONTH(AJ$4,0)),Assumptions!$F$4:$F$44))/NETWORKDAYS($K11,$L11,Assumptions!$F$4:$F$44)) -> 0 | AK11: =IF($J11=0,0,MAX(0,NETWORKDAYS(MAX($K11,AK$4),MIN($L11,EOMONTH(AK$4,0)),Assumptions!$F$4:$F$44))/NETWORKDAYS($K11,$L11,Assumptions!$F$4:$F$44)) -> 0 | AL11: =IF($J11=0,0,MAX(0,NETWORKDAYS(MAX($K11,AL$4),MIN($L11,EOMONTH(AL$4,0)),Assumptions!$F$4:$F$44))/NETWORKDAYS($K11,$L11,Assumptions!$F$4:$F$44)) -> 0 | AM11: =IF($J11=0,0,MAX(0,NETWORKDAYS(MAX($K11,AM$4),MIN($L11,EOMONTH(AM$4,0)),Assumptions!$F$4:$F$44))/NETWORKDAYS($K11,$L11,Assumptions!$F$4:$F$44)) -> 0 | ... BC11: =IF($J11=0,0,MAX(0,NETWORKDAYS(MAX($K11,BC$4),MIN($L11,EOMONTH(BC$4,0)),Assumptions!$F$4:$F$44))/NETWORKDAYS($K11,$L11,Assumptions!$F$4:$F$44)) -> 0
A12: 8 | B12: 1.2 | C12: 2 | D12: Task | E12: Change control and quality | F12: All | J12: =NETWORKDAYS(K12,L12,Assumptions!$F$4:$F$44) -> 400 | K12: =MIN(K13:K14) -> 46356 | L12: =MAX(L13:L14) -> 46913 | N12: =SUMPRODUCT(($C$13:$C$14=3)*(N13:N14)) -> 32 | O12: =SUMPRODUCT(($C$13:$C$14=3)*(O13:O14)) -> 20 | P12: =SUMPRODUCT(($C$13:$C$14=3)*(P13:P14)) -> 18 | Q12: =SUMPRODUCT(($C$13:$C$14=3)*(Q13:Q14)) -> 0 | R12: =SUMPRODUCT(($C$13:$C$14=3)*(R13:R14)) -> 0 | S12: =SUMPRODUCT(($C$13:$C$14=3)*(S13:S14)) -> 0 | T12: =SUMPRODUCT(($C$13:$C$14=3)*(T13:T14)) -> 0 | U12: =SUMPRODUCT(($C$13:$C$14=3)*(U13:U14)) -> 0 | ... X12: =SUMPRODUCT(($C$13:$C$14=3)*(X13:X14)) -> 0 | Y12: =SUM(N12:X12) -> 78 | Z12: =Y12*(1+Assumptions!$C$5) -> 89.7 | AF12: 0 | AG12: 0 | AH12: 0 | AI12: 0 | AJ12: 0 | AK12: 0 | AL12: 0 | AM12: 0 | AN12: 0 | AO12: 0 | AP12: 0 | AQ12: 0 | AR12: 0 | AS12: 0 | AT12: 0 | AU12: 0 | AV12: 0 | AW12: 0 | AX12: 0 | AY12: 0 | AZ12: 0 | BA12: 0 | BB12: 0 | BC12: 0
A13: 9 | B13: 1.2.1 | C13: 3 | D13: Subtask | E13: Change request process and impact assessments (whole programme) | F13: All | H13: PM | I13: 20 | J13: 400 | K13: =WORKDAY(Assumptions!$C$4,I13,Assumptions!$F$4:$F$44) -> 46356 | L13: =IF(J13=0,K13,WORKDAY(K13,J13-1,Assumptions!$F$4:$F$44)) -> 46913 | N13: 20 | O13: 20 | P13: 10 | Q13: 0 | R13: 0 | S13: 0 | T13: 0 | U13: 0 | V13: 0 | W13: 0 | X13: 0 | Y13: =SUM(N13:X13) -> 50 | Z13: =Y13*(1+Assumptions!$C$5) -> 57.5 | AA13: CR register | AB13: Not started | AD13: 0 | AF13: =IF($J13=0,0,MAX(0,NETWORKDAYS(MAX($K13,AF$4),MIN($L13,EOMONTH(AF$4,0)),Assumptions!$F$4:$F$44))/NETWORKDAYS($K13,$L13,Assumptions!$F$4:$F$44)) -> 0.0025 | AG13: =IF($J13=0,0,MAX(0,NETWORKDAYS(MAX($K13,AG$4),MIN($L13,EOMONTH(AG$4,0)),Assumptions!$F$4:$F$44))/NETWORKDAYS($K13,$L13,Assumptions!$F$4:$F$44)) -> 0.0575 | AH13: =IF($J13=0,0,MAX(0,NETWORKDAYS(MAX($K13,AH$4),MIN($L13,EOMONTH(AH$4,0)),Assumptions!$F$4:$F$44))/NETWORKDAYS($K13,$L13,Assumptions!$F$4:$F$44)) -> 0.0525 | AI13: =IF($J13=0,0,MAX(0,NETWORKDAYS(MAX($K13,AI$4),MIN($L13,EOMONTH(AI$4,0)),Assumptions!$F$4:$F$44))/NETWORKDAYS($K13,$L13,Assumptions!$F$4:$F$44)) -> 0.05 | AJ13: =IF($J13=0,0,MAX(0,NETWORKDAYS(MAX($K13,AJ$4),MIN($L13,EOMONTH(AJ$4,0)),Assumptions!$F$4:$F$44))/NETWORKDAYS($K13,$L13,Assumptions!$F$4:$F$44)) -> 0.0575 | AK13: =IF($J13=0,0,MAX(0,NETWORKDAYS(MAX($K13,AK$4),MIN($L13,EOMONTH(AK$4,0)),Assumptions!$F$4:$F$44))/NETWORKDAYS($K13,$L13,Assumptions!$F$4:$F$44)) -> 0.055 | AL13: =IF($J13=0,0,MAX(0,NETWORKDAYS(MAX($K13,AL$4),MIN($L13,EOMONTH(AL$4,0)),Assumptions!$F$4:$F$44))/NETWORKDAYS($K13,$L13,Assumptions!$F$4:$F$44)) -> 0.0525 | AM13: =IF($J13=0,0,MAX(0,NETWORKDAYS(MAX($K13,AM$4),MIN($L13,EOMONTH(AM$4,0)),Assumptions!$F$4:$F$44))/NETWORKDAYS($K13,$L13,Assumptions!$F$4:$F$44)) -> 0.055 | ... BC13: =IF($J13=0,0,MAX(0,NETWORKDAYS(MAX($K13,BC$4),MIN($L13,EOMONTH(BC$4,0)),Assumptions!$F$4:$F$44))/NETWORKDAYS($K13,$L13,Assumptions!$F$4:$F$44)) -> 0
A14: 10 | B14: 1.2.2 | C14: 3 | D14: Subtask | E14: Quality audits and phase-gate reviews (4 gates) | F14: All | H14: PM | I14: 100 | J14: 300 | K14: =WORKDAY(Assumptions!$C$4,I14,Assumptions!$F$4:$F$44) -> 46468 | L14: =IF(J14=0,K14,WORKDAY(K14,J14-1,Assumptions!$F$4:$F$44)) -> 46885 | N14: 12 | O14: 0 | P14: 8 | Q14: 0 | R14: 0 | S14: 0 | T14: 0 | U14: 0 | V14: 8 | W14: 0 | X14: 0 | Y14: =SUM(N14:X14) -> 28 | Z14: =Y14*(1+Assumptions!$C$5) -> 32.2 | AA14: Gate review reports | AB14: Not started | AD14: 0 | AF14: =IF($J14=0,0,MAX(0,NETWORKDAYS(MAX($K14,AF$4),MIN($L14,EOMONTH(AF$4,0)),Assumptions!$F$4:$F$44))/NETWORKDAYS($K14,$L14,Assumptions!$F$4:$F$44)) -> 0 | AG14: =IF($J14=0,0,MAX(0,NETWORKDAYS(MAX($K14,AG$4),MIN($L14,EOMONTH(AG$4,0)),Assumptions!$F$4:$F$44))/NETWORKDAYS($K14,$L14,Assumptions!$F$4:$F$44)) -> 0 | AH14: =IF($J14=0,0,MAX(0,NETWORKDAYS(MAX($K14,AH$4),MIN($L14,EOMONTH(AH$4,0)),Assumptions!$F$4:$F$44))/NETWORKDAYS($K14,$L14,Assumptions!$F$4:$F$44)) -> 0 | AI14: =IF($J14=0,0,MAX(0,NETWORKDAYS(MAX($K14,AI$4),MIN($L14,EOMONTH(AI$4,0)),Assumptions!$F$4:$F$44))/NETWORKDAYS($K14,$L14,Assumptions!$F$4:$F$44)) -> 0 | AJ14: =IF($J14=0,0,MAX(0,NETWORKDAYS(MAX($K14,AJ$4),MIN($L14,EOMONTH(AJ$4,0)),Assumptions!$F$4:$F$44))/NETWORKDAYS($K14,$L14,Assumptions!$F$4:$F$44)) -> 0.026666667 | AK14: =IF($J14=0,0,MAX(0,NETWORKDAYS(MAX($K14,AK$4),MIN($L14,EOMONTH(AK$4,0)),Assumptions!$F$4:$F$44))/NETWORKDAYS($K14,$L14,Assumptions!$F$4:$F$44)) -> 0.073333333 | AL14: =IF($J14=0,0,MAX(0,NETWORKDAYS(MAX($K14,AL$4),MIN($L14,EOMONTH(AL$4,0)),Assumptions!$F$4:$F$44))/NETWORKDAYS($K14,$L14,Assumptions!$F$4:$F$44)) -> 0.07 | AM14: =IF($J14=0,0,MAX(0,NETWORKDAYS(MAX($K14,AM$4),MIN($L14,EOMONTH(AM$4,0)),Assumptions!$F$4:$F$44))/NETWORKDAYS($K14,$L14,Assumptions!$F$4:$F$44)) -> 0.073333333 | ... BC14: =IF($J14=0,0,MAX(0,NETWORKDAYS(MAX($K14,BC$4),MIN($L14,EOMONTH(BC$4,0)),Assumptions!$F$4:$F$44))/NETWORKDAYS($K14,$L14,Assumptions!$F$4:$F$44)) -> 0
A15: 11 | B15: 2 | C15: 1 | D15: Phase | E15: Phase 0: Inception and mobilisation | F15: Phase 0 | J15: =NETWORKDAYS(K15,L15,Assumptions!$F$4:$F$44) -> 26 | K15: =MIN(K16:K27) -> 46328 | L15: =MAX(L16:L27) -> 46363 | N15: =SUMPRODUCT(($C$16:$C$27=3)*(N16:N27)) -> 18 | O15: =SUMPRODUCT(($C$16:$C$27=3)*(O16:O27)) -> 50 | P15: =SUMPRODUCT(($C$16:$C$27=3)*(P16:P27)) -> 30 | Q15: =SUMPRODUCT(($C$16:$C$27=3)*(Q16:Q27)) -> 3 | R15: =SUMPRODUCT(($C$16:$C$27=3)*(R16:R27)) -> 15 | S15: =SUMPRODUCT(($C$16:$C$27=3)*(S16:S27)) -> 0 | T15: =SUMPRODUCT(($C$16:$C$27=3)*(T16:T27)) -> 0 | U15: =SUMPRODUCT(($C$16:$C$27=3)*(U16:U27)) -> 34 | ... X15: =SUMPRODUCT(($C$16:$C$27=3)*(X16:X27)) -> 0 | Y15: =SUM(N15:X15) -> 160 | Z15: =Y15*(1+Assumptions!$C$5) -> 184 | AF15: 0 | AG15: 0 | AH15: 0 | AI15: 0 | AJ15: 0 | AK15: 0 | AL15: 0 | AM15: 0 | AN15: 0 | AO15: 0 | AP15: 0 | AQ15: 0 | AR15: 0 | AS15: 0 | AT15: 0 | AU15: 0 | AV15: 0 | AW15: 0 | AX15: 0 | AY15: 0 | AZ15: 0 | BA15: 0 | BB15: 0 | BC15: 0
A16: 12 | B16: 2.1 | C16: 2 | D16: Task | E16: Mobilisation | F16: Phase 0 | J16: =NETWORKDAYS(K16,L16,Assumptions!$F$4:$F$44) -> 25 | K16: =MIN(K17:K20) -> 46328 | L16: =MAX(L17:L20) -> 46360 | N16: =SUMPRODUCT(($C$17:$C$20=3)*(N17:N20)) -> 11 | O16: =SUMPRODUCT(($C$17:$C$20=3)*(O17:O20)) -> 5 | P16: =SUMPRODUCT(($C$17:$C$20=3)*(P17:P20)) -> 11 | Q16: =SUMPRODUCT(($C$17:$C$20=3)*(Q17:Q20)) -> 0 | R16: =SUMPRODUCT(($C$17:$C$20=3)*(R17:R20)) -> 0 | S16: =SUMPRODUCT(($C$17:$C$20=3)*(S17:S20)) -> 0 | T16: =SUMPRODUCT(($C$17:$C$20=3)*(T17:T20)) -> 0 | U16: =SUMPRODUCT(($C$17:$C$20=3)*(U17:U20)) -> 31 | ... X16: =SUMPRODUCT(($C$17:$C$20=3)*(X17:X20)) -> 0 | Y16: =SUM(N16:X16) -> 58 | Z16: =Y16*(1+Assumptions!$C$5) -> 66.7 | AF16: 0 | AG16: 0 | AH16: 0 | AI16: 0 | AJ16: 0 | AK16: 0 | AL16: 0 | AM16: 0 | AN16: 0 | AO16: 0 | AP16: 0 | AQ16: 0 | AR16: 0 | AS16: 0 | AT16: 0 | AU16: 0 | AV16: 0 | AW16: 0 | AX16: 0 | AY16: 0 | AZ16: 0 | BA16: 0 | BB16: 0 | BC16: 0
A17: 13 | B17: 2.1.1 | C17: 3 | D17: Subtask | E17: Kick-off with GWMC and team onboarding | F17: Phase 0 | H17: PM | I17: 0 | J17: 5 | K17: =WORKDAY(Assumptions!$C$4,I17,Assumptions!$F$4:$F$44) -> 46328 | L17: =IF(J17=0,K17,WORKDAY(K17,J17-1,Assumptions!$F$4:$F$44)) -> 46332 | N17: 5 | O17: 5 | P17: 3 | Q17: 0 | R17: 0 | S17: 0 | T17: 0 | U17: 0 | V17: 0 | W17: 0 | X17: 0 | Y17: =SUM(N17:X17) -> 13 | Z17: =Y17*(1+Assumptions!$C$5) -> 14.95 | AA17: Kick-off deck, project charter | AB17: Not started | AD17: 0 | AF17: =IF($J17=0,0,MAX(0,NETWORKDAYS(MAX($K17,AF$4),MIN($L17,EOMONTH(AF$4,0)),Assumptions!$F$4:$F$44))/NETWORKDAYS($K17,$L17,Assumptions!$F$4:$F$44)) -> 1 | AG17: =IF($J17=0,0,MAX(0,NETWORKDAYS(MAX($K17,AG$4),MIN($L17,EOMONTH(AG$4,0)),Assumptions!$F$4:$F$44))/NETWORKDAYS($K17,$L17,Assumptions!$F$4:$F$44)) -> 0 | AH17: =IF($J17=0,0,MAX(0,NETWORKDAYS(MAX($K17,AH$4),MIN($L17,EOMONTH(AH$4,0)),Assumptions!$F$4:$F$44))/NETWORKDAYS($K17,$L17,Assumptions!$F$4:$F$44)) -> 0 | AI17: =IF($J17=0,0,MAX(0,NETWORKDAYS(MAX($K17,AI$4),MIN($L17,EOMONTH(AI$4,0)),Assumptions!$F$4:$F$44))/NETWORKDAYS($K17,$L17,Assumptions!$F$4:$F$44)) -> 0 | AJ17: =IF($J17=0,0,MAX(0,NETWORKDAYS(MAX($K17,AJ$4),MIN($L17,EOMONTH(AJ$4,0)),Assumptions!$F$4:$F$44))/NETWORKDAYS($K17,$L17,Assumptions!$F$4:$F$44)) -> 0 | AK17: =IF($J17=0,0,MAX(0,NETWORKDAYS(MAX($K17,AK$4),MIN($L17,EOMONTH(AK$4,0)),Assumptions!$F$4:$F$44))/NETWORKDAYS($K17,$L17,Assumptions!$F$4:$F$44)) -> 0 | AL17: =IF($J17=0,0,MAX(0,NETWORKDAYS(MAX($K17,AL$4),MIN($L17,EOMONTH(AL$4,0)),Assumptions!$F$4:$F$44))/NETWORKDAYS($K17,$L17,Assumptions!$F$4:$F$44)) -> 0 | AM17: =IF($J17=0,0,MAX(0,NETWORKDAYS(MAX($K17,AM$4),MIN($L17,EOMONTH(AM$4,0)),Assumptions!$F$4:$F$44))/NETWORKDAYS($K17,$L17,Assumptions!$F$4:$F$44)) -> 0 | ... BC17: =IF($J17=0,0,MAX(0,NETWORKDAYS(MAX($K17,BC$4),MIN($L17,EOMONTH(BC$4,0)),Assumptions!$F$4:$F$44))/NETWORKDAYS($K17,$L17,Assumptions!$F$4:$F$44)) -> 0
A18: 14 | B18: 2.1.2 | C18: 3 | D18: Subtask | E18: Tooling: repositories, CI/CD, tracker, Teams workspace | F18: Phase 0 | H18: DEV | I18: 0 | J18: 10 | K18: =WORKDAY(Assumptions!$C$4,I18,Assumptions!$F$4:$F$44) -> 46328 | L18: =IF(J18=0,K18,WORKDAY(K18,J18-1,Assumptions!$F$4:$F$44)) -> 46339 | N18: 2 | O18: 0 | P18: 3 | Q18: 0 | R18: 0 | S18: 0 | T18: 0 | U18: 10 | V18: 0 | W18: 0 | X18: 0 | Y18: =SUM(N18:X18) -> 15 | Z18: =Y18*(1+Assumptions!$C$5) -> 17.25 | AA18: Working toolchain | AB18: Not started | AD18: 0 | AF18: =IF($J18=0,0,MAX(0,NETWORKDAYS(MAX($K18,AF$4),MIN($L18,EOMONTH(AF$4,0)),Assumptions!$F$4:$F$44))/NETWORKDAYS($K18,$L18,Assumptions!$F$4:$F$44)) -> 1 | AG18: =IF($J18=0,0,MAX(0,NETWORKDAYS(MAX($K18,AG$4),MIN($L18,EOMONTH(AG$4,0)),Assumptions!$F$4:$F$44))/NETWORKDAYS($K18,$L18,Assumptions!$F$4:$F$44)) -> 0 | AH18: =IF($J18=0,0,MAX(0,NETWORKDAYS(MAX($K18,AH$4),MIN($L18,EOMONTH(AH$4,0)),Assumptions!$F$4:$F$44))/NETWORKDAYS($K18,$L18,Assumptions!$F$4:$F$44)) -> 0 | AI18: =IF($J18=0,0,MAX(0,NETWORKDAYS(MAX($K18,AI$4),MIN($L18,EOMONTH(AI$4,0)),Assumptions!$F$4:$F$44))/NETWORKDAYS($K18,$L18,Assumptions!$F$4:$F$44)) -> 0 | AJ18: =IF($J18=0,0,MAX(0,NETWORKDAYS(MAX($K18,AJ$4),MIN($L18,EOMONTH(AJ$4,0)),Assumptions!$F$4:$F$44))/NETWORKDAYS($K18,$L18,Assumptions!$F$4:$F$44)) -> 0 | AK18: =IF($J18=0,0,MAX(0,NETWORKDAYS(MAX($K18,AK$4),MIN($L18,EOMONTH(AK$4,0)),Assumptions!$F$4:$F$44))/NETWORKDAYS($K18,$L18,Assumptions!$F$4:$F$44)) -> 0 | AL18: =IF($J18=0,0,MAX(0,NETWORKDAYS(MAX($K18,AL$4),MIN($L18,EOMONTH(AL$4,0)),Assumptions!$F$4:$F$44))/NETWORKDAYS($K18,$L18,Assumptions!$F$4:$F$44)) -> 0 | AM18: =IF($J18=0,0,MAX(0,NETWORKDAYS(MAX($K18,AM$4),MIN($L18,EOMONTH(AM$4,0)),Assumptions!$F$4:$F$44))/NETWORKDAYS($K18,$L18,Assumptions!$F$4:$F$44)) -> 0 | ... BC18: =IF($J18=0,0,MAX(0,NETWORKDAYS(MAX($K18,BC$4),MIN($L18,EOMONTH(BC$4,0)),Assumptions!$F$4:$F$44))/NETWORKDAYS($K18,$L18,Assumptions!$F$4:$F$44)) -> 0
A19: 15 | B19: 2.1.3 | C19: 3 | D19: Subtask | E19: Dev and test environments provisioned | F19: Phase 0 | H19: DEV | I19: 3 | J19: 15 | K19: =WORKDAY(Assumptions!$C$4,I19,Assumptions!$F$4:$F$44) -> 46331 | L19: =IF(J19=0,K19,WORKDAY(K19,J19-1,Assumptions!$F$4:$F$44)) -> 46351 | N19: 0 | O19: 0 | P19: 3 | Q19: 0 | R19: 0 | S19: 0 | T19: 0 | U19: 15 | V19: 0 | W19: 0 | X19: 0 | Y19: =SUM(N19:X19) -> 18 | Z19: =Y19*(1+Assumptions!$C$5) -> 20.7 | AA19: Dev and test clusters | AB19: Not started | AD19: 0 | AF19: =IF($J19=0,0,MAX(0,NETWORKDAYS(MAX($K19,AF$4),MIN($L19,EOMONTH(AF$4,0)),Assumptions!$F$4:$F$44))/NETWORKDAYS($K19,$L19,Assumptions!$F$4:$F$44)) -> 1 | AG19: =IF($J19=0,0,MAX(0,NETWORKDAYS(MAX($K19,AG$4),MIN($L19,EOMONTH(AG$4,0)),Assumptions!$F$4:$F$44))/NETWORKDAYS($K19,$L19,Assumptions!$F$4:$F$44)) -> 0 | AH19: =IF($J19=0,0,MAX(0,NETWORKDAYS(MAX($K19,AH$4),MIN($L19,EOMONTH(AH$4,0)),Assumptions!$F$4:$F$44))/NETWORKDAYS($K19,$L19,Assumptions!$F$4:$F$44)) -> 0 | AI19: =IF($J19=0,0,MAX(0,NETWORKDAYS(MAX($K19,AI$4),MIN($L19,EOMONTH(AI$4,0)),Assumptions!$F$4:$F$44))/NETWORKDAYS($K19,$L19,Assumptions!$F$4:$F$44)) -> 0 | AJ19: =IF($J19=0,0,MAX(0,NETWORKDAYS(MAX($K19,AJ$4),MIN($L19,EOMONTH(AJ$4,0)),Assumptions!$F$4:$F$44))/NETWORKDAYS($K19,$L19,Assumptions!$F$4:$F$44)) -> 0 | AK19: =IF($J19=0,0,MAX(0,NETWORKDAYS(MAX($K19,AK$4),MIN($L19,EOMONTH(AK$4,0)),Assumptions!$F$4:$F$44))/NETWORKDAYS($K19,$L19,Assumptions!$F$4:$F$44)) -> 0 | AL19: =IF($J19=0,0,MAX(0,NETWORKDAYS(MAX($K19,AL$4),MIN($L19,EOMONTH(AL$4,0)),Assumptions!$F$4:$F$44))/NETWORKDAYS($K19,$L19,Assumptions!$F$4:$F$44)) -> 0 | AM19: =IF($J19=0,0,MAX(0,NETWORKDAYS(MAX($K19,AM$4),MIN($L19,EOMONTH(AM$4,0)),Assumptions!$F$4:$F$44))/NETWORKDAYS($K19,$L19,Assumptions!$F$4:$F$44)) -> 0 | ... BC19: =IF($J19=0,0,MAX(0,NETWORKDAYS(MAX($K19,BC$4),MIN($L19,EOMONTH(BC$4,0)),Assumptions!$F$4:$F$44))/NETWORKDAYS($K19,$L19,Assumptions!$F$4:$F$44)) -> 0
A20: 16 | B20: 2.1.4 | C20: 3 | D20: Subtask | E20: State Data Centre slot request and network approvals | F20: Phase 0 | H20: PM | I20: 0 | J20: 25 | K20: =WORKDAY(Assumptions!$C$4,I20,Assumptions!$F$4:$F$44) -> 46328 | L20: =IF(J20=0,K20,WORKDAY(K20,J20-1,Assumptions!$F$4:$F$44)) -> 46360 | N20: 4 | O20: 0 | P20: 2 | Q20: 0 | R20: 0 | S20: 0 | T20: 0 | U20: 6 | V20: 0 | W20: 0 | X20: 0 | Y20: =SUM(N20:X20) -> 12 | Z20: =Y20*(1+Assumptions!$C$5) -> 13.8 | AA20: SDC allocation letter | AB20: Not started | AD20: 0 | AF20: =IF($J20=0,0,MAX(0,NETWORKDAYS(MAX($K20,AF$4),MIN($L20,EOMONTH(AF$4,0)),Assumptions!$F$4:$F$44))/NETWORKDAYS($K20,$L20,Assumptions!$F$4:$F$44)) -> 0.84 | AG20: =IF($J20=0,0,MAX(0,NETWORKDAYS(MAX($K20,AG$4),MIN($L20,EOMONTH(AG$4,0)),Assumptions!$F$4:$F$44))/NETWORKDAYS($K20,$L20,Assumptions!$F$4:$F$44)) -> 0.16 | AH20: =IF($J20=0,0,MAX(0,NETWORKDAYS(MAX($K20,AH$4),MIN($L20,EOMONTH(AH$4,0)),Assumptions!$F$4:$F$44))/NETWORKDAYS($K20,$L20,Assumptions!$F$4:$F$44)) -> 0 | AI20: =IF($J20=0,0,MAX(0,NETWORKDAYS(MAX($K20,AI$4),MIN($L20,EOMONTH(AI$4,0)),Assumptions!$F$4:$F$44))/NETWORKDAYS($K20,$L20,Assumptions!$F$4:$F$44)) -> 0 | AJ20: =IF($J20=0,0,MAX(0,NETWORKDAYS(MAX($K20,AJ$4),MIN($L20,EOMONTH(AJ$4,0)),Assumptions!$F$4:$F$44))/NETWORKDAYS($K20,$L20,Assumptions!$F$4:$F$44)) -> 0 | AK20: =IF($J20=0,0,MAX(0,NETWORKDAYS(MAX($K20,AK$4),MIN($L20,EOMONTH(AK$4,0)),Assumptions!$F$4:$F$44))/NETWORKDAYS($K20,$L20,Assumptions!$F$4:$F$44)) -> 0 | AL20: =IF($J20=0,0,MAX(0,NETWORKDAYS(MAX($K20,AL$4),MIN($L20,EOMONTH(AL$4,0)),Assumptions!$F$4:$F$44))/NETWORKDAYS($K20,$L20,Assumptions!$F$4:$F$44)) -> 0 | AM20: =IF($J20=0,0,MAX(0,NETWORKDAYS(MAX($K20,AM$4),MIN($L20,EOMONTH(AM$4,0)),Assumptions!$F$4:$F$44))/NETWORKDAYS($K20,$L20,Assumptions!$F$4:$F$44)) -> 0 | ... BC20: =IF($J20=0,0,MAX(0,NETWORKDAYS(MAX($K20,BC$4),MIN($L20,EOMONTH(BC$4,0)),Assumptions!$F$4:$F$44))/NETWORKDAYS($K20,$L20,Assumptions!$F$4:$F$44)) -> 0
A21: 17 | B21: 2.2 | C21: 2 | D21: Task | E21: Requirements and design baseline | F21: Phase 0 | J21: =NETWORKDAYS(K21,L21,Assumptions!$F$4:$F$44) -> 20 | K21: =MIN(K22:K26) -> 46335 | L21: =MAX(L22:L26) -> 46360 | N21: =SUMPRODUCT(($C$22:$C$26=3)*(N22:N26)) -> 7 | O21: =SUMPRODUCT(($C$22:$C$26=3)*(O22:O26)) -> 45 | P21: =SUMPRODUCT(($C$22:$C$26=3)*(P22:P26)) -> 19 | Q21: =SUMPRODUCT(($C$22:$C$26=3)*(Q22:Q26)) -> 3 | R21: =SUMPRODUCT(($C$22:$C$26=3)*(R22:R26)) -> 15 | S21: =SUMPRODUCT(($C$22:$C$26=3)*(S22:S26)) -> 0 | T21: =SUMPRODUCT(($C$22:$C$26=3)*(T22:T26)) -> 0 | U21: =SUMPRODUCT(($C$22:$C$26=3)*(U22:U26)) -> 3 | ... X21: =SUMPRODUCT(($C$22:$C$26=3)*(X22:X26)) -> 0 | Y21: =SUM(N21:X21) -> 102 | Z21: =Y21*(1+Assumptions!$C$5) -> 117.3 | AF21: 0 | AG21: 0 | AH21: 0 | AI21: 0 | AJ21: 0 | AK21: 0 | AL21: 0 | AM21: 0 | AN21: 0 | AO21: 0 | AP21: 0 | AQ21: 0 | AR21: 0 | AS21: 0 | AT21: 0 | AU21: 0 | AV21: 0 | AW21: 0 | AX21: 0 | AY21: 0 | AZ21: 0 | BA21: 0 | BB21: 0 | BC21: 0
A22: 18 | B22: 2.2.1 | C22: 3 | D22: Subtask | E22: SRS walkthroughs with GWMC departments (Phase 1 modules) | F22: Phase 0 | H22: BA | I22: 5 | J22: 15 | K22: =WORKDAY(Assumptions!$C$4,I22,Assumptions!$F$4:$F$44) -> 46335 | L22: =IF(J22=0,K22,WORKDAY(K22,J22-1,Assumptions!$F$4:$F$44)) -> 46353 | M22: 13 | N22: 4 | O22: 25 | P22: 5 | Q22: 0 | R22: 0 | S22: 0 | T22: 0 | U22: 0 | V22: 0 | W22: 0 | X22: 0 | Y22: =SUM(N22:X22) -> 34 | Z22: =Y22*(1+Assumptions!$C$5) -> 39.1 | AA22: Workshop minutes, clarifications | AB22: Not started | AD22: 0 | AF22: =IF($J22=0,0,MAX(0,NETWORKDAYS(MAX($K22,AF$4),MIN($L22,EOMONTH(AF$4,0)),Assumptions!$F$4:$F$44))/NETWORKDAYS($K22,$L22,Assumptions!$F$4:$F$44)) -> 1 | AG22: =IF($J22=0,0,MAX(0,NETWORKDAYS(MAX($K22,AG$4),MIN($L22,EOMONTH(AG$4,0)),Assumptions!$F$4:$F$44))/NETWORKDAYS($K22,$L22,Assumptions!$F$4:$F$44)) -> 0 | AH22: =IF($J22=0,0,MAX(0,NETWORKDAYS(MAX($K22,AH$4),MIN($L22,EOMONTH(AH$4,0)),Assumptions!$F$4:$F$44))/NETWORKDAYS($K22,$L22,Assumptions!$F$4:$F$44)) -> 0 | AI22: =IF($J22=0,0,MAX(0,NETWORKDAYS(MAX($K22,AI$4),MIN($L22,EOMONTH(AI$4,0)),Assumptions!$F$4:$F$44))/NETWORKDAYS($K22,$L22,Assumptions!$F$4:$F$44)) -> 0 | AJ22: =IF($J22=0,0,MAX(0,NETWORKDAYS(MAX($K22,AJ$4),MIN($L22,EOMONTH(AJ$4,0)),Assumptions!$F$4:$F$44))/NETWORKDAYS($K22,$L22,Assumptions!$F$4:$F$44)) -> 0 | AK22: =IF($J22=0,0,MAX(0,NETWORKDAYS(MAX($K22,AK$4),MIN($L22,EOMONTH(AK$4,0)),Assumptions!$F$4:$F$44))/NETWORKDAYS($K22,$L22,Assumptions!$F$4:$F$44)) -> 0 | AL22: =IF($J22=0,0,MAX(0,NETWORKDAYS(MAX($K22,AL$4),MIN($L22,EOMONTH(AL$4,0)),Assumptions!$F$4:$F$44))/NETWORKDAYS($K22,$L22,Assumptions!$F$4:$F$44)) -> 0 | AM22: =IF($J22=0,0,MAX(0,NETWORKDAYS(MAX($K22,AM$4),MIN($L22,EOMONTH(AM$4,0)),Assumptions!$F$4:$F$44))/NETWORKDAYS($K22,$L22,Assumptions!$F$4:$F$44)) -> 0 | ... BC22: =IF($J22=0,0,MAX(0,NETWORKDAYS(MAX($K22,BC$4),MIN($L22,EOMONTH(BC$4,0)),Assumptions!$F$4:$F$44))/NETWORKDAYS($K22,$L22,Assumptions!$F$4:$F$44)) -> 0
A23: 19 | B23: 2.2.2 | C23: 3 | D23: Subtask | E23: GWMC Deployment SRS open items closed for Phase 1 | F23: Phase 0 | H23: BA | I23: 10 | J23: 15 | K23: =WORKDAY(Assumptions!$C$4,I23,Assumptions!$F$4:$F$44) -> 46342 | L23: =IF(J23=0,K23,WORKDAY(K23,J23-1,Assumptions!$F$4:$F$44)) -> 46360 | N23: 3 | O23: 12 | P23: 0 | Q23: 0 | R23: 0 | S23: 0 | T23: 0 | U23: 0 | V23: 0 | W23: 0 | X23: 0 | Y23: =SUM(N23:X23) -> 15 | Z23: =Y23*(1+Assumptions!$C$5) -> 17.25 | AA23: Signed open-items list | AB23: Not started | AD23: 0 | AF23: =IF($J23=0,0,MAX(0,NETWORKDAYS(MAX($K23,AF$4),MIN($L23,EOMONTH(AF$4,0)),Assumptions!$F$4:$F$44))/NETWORKDAYS($K23,$L23,Assumptions!$F$4:$F$44)) -> 0.73333333 | AG23: =IF($J23=0,0,MAX(0,NETWORKDAYS(MAX($K23,AG$4),MIN($L23,EOMONTH(AG$4,0)),Assumptions!$F$4:$F$44))/NETWORKDAYS($K23,$L23,Assumptions!$F$4:$F$44)) -> 0.26666667 | AH23: =IF($J23=0,0,MAX(0,NETWORKDAYS(MAX($K23,AH$4),MIN($L23,EOMONTH(AH$4,0)),Assumptions!$F$4:$F$44))/NETWORKDAYS($K23,$L23,Assumptions!$F$4:$F$44)) -> 0 | AI23: =IF($J23=0,0,MAX(0,NETWORKDAYS(MAX($K23,AI$4),MIN($L23,EOMONTH(AI$4,0)),Assumptions!$F$4:$F$44))/NETWORKDAYS($K23,$L23,Assumptions!$F$4:$F$44)) -> 0 | AJ23: =IF($J23=0,0,MAX(0,NETWORKDAYS(MAX($K23,AJ$4),MIN($L23,EOMONTH(AJ$4,0)),Assumptions!$F$4:$F$44))/NETWORKDAYS($K23,$L23,Assumptions!$F$4:$F$44)) -> 0 | AK23: =IF($J23=0,0,MAX(0,NETWORKDAYS(MAX($K23,AK$4),MIN($L23,EOMONTH(AK$4,0)),Assumptions!$F$4:$F$44))/NETWORKDAYS($K23,$L23,Assumptions!$F$4:$F$44)) -> 0 | AL23: =IF($J23=0,0,MAX(0,NETWORKDAYS(MAX($K23,AL$4),MIN($L23,EOMONTH(AL$4,0)),Assumptions!$F$4:$F$44))/NETWORKDAYS($K23,$L23,Assumptions!$F$4:$F$44)) -> 0 | AM23: =IF($J23=0,0,MAX(0,NETWORKDAYS(MAX($K23,AM$4),MIN($L23,EOMONTH(AM$4,0)),Assumptions!$F$4:$F$44))/NETWORKDAYS($K23,$L23,Assumptions!$F$4:$F$44)) -> 0 | ... BC23: =IF($J23=0,0,MAX(0,NETWORKDAYS(MAX($K23,BC$4),MIN($L23,EOMONTH(BC$4,0)),Assumptions!$F$4:$F$44))/NETWORKDAYS($K23,$L23,Assumptions!$F$4:$F$44)) -> 0
A24: 20 | B24: 2.2.3 | C24: 3 | D24: Subtask | E24: Architecture decisions (ADR-001 to 016) reviewed and signed off | F24: Phase 0 | H24: ARC | I24: 5 | J24: 15 | K24: =WORKDAY(Assumptions!$C$4,I24,Assumptions!$F$4:$F$44) -> 46335 | L24: =IF(J24=0,K24,WORKDAY(K24,J24-1,Assumptions!$F$4:$F$44)) -> 46353 | N24: 0 | O24: 0 | P24: 12 | Q24: 3 | R24: 0 | S24: 0 | T24: 0 | U24: 3 | V24: 0 | W24: 0 | X24: 0 | Y24: =SUM(N24:X24) -> 18 | Z24: =Y24*(1+Assumptions!$C$5) -> 20.7 | AA24: Signed ADRs | AB24: Not started | AD24: 0 | AF24: =IF($J24=0,0,MAX(0,NETWORKDAYS(MAX($K24,AF$4),MIN($L24,EOMONTH(AF$4,0)),Assumptions!$F$4:$F$44))/NETWORKDAYS($K24,$L24,Assumptions!$F$4:$F$44)) -> 1 | AG24: =IF($J24=0,0,MAX(0,NETWORKDAYS(MAX($K24,AG$4),MIN($L24,EOMONTH(AG$4,0)),Assumptions!$F$4:$F$44))/NETWORKDAYS($K24,$L24,Assumptions!$F$4:$F$44)) -> 0 | AH24: =IF($J24=0,0,MAX(0,NETWORKDAYS(MAX($K24,AH$4),MIN($L24,EOMONTH(AH$4,0)),Assumptions!$F$4:$F$44))/NETWORKDAYS($K24,$L24,Assumptions!$F$4:$F$44)) -> 0 | AI24: =IF($J24=0,0,MAX(0,NETWORKDAYS(MAX($K24,AI$4),MIN($L24,EOMONTH(AI$4,0)),Assumptions!$F$4:$F$44))/NETWORKDAYS($K24,$L24,Assumptions!$F$4:$F$44)) -> 0 | AJ24: =IF($J24=0,0,MAX(0,NETWORKDAYS(MAX($K24,AJ$4),MIN($L24,EOMONTH(AJ$4,0)),Assumptions!$F$4:$F$44))/NETWORKDAYS($K24,$L24,Assumptions!$F$4:$F$44)) -> 0 | AK24: =IF($J24=0,0,MAX(0,NETWORKDAYS(MAX($K24,AK$4),MIN($L24,EOMONTH(AK$4,0)),Assumptions!$F$4:$F$44))/NETWORKDAYS($K24,$L24,Assumptions!$F$4:$F$44)) -> 0 | AL24: =IF($J24=0,0,MAX(0,NETWORKDAYS(MAX($K24,AL$4),MIN($L24,EOMONTH(AL$4,0)),Assumptions!$F$4:$F$44))/NETWORKDAYS($K24,$L24,Assumptions!$F$4:$F$44)) -> 0 | AM24: =IF($J24=0,0,MAX(0,NETWORKDAYS(MAX($K24,AM$4),MIN($L24,EOMONTH(AM$4,0)),Assumptions!$F$4:$F$44))/NETWORKDAYS($K24,$L24,Assumptions!$F$4:$F$44)) -> 0 | ... BC24: =IF($J24=0,0,MAX(0,NETWORKDAYS(MAX($K24,BC$4),MIN($L24,EOMONTH(BC$4,0)),Assumptions!$F$4:$F$44))/NETWORKDAYS($K24,$L24,Assumptions!$F$4:$F$44)) -> 0
A25: 21 | B25: 2.2.4 | C25: 3 | D25: Subtask | E25: UX research, design system and accessibility baseline | F25: Phase 0 | H25: FE | I25: 5 | J25: 20 | K25: =WORKDAY(Assumptions!$C$4,I25,Assumptions!$F$4:$F$44) -> 46335 | L25: =IF(J25=0,K25,WORKDAY(K25,J25-1,Assumptions!$F$4:$F$44)) -> 46360 | N25: 0 | O25: 4 | P25: 0 | Q25: 0 | R25: 15 | S25: 0 | T25: 0 | U25: 0 | V25: 0 | W25: 0 | X25: 0 | Y25: =SUM(N25:X25) -> 19 | Z25: =Y25*(1+Assumptions!$C$5) -> 21.85 | AA25: Design system, UI kit, GIGW checklist | AB25: Not started | AD25: 0 | AF25: =IF($J25=0,0,MAX(0,NETWORKDAYS(MAX($K25,AF$4),MIN($L25,EOMONTH(AF$4,0)),Assumptions!$F$4:$F$44))/NETWORKDAYS($K25,$L25,Assumptions!$F$4:$F$44)) -> 0.8 | AG25: =IF($J25=0,0,MAX(0,NETWORKDAYS(MAX($K25,AG$4),MIN($L25,EOMONTH(AG$4,0)),Assumptions!$F$4:$F$44))/NETWORKDAYS($K25,$L25,Assumptions!$F$4:$F$44)) -> 0.2 | AH25: =IF($J25=0,0,MAX(0,NETWORKDAYS(MAX($K25,AH$4),MIN($L25,EOMONTH(AH$4,0)),Assumptions!$F$4:$F$44))/NETWORKDAYS($K25,$L25,Assumptions!$F$4:$F$44)) -> 0 | AI25: =IF($J25=0,0,MAX(0,NETWORKDAYS(MAX($K25,AI$4),MIN($L25,EOMONTH(AI$4,0)),Assumptions!$F$4:$F$44))/NETWORKDAYS($K25,$L25,Assumptions!$F$4:$F$44)) -> 0 | AJ25: =IF($J25=0,0,MAX(0,NETWORKDAYS(MAX($K25,AJ$4),MIN($L25,EOMONTH(AJ$4,0)),Assumptions!$F$4:$F$44))/NETWORKDAYS($K25,$L25,Assumptions!$F$4:$F$44)) -> 0 | AK25: =IF($J25=0,0,MAX(0,NETWORKDAYS(MAX($K25,AK$4),MIN($L25,EOMONTH(AK$4,0)),Assumptions!$F$4:$F$44))/NETWORKDAYS($K25,$L25,Assumptions!$F$4:$F$44)) -> 0 | AL25: =IF($J25=0,0,MAX(0,NETWORKDAYS(MAX($K25,AL$4),MIN($L25,EOMONTH(AL$4,0)),Assumptions!$F$4:$F$44))/NETWORKDAYS($K25,$L25,Assumptions!$F$4:$F$44)) -> 0 | AM25: =IF($J25=0,0,MAX(0,NETWORKDAYS(MAX($K25,AM$4),MIN($L25,EOMONTH(AM$4,0)),Assumptions!$F$4:$F$44))/NETWORKDAYS($K25,$L25,Assumptions!$F$4:$F$44)) -> 0 | ... BC25: =IF($J25=0,0,MAX(0,NETWORKDAYS(MAX($K25,BC$4),MIN($L25,EOMONTH(BC$4,0)),Assumptions!$F$4:$F$44))/NETWORKDAYS($K25,$L25,Assumptions!$F$4:$F$44)) -> 0
A26: 22 | B26: 2.2.5 | C26: 3 | D26: Subtask | E26: Data migration strategy and legacy data assessment | F26: Phase 0 | H26: DATA | I26: 10 | J26: 15 | K26: =WORKDAY(Assumptions!$C$4,I26,Assumptions!$F$4:$F$44) -> 46342 | L26: =IF(J26=0,K26,WORKDAY(K26,J26-1,Assumptions!$F$4:$F$44)) -> 46360 | N26: 0 | O26: 4 | P26: 2 | Q26: 0 | R26: 0 | S26: 0 | T26: 0 | U26: 0 | V26: 0 | W26: 10 | X26: 0 | Y26: =SUM(N26:X26) -> 16 | Z26: =Y26*(1+Assumptions!$C$5) -> 18.4 | AA26: Migration strategy | AB26: Not started | AD26: 0 | AF26: =IF($J26=0,0,MAX(0,NETWORKDAYS(MAX($K26,AF$4),MIN($L26,EOMONTH(AF$4,0)),Assumptions!$F$4:$F$44))/NETWORKDAYS($K26,$L26,Assumptions!$F$4:$F$44)) -> 0.73333333 | AG26: =IF($J26=0,0,MAX(0,NETWORKDAYS(MAX($K26,AG$4),MIN($L26,EOMONTH(AG$4,0)),Assumptions!$F$4:$F$44))/NETWORKDAYS($K26,$L26,Assumptions!$F$4:$F$44)) -> 0.26666667 | AH26: =IF($J26=0,0,MAX(0,NETWORKDAYS(MAX($K26,AH$4),MIN($L26,EOMONTH(AH$4,0)),Assumptions!$F$4:$F$44))/NETWORKDAYS($K26,$L26,Assumptions!$F$4:$F$44)) -> 0 | AI26: =IF($J26=0,0,MAX(0,NETWORKDAYS(MAX($K26,AI$4),MIN($L26,EOMONTH(AI$4,0)),Assumptions!$F$4:$F$44))/NETWORKDAYS($K26,$L26,Assumptions!$F$4:$F$44)) -> 0 | AJ26: =IF($J26=0,0,MAX(0,NETWORKDAYS(MAX($K26,AJ$4),MIN($L26,EOMONTH(AJ$4,0)),Assumptions!$F$4:$F$44))/NETWORKDAYS($K26,$L26,Assumptions!$F$4:$F$44)) -> 0 | AK26: =IF($J26=0,0,MAX(0,NETWORKDAYS(MAX($K26,AK$4),MIN($L26,EOMONTH(AK$4,0)),Assumptions!$F$4:$F$44))/NETWORKDAYS($K26,$L26,Assumptions!$F$4:$F$44)) -> 0 | AL26: =IF($J26=0,0,MAX(0,NETWORKDAYS(MAX($K26,AL$4),MIN($L26,EOMONTH(AL$4,0)),Assumptions!$F$4:$F$44))/NETWORKDAYS($K26,$L26,Assumptions!$F$4:$F$44)) -> 0 | AM26: =IF($J26=0,0,MAX(0,NETWORKDAYS(MAX($K26,AM$4),MIN($L26,EOMONTH(AM$4,0)),Assumptions!$F$4:$F$44))/NETWORKDAYS($K26,$L26,Assumptions!$F$4:$F$44)) -> 0 | ... BC26: =IF($J26=0,0,MAX(0,NETWORKDAYS(MAX($K26,BC$4),MIN($L26,EOMONTH(BC$4,0)),Assumptions!$F$4:$F$44))/NETWORKDAYS($K26,$L26,Assumptions!$F$4:$F$44)) -> 0
A27: 23 | B27: 2.3 | C27: 2 | D27: Milestone | E27: M0: Inception complete, Phase 1 build starts | F27: Phase 0 | I27: 25 | J27: 0 | K27: =WORKDAY(Assumptions!$C$4,I27,Assumptions!$F$4:$F$44) -> 46363 | L27: =IF(J27=0,K27,WORKDAY(K27,J27-1,Assumptions!$F$4:$F$44)) -> 46363 | M27: 18,20 | N27: 0 | O27: 0 | P27: 0 | Q27: 0 | R27: 0 | S27: 0 | T27: 0 | U27: 0 | V27: 0 | W27: 0 | X27: 0 | Y27: =SUM(N27:X27) -> 0 | Z27: =Y27*(1+Assumptions!$C$5) -> 0 | AB27: Not started | AD27: 0 | AF27: 0 | AG27: 0 | AH27: 0 | AI27: 0 | AJ27: 0 | AK27: 0 | AL27: 0 | AM27: 0 | AN27: 0 | AO27: 0 | AP27: 0 | AQ27: 0 | AR27: 0 | AS27: 0 | AT27: 0 | AU27: 0 | AV27: 0 | AW27: 0 | AX27: 0 | AY27: 0 | AZ27: 0 | BA27: 0 | BB27: 0 | BC27: 0
A28: 24 | B28: 3 | C28: 1 | D28: Phase | E28: Platform foundation (built in Phase 1) | F28: Phase 1 | J28: =NETWORKDAYS(K28,L28,Assumptions!$F$4:$F$44) -> 84 | K28: =MIN(K29:K105) -> 46342 | L28: =MAX(L29:L105) -> 46457 | N28: =SUMPRODUCT(($C$29:$C$105=3)*(N29:N105)) -> 0 | O28: =SUMPRODUCT(($C$29:$C$105=3)*(O29:O105)) -> 15 | P28: =SUMPRODUCT(($C$29:$C$105=3)*(P29:P105)) -> 56 | Q28: =SUMPRODUCT(($C$29:$C$105=3)*(Q29:Q105)) -> 320 | R28: =SUMPRODUCT(($C$29:$C$105=3)*(R29:R105)) -> 97 | S28: =SUMPRODUCT(($C$29:$C$105=3)*(S29:S105)) -> 49 | T28: =SUMPRODUCT(($C$29:$C$105=3)*(T29:T105)) -> 32 | U28: =SUMPRODUCT(($C$29:$C$105=3)*(U29:U105)) -> 95 | ... X28: =SUMPRODUCT(($C$29:$C$105=3)*(X29:X105)) -> 0 | Y28: =SUM(N28:X28) -> 785 | Z28: =Y28*(1+Assumptions!$C$5) -> 902.75 | AF28: 0 | AG28: 0 | AH28: 0 | AI28: 0 | AJ28: 0 | AK28: 0 | AL28: 0 | AM28: 0 | AN28: 0 | AO28: 0 | AP28: 0 | AQ28: 0 | AR28: 0 | AS28: 0 | AT28: 0 | AU28: 0 | AV28: 0 | AW28: 0 | AX28: 0 | AY28: 0 | AZ28: 0 | BA28: 0 | BB28: 0 | BC28: 0
A29: 25 | B29: 3.1 | C29: 2 | D29: Task | E29: Identity, OTP, CAPTCHA and step-up (Keycloak) | F29: Phase 1 | G29: Platform | J29: =NETWORKDAYS(K29,L29,Assumptions!$F$4:$F$44) -> 51 | K29: =MIN(K30:K32) -> 46342 | L29: =MAX(L30:L32) -> 46412 | N29: =SUMPRODUCT(($C$30:$C$32=3)*(N30:N32)) -> 0 | O29: =SUMPRODUCT(($C$30:$C$32=3)*(O30:O32)) -> 0 | P29: =SUMPRODUCT(($C$30:$C$32=3)*(P30:P32)) -> 4 | Q29: =SUMPRODUCT(($C$30:$C$32=3)*(Q30:Q32)) -> 33 | R29: =SUMPRODUCT(($C$30:$C$32=3)*(R30:R32)) -> 7 | S29: =SUMPRODUCT(($C$30:$C$32=3)*(S30:S32)) -> 0 | T29: =SUMPRODUCT(($C$30:$C$32=3)*(T30:T32)) -> 0 | U29: =SUMPRODUCT(($C$30:$C$32=3)*(U30:U32)) -> 4 | ... X29: =SUMPRODUCT(($C$30:$C$32=3)*(X30:X32)) -> 0 | Y29: =SUM(N29:X29) -> 58 | Z29: =Y29*(1+Assumptions!$C$5) -> 66.7 | AA29: PLT-FR-001, 026, 028 to 032 | AF29: 0 | AG29: 0 | AH29: 0 | AI29: 0 | AJ29: 0 | AK29: 0 | AL29: 0 | AM29: 0 | AN29: 0 | AO29: 0 | AP29: 0 | AQ29: 0 | AR29: 0 | AS29: 0 | AT29: 0 | AU29: 0 | AV29: 0 | AW29: 0 | AX29: 0 | AY29: 0 | AZ29: 0 | BA29: 0 | BB29: 0 | BC29: 0
A30: 26 | B30: 3.1.1 | C30: 3 | D30: Subtask | E30: Detailed design and contracts | F30: Phase 1 | G30: Platform | H30: ARC | I30: 10 | J30: 10 | K30: =WORKDAY(Assumptions!$C$4,I30,Assumptions!$F$4:$F$44) -> 46342 | L30: =IF(J30=0,K30,WORKDAY(K30,J30-1,Assumptions!$F$4:$F$44)) -> 46353 | M30: 20 | N30: 0 | O30: 0 | P30: 4 | Q30: 3 | R30: 0 | S30: 0 | T30: 0 | U30: 0 | V30: 0 | W30: 0 | X30: 0 | Y30: =SUM(N30:X30) -> 7 | Z30: =Y30*(1+Assumptions!$C$5) -> 8.05 | AA30: Design note, OpenAPI and event schemas | AB30: Not started | AD30: 0 | AF30: =IF($J30=0,0,MAX(0,NETWORKDAYS(MAX($K30,AF$4),MIN($L30,EOMONTH(AF$4,0)),Assumptions!$F$4:$F$44))/NETWORKDAYS($K30,$L30,Assumptions!$F$4:$F$44)) -> 1 | AG30: =IF($J30=0,0,MAX(0,NETWORKDAYS(MAX($K30,AG$4),MIN($L30,EOMONTH(AG$4,0)),Assumptions!$F$4:$F$44))/NETWORKDAYS($K30,$L30,Assumptions!$F$4:$F$44)) -> 0 | AH30: =IF($J30=0,0,MAX(0,NETWORKDAYS(MAX($K30,AH$4),MIN($L30,EOMONTH(AH$4,0)),Assumptions!$F$4:$F$44))/NETWORKDAYS($K30,$L30,Assumptions!$F$4:$F$44)) -> 0 | AI30: =IF($J30=0,0,MAX(0,NETWORKDAYS(MAX($K30,AI$4),MIN($L30,EOMONTH(AI$4,0)),Assumptions!$F$4:$F$44))/NETWORKDAYS($K30,$L30,Assumptions!$F$4:$F$44)) -> 0 | AJ30: =IF($J30=0,0,MAX(0,NETWORKDAYS(MAX($K30,AJ$4),MIN($L30,EOMONTH(AJ$4,0)),Assumptions!$F$4:$F$44))/NETWORKDAYS($K30,$L30,Assumptions!$F$4:$F$44)) -> 0 | AK30: =IF($J30=0,0,MAX(0,NETWORKDAYS(MAX($K30,AK$4),MIN($L30,EOMONTH(AK$4,0)),Assumptions!$F$4:$F$44))/NETWORKDAYS($K30,$L30,Assumptions!$F$4:$F$44)) -> 0 | AL30: =IF($J30=0,0,MAX(0,NETWORKDAYS(MAX($K30,AL$4),MIN($L30,EOMONTH(AL$4,0)),Assumptions!$F$4:$F$44))/NETWORKDAYS($K30,$L30,Assumptions!$F$4:$F$44)) -> 0 | AM30: =IF($J30=0,0,MAX(0,NETWORKDAYS(MAX($K30,AM$4),MIN($L30,EOMONTH(AM$4,0)),Assumptions!$F$4:$F$44))/NETWORKDAYS($K30,$L30,Assumptions!$F$4:$F$44)) -> 0 | ... BC30: =IF($J30=0,0,MAX(0,NETWORKDAYS(MAX($K30,BC$4),MIN($L30,EOMONTH(BC$4,0)),Assumptions!$F$4:$F$44))/NETWORKDAYS($K30,$L30,Assumptions!$F$4:$F$44)) -> 0
A31: 27 | B31: 3.1.2 | C31: 3 | D31: Subtask | E31: Build and unit tests | F31: Phase 1 | G31: Platform | H31: BE | I31: 20 | J31: 30 | K31: =WORKDAY(Assumptions!$C$4,I31,Assumptions!$F$4:$F$44) -> 46356 | L31: =IF(J31=0,K31,WORKDAY(K31,J31-1,Assumptions!$F$4:$F$44)) -> 46395 | N31: 0 | O31: 0 | P31: 0 | Q31: 27 | R31: 7 | S31: 0 | T31: 0 | U31: 4 | V31: 0 | W31: 0 | X31: 0 | Y31: =SUM(N31:X31) -> 38 | Z31: =Y31*(1+Assumptions!$C$5) -> 43.7 | AA31: Working service | AB31: Not started | AD31: 0 | AF31: =IF($J31=0,0,MAX(0,NETWORKDAYS(MAX($K31,AF$4),MIN($L31,EOMONTH(AF$4,0)),Assumptions!$F$4:$F$44))/NETWORKDAYS($K31,$L31,Assumptions!$F$4:$F$44)) -> 0.033333333 | AG31: =IF($J31=0,0,MAX(0,NETWORKDAYS(MAX($K31,AG$4),MIN($L31,EOMONTH(AG$4,0)),Assumptions!$F$4:$F$44))/NETWORKDAYS($K31,$L31,Assumptions!$F$4:$F$44)) -> 0.76666667 | AH31: =IF($J31=0,0,MAX(0,NETWORKDAYS(MAX($K31,AH$4),MIN($L31,EOMONTH(AH$4,0)),Assumptions!$F$4:$F$44))/NETWORKDAYS($K31,$L31,Assumptions!$F$4:$F$44)) -> 0.2 | AI31: =IF($J31=0,0,MAX(0,NETWORKDAYS(MAX($K31,AI$4),MIN($L31,EOMONTH(AI$4,0)),Assumptions!$F$4:$F$44))/NETWORKDAYS($K31,$L31,Assumptions!$F$4:$F$44)) -> 0 | AJ31: =IF($J31=0,0,MAX(0,NETWORKDAYS(MAX($K31,AJ$4),MIN($L31,EOMONTH(AJ$4,0)),Assumptions!$F$4:$F$44))/NETWORKDAYS($K31,$L31,Assumptions!$F$4:$F$44)) -> 0 | AK31: =IF($J31=0,0,MAX(0,NETWORKDAYS(MAX($K31,AK$4),MIN($L31,EOMONTH(AK$4,0)),Assumptions!$F$4:$F$44))/NETWORKDAYS($K31,$L31,Assumptions!$F$4:$F$44)) -> 0 | AL31: =IF($J31=0,0,MAX(0,NETWORKDAYS(MAX($K31,AL$4),MIN($L31,EOMONTH(AL$4,0)),Assumptions!$F$4:$F$44))/NETWORKDAYS($K31,$L31,Assumptions!$F$4:$F$44)) -> 0 | AM31: =IF($J31=0,0,MAX(0,NETWORKDAYS(MAX($K31,AM$4),MIN($L31,EOMONTH(AM$4,0)),Assumptions!$F$4:$F$44))/NETWORKDAYS($K31,$L31,Assumptions!$F$4:$F$44)) -> 0 | ... BC31: =IF($J31=0,0,MAX(0,NETWORKDAYS(MAX($K31,BC$4),MIN($L31,EOMONTH(BC$4,0)),Assumptions!$F$4:$F$44))/NETWORKDAYS($K31,$L31,Assumptions!$F$4:$F$44)) -> 0
A32: 28 | B32: 3.1.3 | C32: 3 | D32: Subtask | E32: Component, security and contract tests | F32: Phase 1 | G32: Platform | H32: QA | I32: 48 | J32: 13 | K32: =WORKDAY(Assumptions!$C$4,I32,Assumptions!$F$4:$F$44) -> 46394 | L32: =IF(J32=0,K32,WORKDAY(K32,J32-1,Assumptions!$F$4:$F$44)) -> 46412 | N32: 0 | O32: 0 | P32: 0 | Q32: 3 | R32: 0 | S32: 0 | T32: 0 | U32: 0 | V32: 10 | W32: 0 | X32: 0 | Y32: =SUM(N32:X32) -> 13 | Z32: =Y32*(1+Assumptions!$C$5) -> 14.95 | AA32: Test report | AB32: Not started | AD32: 0 | AF32: =IF($J32=0,0,MAX(0,NETWORKDAYS(MAX($K32,AF$4),MIN($L32,EOMONTH(AF$4,0)),Assumptions!$F$4:$F$44))/NETWORKDAYS($K32,$L32,Assumptions!$F$4:$F$44)) -> 0 | AG32: =IF($J32=0,0,MAX(0,NETWORKDAYS(MAX($K32,AG$4),MIN($L32,EOMONTH(AG$4,0)),Assumptions!$F$4:$F$44))/NETWORKDAYS($K32,$L32,Assumptions!$F$4:$F$44)) -> 0 | AH32: =IF($J32=0,0,MAX(0,NETWORKDAYS(MAX($K32,AH$4),MIN($L32,EOMONTH(AH$4,0)),Assumptions!$F$4:$F$44))/NETWORKDAYS($K32,$L32,Assumptions!$F$4:$F$44)) -> 1 | AI32: =IF($J32=0,0,MAX(0,NETWORKDAYS(MAX($K32,AI$4),MIN($L32,EOMONTH(AI$4,0)),Assumptions!$F$4:$F$44))/NETWORKDAYS($K32,$L32,Assumptions!$F$4:$F$44)) -> 0 | AJ32: =IF($J32=0,0,MAX(0,NETWORKDAYS(MAX($K32,AJ$4),MIN($L32,EOMONTH(AJ$4,0)),Assumptions!$F$4:$F$44))/NETWORKDAYS($K32,$L32,Assumptions!$F$4:$F$44)) -> 0 | AK32: =IF($J32=0,0,MAX(0,NETWORKDAYS(MAX($K32,AK$4),MIN($L32,EOMONTH(AK$4,0)),Assumptions!$F$4:$F$44))/NETWORKDAYS($K32,$L32,Assumptions!$F$4:$F$44)) -> 0 | AL32: =IF($J32=0,0,MAX(0,NETWORKDAYS(MAX($K32,AL$4),MIN($L32,EOMONTH(AL$4,0)),Assumptions!$F$4:$F$44))/NETWORKDAYS($K32,$L32,Assumptions!$F$4:$F$44)) -> 0 | AM32: =IF($J32=0,0,MAX(0,NETWORKDAYS(MAX($K32,AM$4),MIN($L32,EOMONTH(AM$4,0)),Assumptions!$F$4:$F$44))/NETWORKDAYS($K32,$L32,Assumptions!$F$4:$F$44)) -> 0 | ... BC32: =IF($J32=0,0,MAX(0,NETWORKDAYS(MAX($K32,BC$4),MIN($L32,EOMONTH(BC$4,0)),Assumptions!$F$4:$F$44))/NETWORKDAYS($K32,$L32,Assumptions!$F$4:$F$44)) -> 0
A33: 29 | B33: 3.2 | C33: 2 | D33: Task | E33: Tenant, configuration console and Telangana state pack | F33: Phase 1 | G33: Platform | J33: =NETWORKDAYS(K33,L33,Assumptions!$F$4:$F$44) -> 50 | K33: =MIN(K34:K36) -> 46350 | L33: =MAX(L34:L36) -> 46419 | N33: =SUMPRODUCT(($C$34:$C$36=3)*(N34:N36)) -> 0 | O33: =SUMPRODUCT(($C$34:$C$36=3)*(O34:O36)) -> 7 | P33: =SUMPRODUCT(($C$34:$C$36=3)*(P34:P36)) -> 3 | Q33: =SUMPRODUCT(($C$34:$C$36=3)*(Q34:Q36)) -> 26 | R33: =SUMPRODUCT(($C$34:$C$36=3)*(R34:R36)) -> 14 | S33: =SUMPRODUCT(($C$34:$C$36=3)*(S34:S36)) -> 0 | T33: =SUMPRODUCT(($C$34:$C$36=3)*(T34:T36)) -> 0 | U33: =SUMPRODUCT(($C$34:$C$36=3)*(U34:U36)) -> 0 | ... X33: =SUMPRODUCT(($C$34:$C$36=3)*(X34:X36)) -> 0 | Y33: =SUM(N33:X33) -> 58 | Z33: =Y33*(1+Assumptions!$C$5) -> 66.7 | AA33: PLT-FR-015 to 018, 022 | AF33: 0 | AG33: 0 | AH33: 0 | AI33: 0 | AJ33: 0 | AK33: 0 | AL33: 0 | AM33: 0 | AN33: 0 | AO33: 0 | AP33: 0 | AQ33: 0 | AR33: 0 | AS33: 0 | AT33: 0 | AU33: 0 | AV33: 0 | AW33: 0 | AX33: 0 | AY33: 0 | AZ33: 0 | BA33: 0 | BB33: 0 | BC33: 0
A34: 30 | B34: 3.2.1 | C34: 3 | D34: Subtask | E34: Detailed design and contracts | F34: Phase 1 | G34: Platform | H34: ARC | I34: 16 | J34: 10 | K34: =WORKDAY(Assumptions!$C$4,I34,Assumptions!$F$4:$F$44) -> 46350 | L34: =IF(J34=0,K34,WORKDAY(K34,J34-1,Assumptions!$F$4:$F$44)) -> 46363 | M34: 20 | N34: 0 | O34: 0 | P34: 3 | Q34: 2 | R34: 0 | S34: 0 | T34: 0 | U34: 0 | V34: 0 | W34: 0 | X34: 0 | Y34: =SUM(N34:X34) -> 5 | Z34: =Y34*(1+Assumptions!$C$5) -> 5.75 | AA34: Design note, OpenAPI and event schemas | AB34: Not started | AD34: 0 | AF34: =IF($J34=0,0,MAX(0,NETWORKDAYS(MAX($K34,AF$4),MIN($L34,EOMONTH(AF$4,0)),Assumptions!$F$4:$F$44))/NETWORKDAYS($K34,$L34,Assumptions!$F$4:$F$44)) -> 0.5 | AG34: =IF($J34=0,0,MAX(0,NETWORKDAYS(MAX($K34,AG$4),MIN($L34,EOMONTH(AG$4,0)),Assumptions!$F$4:$F$44))/NETWORKDAYS($K34,$L34,Assumptions!$F$4:$F$44)) -> 0.5 | AH34: =IF($J34=0,0,MAX(0,NETWORKDAYS(MAX($K34,AH$4),MIN($L34,EOMONTH(AH$4,0)),Assumptions!$F$4:$F$44))/NETWORKDAYS($K34,$L34,Assumptions!$F$4:$F$44)) -> 0 | AI34: =IF($J34=0,0,MAX(0,NETWORKDAYS(MAX($K34,AI$4),MIN($L34,EOMONTH(AI$4,0)),Assumptions!$F$4:$F$44))/NETWORKDAYS($K34,$L34,Assumptions!$F$4:$F$44)) -> 0 | AJ34: =IF($J34=0,0,MAX(0,NETWORKDAYS(MAX($K34,AJ$4),MIN($L34,EOMONTH(AJ$4,0)),Assumptions!$F$4:$F$44))/NETWORKDAYS($K34,$L34,Assumptions!$F$4:$F$44)) -> 0 | AK34: =IF($J34=0,0,MAX(0,NETWORKDAYS(MAX($K34,AK$4),MIN($L34,EOMONTH(AK$4,0)),Assumptions!$F$4:$F$44))/NETWORKDAYS($K34,$L34,Assumptions!$F$4:$F$44)) -> 0 | AL34: =IF($J34=0,0,MAX(0,NETWORKDAYS(MAX($K34,AL$4),MIN($L34,EOMONTH(AL$4,0)),Assumptions!$F$4:$F$44))/NETWORKDAYS($K34,$L34,Assumptions!$F$4:$F$44)) -> 0 | AM34: =IF($J34=0,0,MAX(0,NETWORKDAYS(MAX($K34,AM$4),MIN($L34,EOMONTH(AM$4,0)),Assumptions!$F$4:$F$44))/NETWORKDAYS($K34,$L34,Assumptions!$F$4:$F$44)) -> 0 | ... BC34: =IF($J34=0,0,MAX(0,NETWORKDAYS(MAX($K34,BC$4),MIN($L34,EOMONTH(BC$4,0)),Assumptions!$F$4:$F$44))/NETWORKDAYS($K34,$L34,Assumptions!$F$4:$F$44)) -> 0
A35: 31 | B35: 3.2.2 | C35: 3 | D35: Subtask | E35: Build and unit tests | F35: Phase 1 | G35: Platform | H35: BE | I35: 26 | J35: 30 | K35: =WORKDAY(Assumptions!$C$4,I35,Assumptions!$F$4:$F$44) -> 46364 | L35: =IF(J35=0,K35,WORKDAY(K35,J35-1,Assumptions!$F$4:$F$44)) -> 46405 | N35: 0 | O35: 7 | P35: 0 | Q35: 22 | R35: 14 | S35: 0 | T35: 0 | U35: 0 | V35: 0 | W35: 0 | X35: 0 | Y35: =SUM(N35:X35) -> 43 | Z35: =Y35*(1+Assumptions!$C$5) -> 49.45 | AA35: Working service | AB35: Not started | AD35: 0 | AF35: =IF($J35=0,0,MAX(0,NETWORKDAYS(MAX($K35,AF$4),MIN($L35,EOMONTH(AF$4,0)),Assumptions!$F$4:$F$44))/NETWORKDAYS($K35,$L35,Assumptions!$F$4:$F$44)) -> 0 | AG35: =IF($J35=0,0,MAX(0,NETWORKDAYS(MAX($K35,AG$4),MIN($L35,EOMONTH(AG$4,0)),Assumptions!$F$4:$F$44))/NETWORKDAYS($K35,$L35,Assumptions!$F$4:$F$44)) -> 0.6 | AH35: =IF($J35=0,0,MAX(0,NETWORKDAYS(MAX($K35,AH$4),MIN($L35,EOMONTH(AH$4,0)),Assumptions!$F$4:$F$44))/NETWORKDAYS($K35,$L35,Assumptions!$F$4:$F$44)) -> 0.4 | AI35: =IF($J35=0,0,MAX(0,NETWORKDAYS(MAX($K35,AI$4),MIN($L35,EOMONTH(AI$4,0)),Assumptions!$F$4:$F$44))/NETWORKDAYS($K35,$L35,Assumptions!$F$4:$F$44)) -> 0 | AJ35: =IF($J35=0,0,MAX(0,NETWORKDAYS(MAX($K35,AJ$4),MIN($L35,EOMONTH(AJ$4,0)),Assumptions!$F$4:$F$44))/NETWORKDAYS($K35,$L35,Assumptions!$F$4:$F$44)) -> 0 | AK35: =IF($J35=0,0,MAX(0,NETWORKDAYS(MAX($K35,AK$4),MIN($L35,EOMONTH(AK$4,0)),Assumptions!$F$4:$F$44))/NETWORKDAYS($K35,$L35,Assumptions!$F$4:$F$44)) -> 0 | AL35: =IF($J35=0,0,MAX(0,NETWORKDAYS(MAX($K35,AL$4),MIN($L35,EOMONTH(AL$4,0)),Assumptions!$F$4:$F$44))/NETWORKDAYS($K35,$L35,Assumptions!$F$4:$F$44)) -> 0 | AM35: =IF($J35=0,0,MAX(0,NETWORKDAYS(MAX($K35,AM$4),MIN($L35,EOMONTH(AM$4,0)),Assumptions!$F$4:$F$44))/NETWORKDAYS($K35,$L35,Assumptions!$F$4:$F$44)) -> 0 | ... BC35: =IF($J35=0,0,MAX(0,NETWORKDAYS(MAX($K35,BC$4),MIN($L35,EOMONTH(BC$4,0)),Assumptions!$F$4:$F$44))/NETWORKDAYS($K35,$L35,Assumptions!$F$4:$F$44)) -> 0
A36: 32 | B36: 3.2.3 | C36: 3 | D36: Subtask | E36: Component, security and contract tests | F36: Phase 1 | G36: Platform | H36: QA | I36: 53 | J36: 13 | K36: =WORKDAY(Assumptions!$C$4,I36,Assumptions!$F$4:$F$44) -> 46401 | L36: =IF(J36=0,K36,WORKDAY(K36,J36-1,Assumptions!$F$4:$F$44)) -> 46419 | N36: 0 | O36: 0 | P36: 0 | Q36: 2 | R36: 0 | S36: 0 | T36: 0 | U36: 0 | V36: 8 | W36: 0 | X36: 0 | Y36: =SUM(N36:X36) -> 10 | Z36: =Y36*(1+Assumptions!$C$5) -> 11.5 | AA36: Test report | AB36: Not started | AD36: 0 | AF36: =IF($J36=0,0,MAX(0,NETWORKDAYS(MAX($K36,AF$4),MIN($L36,EOMONTH(AF$4,0)),Assumptions!$F$4:$F$44))/NETWORKDAYS($K36,$L36,Assumptions!$F$4:$F$44)) -> 0 | AG36: =IF($J36=0,0,MAX(0,NETWORKDAYS(MAX($K36,AG$4),MIN($L36,EOMONTH(AG$4,0)),Assumptions!$F$4:$F$44))/NETWORKDAYS($K36,$L36,Assumptions!$F$4:$F$44)) -> 0 | AH36: =IF($J36=0,0,MAX(0,NETWORKDAYS(MAX($K36,AH$4),MIN($L36,EOMONTH(AH$4,0)),Assumptions!$F$4:$F$44))/NETWORKDAYS($K36,$L36,Assumptions!$F$4:$F$44)) -> 0.92307692 | AI36: =IF($J36=0,0,MAX(0,NETWORKDAYS(MAX($K36,AI$4),MIN($L36,EOMONTH(AI$4,0)),Assumptions!$F$4:$F$44))/NETWORKDAYS($K36,$L36,Assumptions!$F$4:$F$44)) -> 0.076923077 | AJ36: =IF($J36=0,0,MAX(0,NETWORKDAYS(MAX($K36,AJ$4),MIN($L36,EOMONTH(AJ$4,0)),Assumptions!$F$4:$F$44))/NETWORKDAYS($K36,$L36,Assumptions!$F$4:$F$44)) -> 0 | AK36: =IF($J36=0,0,MAX(0,NETWORKDAYS(MAX($K36,AK$4),MIN($L36,EOMONTH(AK$4,0)),Assumptions!$F$4:$F$44))/NETWORKDAYS($K36,$L36,Assumptions!$F$4:$F$44)) -> 0 | AL36: =IF($J36=0,0,MAX(0,NETWORKDAYS(MAX($K36,AL$4),MIN($L36,EOMONTH(AL$4,0)),Assumptions!$F$4:$F$44))/NETWORKDAYS($K36,$L36,Assumptions!$F$4:$F$44)) -> 0 | AM36: =IF($J36=0,0,MAX(0,NETWORKDAYS(MAX($K36,AM$4),MIN($L36,EOMONTH(AM$4,0)),Assumptions!$F$4:$F$44))/NETWORKDAYS($K36,$L36,Assumptions!$F$4:$F$44)) -> 0 | ... BC36: =IF($J36=0,0,MAX(0,NETWORKDAYS(MAX($K36,BC$4),MIN($L36,EOMONTH(BC$4,0)),Assumptions!$F$4:$F$44))/NETWORKDAYS($K36,$L36,Assumptions!$F$4:$F$44)) -> 0
A37: 33 | B37: 3.3 | C37: 2 | D37: Task | E37: Workflow and rules engine (Flowable BPMN and DMN) | F37: Phase 1 | G37: Platform | J37: =NETWORKDAYS(K37,L37,Assumptions!$F$4:$F$44) -> 50 | K37: =MIN(K38:K40) -> 46350 | L37: =MAX(L38:L40) -> 46419 | N37: =SUMPRODUCT(($C$38:$C$40=3)*(N38:N40)) -> 0 | O37: =SUMPRODUCT(($C$38:$C$40=3)*(O38:O40)) -> 0 | P37: =SUMPRODUCT(($C$38:$C$40=3)*(P38:P40)) -> 4 | Q37: =SUMPRODUCT(($C$38:$C$40=3)*(Q38:Q40)) -> 31 | R37: =SUMPRODUCT(($C$38:$C$40=3)*(R38:R40)) -> 9 | S37: =SUMPRODUCT(($C$38:$C$40=3)*(S38:S40)) -> 0 | T37: =SUMPRODUCT(($C$38:$C$40=3)*(T38:T40)) -> 0 | U37: =SUMPRODUCT(($C$38:$C$40=3)*(U38:U40)) -> 0 | ... X37: =SUMPRODUCT(($C$38:$C$40=3)*(X38:X40)) -> 0 | Y37: =SUM(N37:X37) -> 52 | Z37: =Y37*(1+Assumptions!$C$5) -> 59.8 | AA37: PLT-FR-003, 004 | AF37: 0 | AG37: 0 | AH37: 0 | AI37: 0 | AJ37: 0 | AK37: 0 | AL37: 0 | AM37: 0 | AN37: 0 | AO37: 0 | AP37: 0 | AQ37: 0 | AR37: 0 | AS37: 0 | AT37: 0 | AU37: 0 | AV37: 0 | AW37: 0 | AX37: 0 | AY37: 0 | AZ37: 0 | BA37: 0 | BB37: 0 | BC37: 0
A38: 34 | B38: 3.3.1 | C38: 3 | D38: Subtask | E38: Detailed design and contracts | F38: Phase 1 | G38: Platform | H38: ARC | I38: 16 | J38: 10 | K38: =WORKDAY(Assumptions!$C$4,I38,Assumptions!$F$4:$F$44) -> 46350 | L38: =IF(J38=0,K38,WORKDAY(K38,J38-1,Assumptions!$F$4:$F$44)) -> 46363 | M38: 20 | N38: 0 | O38: 0 | P38: 4 | Q38: 3 | R38: 0 | S38: 0 | T38: 0 | U38: 0 | V38: 0 | W38: 0 | X38: 0 | Y38: =SUM(N38:X38) -> 7 | Z38: =Y38*(1+Assumptions!$C$5) -> 8.05 | AA38: Design note, OpenAPI and event schemas | AB38: Not started | AD38: 0 | AF38: =IF($J38=0,0,MAX(0,NETWORKDAYS(MAX($K38,AF$4),MIN($L38,EOMONTH(AF$4,0)),Assumptions!$F$4:$F$44))/NETWORKDAYS($K38,$L38,Assumptions!$F$4:$F$44)) -> 0.5 | AG38: =IF($J38=0,0,MAX(0,NETWORKDAYS(MAX($K38,AG$4),MIN($L38,EOMONTH(AG$4,0)),Assumptions!$F$4:$F$44))/NETWORKDAYS($K38,$L38,Assumptions!$F$4:$F$44)) -> 0.5 | AH38: =IF($J38=0,0,MAX(0,NETWORKDAYS(MAX($K38,AH$4),MIN($L38,EOMONTH(AH$4,0)),Assumptions!$F$4:$F$44))/NETWORKDAYS($K38,$L38,Assumptions!$F$4:$F$44)) -> 0 | AI38: =IF($J38=0,0,MAX(0,NETWORKDAYS(MAX($K38,AI$4),MIN($L38,EOMONTH(AI$4,0)),Assumptions!$F$4:$F$44))/NETWORKDAYS($K38,$L38,Assumptions!$F$4:$F$44)) -> 0 | AJ38: =IF($J38=0,0,MAX(0,NETWORKDAYS(MAX($K38,AJ$4),MIN($L38,EOMONTH(AJ$4,0)),Assumptions!$F$4:$F$44))/NETWORKDAYS($K38,$L38,Assumptions!$F$4:$F$44)) -> 0 | AK38: =IF($J38=0,0,MAX(0,NETWORKDAYS(MAX($K38,AK$4),MIN($L38,EOMONTH(AK$4,0)),Assumptions!$F$4:$F$44))/NETWORKDAYS($K38,$L38,Assumptions!$F$4:$F$44)) -> 0 | AL38: =IF($J38=0,0,MAX(0,NETWORKDAYS(MAX($K38,AL$4),MIN($L38,EOMONTH(AL$4,0)),Assumptions!$F$4:$F$44))/NETWORKDAYS($K38,$L38,Assumptions!$F$4:$F$44)) -> 0 | AM38: =IF($J38=0,0,MAX(0,NETWORKDAYS(MAX($K38,AM$4),MIN($L38,EOMONTH(AM$4,0)),Assumptions!$F$4:$F$44))/NETWORKDAYS($K38,$L38,Assumptions!$F$4:$F$44)) -> 0 | ... BC38: =IF($J38=0,0,MAX(0,NETWORKDAYS(MAX($K38,BC$4),MIN($L38,EOMONTH(BC$4,0)),Assumptions!$F$4:$F$44))/NETWORKDAYS($K38,$L38,Assumptions!$F$4:$F$44)) -> 0
A39: 35 | B39: 3.3.2 | C39: 3 | D39: Subtask | E39: Build and unit tests | F39: Phase 1 | G39: Platform | H39: BE | I39: 26 | J39: 30 | K39: =WORKDAY(Assumptions!$C$4,I39,Assumptions!$F$4:$F$44) -> 46364 | L39: =IF(J39=0,K39,WORKDAY(K39,J39-1,Assumptions!$F$4:$F$44)) -> 46405 | N39: 0 | O39: 0 | P39: 0 | Q39: 25 | R39: 9 | S39: 0 | T39: 0 | U39: 0 | V39: 0 | W39: 0 | X39: 0 | Y39: =SUM(N39:X39) -> 34 | Z39: =Y39*(1+Assumptions!$C$5) -> 39.1 | AA39: Working service | AB39: Not started | AD39: 0 | AF39: =IF($J39=0,0,MAX(0,NETWORKDAYS(MAX($K39,AF$4),MIN($L39,EOMONTH(AF$4,0)),Assumptions!$F$4:$F$44))/NETWORKDAYS($K39,$L39,Assumptions!$F$4:$F$44)) -> 0 | AG39: =IF($J39=0,0,MAX(0,NETWORKDAYS(MAX($K39,AG$4),MIN($L39,EOMONTH(AG$4,0)),Assumptions!$F$4:$F$44))/NETWORKDAYS($K39,$L39,Assumptions!$F$4:$F$44)) -> 0.6 | AH39: =IF($J39=0,0,MAX(0,NETWORKDAYS(MAX($K39,AH$4),MIN($L39,EOMONTH(AH$4,0)),Assumptions!$F$4:$F$44))/NETWORKDAYS($K39,$L39,Assumptions!$F$4:$F$44)) -> 0.4 | AI39: =IF($J39=0,0,MAX(0,NETWORKDAYS(MAX($K39,AI$4),MIN($L39,EOMONTH(AI$4,0)),Assumptions!$F$4:$F$44))/NETWORKDAYS($K39,$L39,Assumptions!$F$4:$F$44)) -> 0 | AJ39: =IF($J39=0,0,MAX(0,NETWORKDAYS(MAX($K39,AJ$4),MIN($L39,EOMONTH(AJ$4,0)),Assumptions!$F$4:$F$44))/NETWORKDAYS($K39,$L39,Assumptions!$F$4:$F$44)) -> 0 | AK39: =IF($J39=0,0,MAX(0,NETWORKDAYS(MAX($K39,AK$4),MIN($L39,EOMONTH(AK$4,0)),Assumptions!$F$4:$F$44))/NETWORKDAYS($K39,$L39,Assumptions!$F$4:$F$44)) -> 0 | AL39: =IF($J39=0,0,MAX(0,NETWORKDAYS(MAX($K39,AL$4),MIN($L39,EOMONTH(AL$4,0)),Assumptions!$F$4:$F$44))/NETWORKDAYS($K39,$L39,Assumptions!$F$4:$F$44)) -> 0 | AM39: =IF($J39=0,0,MAX(0,NETWORKDAYS(MAX($K39,AM$4),MIN($L39,EOMONTH(AM$4,0)),Assumptions!$F$4:$F$44))/NETWORKDAYS($K39,$L39,Assumptions!$F$4:$F$44)) -> 0 | ... BC39: =IF($J39=0,0,MAX(0,NETWORKDAYS(MAX($K39,BC$4),MIN($L39,EOMONTH(BC$4,0)),Assumptions!$F$4:$F$44))/NETWORKDAYS($K39,$L39,Assumptions!$F$4:$F$44)) -> 0
A40: 36 | B40: 3.3.3 | C40: 3 | D40: Subtask | E40: Component, security and contract tests | F40: Phase 1 | G40: Platform | H40: QA | I40: 53 | J40: 13 | K40: =WORKDAY(Assumptions!$C$4,I40,Assumptions!$F$4:$F$44) -> 46401 | L40: =IF(J40=0,K40,WORKDAY(K40,J40-1,Assumptions!$F$4:$F$44)) -> 46419 | N40: 0 | O40: 0 | P40: 0 | Q40: 3 | R40: 0 | S40: 0 | T40: 0 | U40: 0 | V40: 8 | W40: 0 | X40: 0 | Y40: =SUM(N40:X40) -> 11 | Z40: =Y40*(1+Assumptions!$C$5) -> 12.65 | AA40: Test report | AB40: Not started | AD40: 0 | AF40: =IF($J40=0,0,MAX(0,NETWORKDAYS(MAX($K40,AF$4),MIN($L40,EOMONTH(AF$4,0)),Assumptions!$F$4:$F$44))/NETWORKDAYS($K40,$L40,Assumptions!$F$4:$F$44)) -> 0 | AG40: =IF($J40=0,0,MAX(0,NETWORKDAYS(MAX($K40,AG$4),MIN($L40,EOMONTH(AG$4,0)),Assumptions!$F$4:$F$44))/NETWORKDAYS($K40,$L40,Assumptions!$F$4:$F$44)) -> 0 | AH40: =IF($J40=0,0,MAX(0,NETWORKDAYS(MAX($K40,AH$4),MIN($L40,EOMONTH(AH$4,0)),Assumptions!$F$4:$F$44))/NETWORKDAYS($K40,$L40,Assumptions!$F$4:$F$44)) -> 0.92307692 | AI40: =IF($J40=0,0,MAX(0,NETWORKDAYS(MAX($K40,AI$4),MIN($L40,EOMONTH(AI$4,0)),Assumptions!$F$4:$F$44))/NETWORKDAYS($K40,$L40,Assumptions!$F$4:$F$44)) -> 0.076923077 | AJ40: =IF($J40=0,0,MAX(0,NETWORKDAYS(MAX($K40,AJ$4),MIN($L40,EOMONTH(AJ$4,0)),Assumptions!$F$4:$F$44))/NETWORKDAYS($K40,$L40,Assumptions!$F$4:$F$44)) -> 0 | AK40: =IF($J40=0,0,MAX(0,NETWORKDAYS(MAX($K40,AK$4),MIN($L40,EOMONTH(AK$4,0)),Assumptions!$F$4:$F$44))/NETWORKDAYS($K40,$L40,Assumptions!$F$4:$F$44)) -> 0 | AL40: =IF($J40=0,0,MAX(0,NETWORKDAYS(MAX($K40,AL$4),MIN($L40,EOMONTH(AL$4,0)),Assumptions!$F$4:$F$44))/NETWORKDAYS($K40,$L40,Assumptions!$F$4:$F$44)) -> 0 | AM40: =IF($J40=0,0,MAX(0,NETWORKDAYS(MAX($K40,AM$4),MIN($L40,EOMONTH(AM$4,0)),Assumptions!$F$4:$F$44))/NETWORKDAYS($K40,$L40,Assumptions!$F$4:$F$44)) -> 0 | ... BC40: =IF($J40=0,0,MAX(0,NETWORKDAYS(MAX($K40,BC$4),MIN($L40,EOMONTH(BC$4,0)),Assumptions!$F$4:$F$44))/NETWORKDAYS($K40,$L40,Assumptions!$F$4:$F$44)) -> 0
A41: 37 | B41: 3.4 | C41: 2 | D41: Task | E41: API gateway, BFFs and service mesh | F41: Phase 1 | G41: Platform | J41: =NETWORKDAYS(K41,L41,Assumptions!$F$4:$F$44) -> 39 | K41: =MIN(K42:K44) -> 46342 | L41: =MAX(L42:L44) -> 46394 | N41: =SUMPRODUCT(($C$42:$C$44=3)*(N42:N44)) -> 0 | O41: =SUMPRODUCT(($C$42:$C$44=3)*(O42:O44)) -> 0 | P41: =SUMPRODUCT(($C$42:$C$44=3)*(P42:P44)) -> 3 | Q41: =SUMPRODUCT(($C$42:$C$44=3)*(Q42:Q44)) -> 18 | R41: =SUMPRODUCT(($C$42:$C$44=3)*(R42:R44)) -> 0 | S41: =SUMPRODUCT(($C$42:$C$44=3)*(S42:S44)) -> 0 | T41: =SUMPRODUCT(($C$42:$C$44=3)*(T42:T44)) -> 0 | U41: =SUMPRODUCT(($C$42:$C$44=3)*(U42:U44)) -> 9 | ... X41: =SUMPRODUCT(($C$42:$C$44=3)*(X42:X44)) -> 0 | Y41: =SUM(N41:X41) -> 34 | Z41: =Y41*(1+Assumptions!$C$5) -> 39.1 | AA41: PLT-FR-010 | AF41: 0 | AG41: 0 | AH41: 0 | AI41: 0 | AJ41: 0 | AK41: 0 | AL41: 0 | AM41: 0 | AN41: 0 | AO41: 0 | AP41: 0 | AQ41: 0 | AR41: 0 | AS41: 0 | AT41: 0 | AU41: 0 | AV41: 0 | AW41: 0 | AX41: 0 | AY41: 0 | AZ41: 0 | BA41: 0 | BB41: 0 | BC41: 0
A42: 38 | B42: 3.4.1 | C42: 3 | D42: Subtask | E42: Detailed design and contracts | F42: Phase 1 | G42: Platform | H42: ARC | I42: 10 | J42: 8 | K42: =WORKDAY(Assumptions!$C$4,I42,Assumptions!$F$4:$F$44) -> 46342 | L42: =IF(J42=0,K42,WORKDAY(K42,J42-1,Assumptions!$F$4:$F$44)) -> 46351 | M42: 20 | N42: 0 | O42: 0 | P42: 3 | Q42: 2 | R42: 0 | S42: 0 | T42: 0 | U42: 0 | V42: 0 | W42: 0 | X42: 0 | Y42: =SUM(N42:X42) -> 5 | Z42: =Y42*(1+Assumptions!$C$5) -> 5.75 | AA42: Design note, OpenAPI and event schemas | AB42: Not started | AD42: 0 | AF42: =IF($J42=0,0,MAX(0,NETWORKDAYS(MAX($K42,AF$4),MIN($L42,EOMONTH(AF$4,0)),Assumptions!$F$4:$F$44))/NETWORKDAYS($K42,$L42,Assumptions!$F$4:$F$44)) -> 1 | AG42: =IF($J42=0,0,MAX(0,NETWORKDAYS(MAX($K42,AG$4),MIN($L42,EOMONTH(AG$4,0)),Assumptions!$F$4:$F$44))/NETWORKDAYS($K42,$L42,Assumptions!$F$4:$F$44)) -> 0 | AH42: =IF($J42=0,0,MAX(0,NETWORKDAYS(MAX($K42,AH$4),MIN($L42,EOMONTH(AH$4,0)),Assumptions!$F$4:$F$44))/NETWORKDAYS($K42,$L42,Assumptions!$F$4:$F$44)) -> 0 | AI42: =IF($J42=0,0,MAX(0,NETWORKDAYS(MAX($K42,AI$4),MIN($L42,EOMONTH(AI$4,0)),Assumptions!$F$4:$F$44))/NETWORKDAYS($K42,$L42,Assumptions!$F$4:$F$44)) -> 0 | AJ42: =IF($J42=0,0,MAX(0,NETWORKDAYS(MAX($K42,AJ$4),MIN($L42,EOMONTH(AJ$4,0)),Assumptions!$F$4:$F$44))/NETWORKDAYS($K42,$L42,Assumptions!$F$4:$F$44)) -> 0 | AK42: =IF($J42=0,0,MAX(0,NETWORKDAYS(MAX($K42,AK$4),MIN($L42,EOMONTH(AK$4,0)),Assumptions!$F$4:$F$44))/NETWORKDAYS($K42,$L42,Assumptions!$F$4:$F$44)) -> 0 | AL42: =IF($J42=0,0,MAX(0,NETWORKDAYS(MAX($K42,AL$4),MIN($L42,EOMONTH(AL$4,0)),Assumptions!$F$4:$F$44))/NETWORKDAYS($K42,$L42,Assumptions!$F$4:$F$44)) -> 0 | AM42: =IF($J42=0,0,MAX(0,NETWORKDAYS(MAX($K42,AM$4),MIN($L42,EOMONTH(AM$4,0)),Assumptions!$F$4:$F$44))/NETWORKDAYS($K42,$L42,Assumptions!$F$4:$F$44)) -> 0 | ... BC42: =IF($J42=0,0,MAX(0,NETWORKDAYS(MAX($K42,BC$4),MIN($L42,EOMONTH(BC$4,0)),Assumptions!$F$4:$F$44))/NETWORKDAYS($K42,$L42,Assumptions!$F$4:$F$44)) -> 0
A43: 39 | B43: 3.4.2 | C43: 3 | D43: Subtask | E43: Build and unit tests | F43: Phase 1 | G43: Platform | H43: BE | I43: 18 | J43: 24 | K43: =WORKDAY(Assumptions!$C$4,I43,Assumptions!$F$4:$F$44) -> 46352 | L43: =IF(J43=0,K43,WORKDAY(K43,J43-1,Assumptions!$F$4:$F$44)) -> 46385 | N43: 0 | O43: 0 | P43: 0 | Q43: 14 | R43: 0 | S43: 0 | T43: 0 | U43: 9 | V43: 0 | W43: 0 | X43: 0 | Y43: =SUM(N43:X43) -> 23 | Z43: =Y43*(1+Assumptions!$C$5) -> 26.45 | AA43: Working service | AB43: Not started | AD43: 0 | AF43: =IF($J43=0,0,MAX(0,NETWORKDAYS(MAX($K43,AF$4),MIN($L43,EOMONTH(AF$4,0)),Assumptions!$F$4:$F$44))/NETWORKDAYS($K43,$L43,Assumptions!$F$4:$F$44)) -> 0.125 | AG43: =IF($J43=0,0,MAX(0,NETWORKDAYS(MAX($K43,AG$4),MIN($L43,EOMONTH(AG$4,0)),Assumptions!$F$4:$F$44))/NETWORKDAYS($K43,$L43,Assumptions!$F$4:$F$44)) -> 0.875 | AH43: =IF($J43=0,0,MAX(0,NETWORKDAYS(MAX($K43,AH$4),MIN($L43,EOMONTH(AH$4,0)),Assumptions!$F$4:$F$44))/NETWORKDAYS($K43,$L43,Assumptions!$F$4:$F$44)) -> 0 | AI43: =IF($J43=0,0,MAX(0,NETWORKDAYS(MAX($K43,AI$4),MIN($L43,EOMONTH(AI$4,0)),Assumptions!$F$4:$F$44))/NETWORKDAYS($K43,$L43,Assumptions!$F$4:$F$44)) -> 0 | AJ43: =IF($J43=0,0,MAX(0,NETWORKDAYS(MAX($K43,AJ$4),MIN($L43,EOMONTH(AJ$4,0)),Assumptions!$F$4:$F$44))/NETWORKDAYS($K43,$L43,Assumptions!$F$4:$F$44)) -> 0 | AK43: =IF($J43=0,0,MAX(0,NETWORKDAYS(MAX($K43,AK$4),MIN($L43,EOMONTH(AK$4,0)),Assumptions!$F$4:$F$44))/NETWORKDAYS($K43,$L43,Assumptions!$F$4:$F$44)) -> 0 | AL43: =IF($J43=0,0,MAX(0,NETWORKDAYS(MAX($K43,AL$4),MIN($L43,EOMONTH(AL$4,0)),Assumptions!$F$4:$F$44))/NETWORKDAYS($K43,$L43,Assumptions!$F$4:$F$44)) -> 0 | AM43: =IF($J43=0,0,MAX(0,NETWORKDAYS(MAX($K43,AM$4),MIN($L43,EOMONTH(AM$4,0)),Assumptions!$F$4:$F$44))/NETWORKDAYS($K43,$L43,Assumptions!$F$4:$F$44)) -> 0 | ... BC43: =IF($J43=0,0,MAX(0,NETWORKDAYS(MAX($K43,BC$4),MIN($L43,EOMONTH(BC$4,0)),Assumptions!$F$4:$F$44))/NETWORKDAYS($K43,$L43,Assumptions!$F$4:$F$44)) -> 0
A44: 40 | B44: 3.4.3 | C44: 3 | D44: Subtask | E44: Component, security and contract tests | F44: Phase 1 | G44: Platform | H44: QA | I44: 39 | J44: 10 | K44: =WORKDAY(Assumptions!$C$4,I44,Assumptions!$F$4:$F$44) -> 46381 | L44: =IF(J44=0,K44,WORKDAY(K44,J44-1,Assumptions!$F$4:$F$44)) -> 46394 | N44: 0 | O44: 0 | P44: 0 | Q44: 2 | R44: 0 | S44: 0 | T44: 0 | U44: 0 | V44: 4 | W44: 0 | X44: 0 | Y44: =SUM(N44:X44) -> 6 | Z44: =Y44*(1+Assumptions!$C$5) -> 6.9 | AA44: Test report | AB44: Not started | AD44: 0 | AF44: =IF($J44=0,0,MAX(0,NETWORKDAYS(MAX($K44,AF$4),MIN($L44,EOMONTH(AF$4,0)),Assumptions!$F$4:$F$44))/NETWORKDAYS($K44,$L44,Assumptions!$F$4:$F$44)) -> 0 | AG44: =IF($J44=0,0,MAX(0,NETWORKDAYS(MAX($K44,AG$4),MIN($L44,EOMONTH(AG$4,0)),Assumptions!$F$4:$F$44))/NETWORKDAYS($K44,$L44,Assumptions!$F$4:$F$44)) -> 0.5 | AH44: =IF($J44=0,0,MAX(0,NETWORKDAYS(MAX($K44,AH$4),MIN($L44,EOMONTH(AH$4,0)),Assumptions!$F$4:$F$44))/NETWORKDAYS($K44,$L44,Assumptions!$F$4:$F$44)) -> 0.5 | AI44: =IF($J44=0,0,MAX(0,NETWORKDAYS(MAX($K44,AI$4),MIN($L44,EOMONTH(AI$4,0)),Assumptions!$F$4:$F$44))/NETWORKDAYS($K44,$L44,Assumptions!$F$4:$F$44)) -> 0 | AJ44: =IF($J44=0,0,MAX(0,NETWORKDAYS(MAX($K44,AJ$4),MIN($L44,EOMONTH(AJ$4,0)),Assumptions!$F$4:$F$44))/NETWORKDAYS($K44,$L44,Assumptions!$F$4:$F$44)) -> 0 | AK44: =IF($J44=0,0,MAX(0,NETWORKDAYS(MAX($K44,AK$4),MIN($L44,EOMONTH(AK$4,0)),Assumptions!$F$4:$F$44))/NETWORKDAYS($K44,$L44,Assumptions!$F$4:$F$44)) -> 0 | AL44: =IF($J44=0,0,MAX(0,NETWORKDAYS(MAX($K44,AL$4),MIN($L44,EOMONTH(AL$4,0)),Assumptions!$F$4:$F$44))/NETWORKDAYS($K44,$L44,Assumptions!$F$4:$F$44)) -> 0 | AM44: =IF($J44=0,0,MAX(0,NETWORKDAYS(MAX($K44,AM$4),MIN($L44,EOMONTH(AM$4,0)),Assumptions!$F$4:$F$44))/NETWORKDAYS($K44,$L44,Assumptions!$F$4:$F$44)) -> 0 | ... BC44: =IF($J44=0,0,MAX(0,NETWORKDAYS(MAX($K44,BC$4),MIN($L44,EOMONTH(BC$4,0)),Assumptions!$F$4:$F$44))/NETWORKDAYS($K44,$L44,Assumptions!$F$4:$F$44)) -> 0
A45: 41 | B45: 3.5 | C45: 2 | D45: Task | E45: Event bus, outbox/inbox library and schema registry | F45: Phase 1 | G45: Platform | J45: =NETWORKDAYS(K45,L45,Assumptions!$F$4:$F$44) -> 39 | K45: =MIN(K46:K48) -> 46342 | L45: =MAX(L46:L48) -> 46394 | N45: =SUMPRODUCT(($C$46:$C$48=3)*(N46:N48)) -> 0 | O45: =SUMPRODUCT(($C$46:$C$48=3)*(O46:O48)) -> 0 | P45: =SUMPRODUCT(($C$46:$C$48=3)*(P46:P48)) -> 4 | Q45: =SUMPRODUCT(($C$46:$C$48=3)*(Q46:Q48)) -> 20 | R45: =SUMPRODUCT(($C$46:$C$48=3)*(R46:R48)) -> 0 | S45: =SUMPRODUCT(($C$46:$C$48=3)*(S46:S48)) -> 0 | T45: =SUMPRODUCT(($C$46:$C$48=3)*(T46:T48)) -> 0 | U45: =SUMPRODUCT(($C$46:$C$48=3)*(U46:U48)) -> 5 | ... X45: =SUMPRODUCT(($C$46:$C$48=3)*(X46:X48)) -> 0 | Y45: =SUM(N45:X45) -> 34 | Z45: =Y45*(1+Assumptions!$C$5) -> 39.1 | AA45: NFR-003 | AF45: 0 | AG45: 0 | AH45: 0 | AI45: 0 | AJ45: 0 | AK45: 0 | AL45: 0 | AM45: 0 | AN45: 0 | AO45: 0 | AP45: 0 | AQ45: 0 | AR45: 0 | AS45: 0 | AT45: 0 | AU45: 0 | AV45: 0 | AW45: 0 | AX45: 0 | AY45: 0 | AZ45: 0 | BA45: 0 | BB45: 0 | BC45: 0
A46: 42 | B46: 3.5.1 | C46: 3 | D46: Subtask | E46: Detailed design and contracts | F46: Phase 1 | G46: Platform | H46: ARC | I46: 10 | J46: 8 | K46: =WORKDAY(Assumptions!$C$4,I46,Assumptions!$F$4:$F$44) -> 46342 | L46: =IF(J46=0,K46,WORKDAY(K46,J46-1,Assumptions!$F$4:$F$44)) -> 46351 | M46: 20 | N46: 0 | O46: 0 | P46: 4 | Q46: 2 | R46: 0 | S46: 0 | T46: 0 | U46: 0 | V46: 0 | W46: 0 | X46: 0 | Y46: =SUM(N46:X46) -> 6 | Z46: =Y46*(1+Assumptions!$C$5) -> 6.9 | AA46: Design note, OpenAPI and event schemas | AB46: Not started | AD46: 0 | AF46: =IF($J46=0,0,MAX(0,NETWORKDAYS(MAX($K46,AF$4),MIN($L46,EOMONTH(AF$4,0)),Assumptions!$F$4:$F$44))/NETWORKDAYS($K46,$L46,Assumptions!$F$4:$F$44)) -> 1 | AG46: =IF($J46=0,0,MAX(0,NETWORKDAYS(MAX($K46,AG$4),MIN($L46,EOMONTH(AG$4,0)),Assumptions!$F$4:$F$44))/NETWORKDAYS($K46,$L46,Assumptions!$F$4:$F$44)) -> 0 | AH46: =IF($J46=0,0,MAX(0,NETWORKDAYS(MAX($K46,AH$4),MIN($L46,EOMONTH(AH$4,0)),Assumptions!$F$4:$F$44))/NETWORKDAYS($K46,$L46,Assumptions!$F$4:$F$44)) -> 0 | AI46: =IF($J46=0,0,MAX(0,NETWORKDAYS(MAX($K46,AI$4),MIN($L46,EOMONTH(AI$4,0)),Assumptions!$F$4:$F$44))/NETWORKDAYS($K46,$L46,Assumptions!$F$4:$F$44)) -> 0 | AJ46: =IF($J46=0,0,MAX(0,NETWORKDAYS(MAX($K46,AJ$4),MIN($L46,EOMONTH(AJ$4,0)),Assumptions!$F$4:$F$44))/NETWORKDAYS($K46,$L46,Assumptions!$F$4:$F$44)) -> 0 | AK46: =IF($J46=0,0,MAX(0,NETWORKDAYS(MAX($K46,AK$4),MIN($L46,EOMONTH(AK$4,0)),Assumptions!$F$4:$F$44))/NETWORKDAYS($K46,$L46,Assumptions!$F$4:$F$44)) -> 0 | AL46: =IF($J46=0,0,MAX(0,NETWORKDAYS(MAX($K46,AL$4),MIN($L46,EOMONTH(AL$4,0)),Assumptions!$F$4:$F$44))/NETWORKDAYS($K46,$L46,Assumptions!$F$4:$F$44)) -> 0 | AM46: =IF($J46=0,0,MAX(0,NETWORKDAYS(MAX($K46,AM$4),MIN($L46,EOMONTH(AM$4,0)),Assumptions!$F$4:$F$44))/NETWORKDAYS($K46,$L46,Assumptions!$F$4:$F$44)) -> 0 | ... BC46: =IF($J46=0,0,MAX(0,NETWORKDAYS(MAX($K46,BC$4),MIN($L46,EOMONTH(BC$4,0)),Assumptions!$F$4:$F$44))/NETWORKDAYS($K46,$L46,Assumptions!$F$4:$F$44)) -> 0
A47: 43 | B47: 3.5.2 | C47: 3 | D47: Subtask | E47: Build and unit tests | F47: Phase 1 | G47: Platform | H47: BE | I47: 18 | J47: 24 | K47: =WORKDAY(Assumptions!$C$4,I47,Assumptions!$F$4:$F$44) -> 46352 | L47: =IF(J47=0,K47,WORKDAY(K47,J47-1,Assumptions!$F$4:$F$44)) -> 46385 | N47: 0 | O47: 0 | P47: 0 | Q47: 16 | R47: 0 | S47: 0 | T47: 0 | U47: 5 | V47: 0 | W47: 0 | X47: 0 | Y47: =SUM(N47:X47) -> 21 | Z47: =Y47*(1+Assumptions!$C$5) -> 24.15 | AA47: Working service | AB47: Not started | AD47: 0 | AF47: =IF($J47=0,0,MAX(0,NETWORKDAYS(MAX($K47,AF$4),MIN($L47,EOMONTH(AF$4,0)),Assumptions!$F$4:$F$44))/NETWORKDAYS($K47,$L47,Assumptions!$F$4:$F$44)) -> 0.125 | AG47: =IF($J47=0,0,MAX(0,NETWORKDAYS(MAX($K47,AG$4),MIN($L47,EOMONTH(AG$4,0)),Assumptions!$F$4:$F$44))/NETWORKDAYS($K47,$L47,Assumptions!$F$4:$F$44)) -> 0.875 | AH47: =IF($J47=0,0,MAX(0,NETWORKDAYS(MAX($K47,AH$4),MIN($L47,EOMONTH(AH$4,0)),Assumptions!$F$4:$F$44))/NETWORKDAYS($K47,$L47,Assumptions!$F$4:$F$44)) -> 0 | AI47: =IF($J47=0,0,MAX(0,NETWORKDAYS(MAX($K47,AI$4),MIN($L47,EOMONTH(AI$4,0)),Assumptions!$F$4:$F$44))/NETWORKDAYS($K47,$L47,Assumptions!$F$4:$F$44)) -> 0 | AJ47: =IF($J47=0,0,MAX(0,NETWORKDAYS(MAX($K47,AJ$4),MIN($L47,EOMONTH(AJ$4,0)),Assumptions!$F$4:$F$44))/NETWORKDAYS($K47,$L47,Assumptions!$F$4:$F$44)) -> 0 | AK47: =IF($J47=0,0,MAX(0,NETWORKDAYS(MAX($K47,AK$4),MIN($L47,EOMONTH(AK$4,0)),Assumptions!$F$4:$F$44))/NETWORKDAYS($K47,$L47,Assumptions!$F$4:$F$44)) -> 0 | AL47: =IF($J47=0,0,MAX(0,NETWORKDAYS(MAX($K47,AL$4),MIN($L47,EOMONTH(AL$4,0)),Assumptions!$F$4:$F$44))/NETWORKDAYS($K47,$L47,Assumptions!$F$4:$F$44)) -> 0 | AM47: =IF($J47=0,0,MAX(0,NETWORKDAYS(MAX($K47,AM$4),MIN($L47,EOMONTH(AM$4,0)),Assumptions!$F$4:$F$44))/NETWORKDAYS($K47,$L47,Assumptions!$F$4:$F$44)) -> 0 | ... BC47: =IF($J47=0,0,MAX(0,NETWORKDAYS(MAX($K47,BC$4),MIN($L47,EOMONTH(BC$4,0)),Assumptions!$F$4:$F$44))/NETWORKDAYS($K47,$L47,Assumptions!$F$4:$F$44)) -> 0
A48: 44 | B48: 3.5.3 | C48: 3 | D48: Subtask | E48: Component, security and contract tests | F48: Phase 1 | G48: Platform | H48: QA | I48: 39 | J48: 10 | K48: =WORKDAY(Assumptions!$C$4,I48,Assumptions!$F$4:$F$44) -> 46381 | L48: =IF(J48=0,K48,WORKDAY(K48,J48-1,Assumptions!$F$4:$F$44)) -> 46394 | N48: 0 | O48: 0 | P48: 0 | Q48: 2 | R48: 0 | S48: 0 | T48: 0 | U48: 0 | V48: 5 | W48: 0 | X48: 0 | Y48: =SUM(N48:X48) -> 7 | Z48: =Y48*(1+Assumptions!$C$5) -> 8.05 | AA48: Test report | AB48: Not started | AD48: 0 | AF48: =IF($J48=0,0,MAX(0,NETWORKDAYS(MAX($K48,AF$4),MIN($L48,EOMONTH(AF$4,0)),Assumptions!$F$4:$F$44))/NETWORKDAYS($K48,$L48,Assumptions!$F$4:$F$44)) -> 0 | AG48: =IF($J48=0,0,MAX(0,NETWORKDAYS(MAX($K48,AG$4),MIN($L48,EOMONTH(AG$4,0)),Assumptions!$F$4:$F$44))/NETWORKDAYS($K48,$L48,Assumptions!$F$4:$F$44)) -> 0.5 | AH48: =IF($J48=0,0,MAX(0,NETWORKDAYS(MAX($K48,AH$4),MIN($L48,EOMONTH(AH$4,0)),Assumptions!$F$4:$F$44))/NETWORKDAYS($K48,$L48,Assumptions!$F$4:$F$44)) -> 0.5 | AI48: =IF($J48=0,0,MAX(0,NETWORKDAYS(MAX($K48,AI$4),MIN($L48,EOMONTH(AI$4,0)),Assumptions!$F$4:$F$44))/NETWORKDAYS($K48,$L48,Assumptions!$F$4:$F$44)) -> 0 | AJ48: =IF($J48=0,0,MAX(0,NETWORKDAYS(MAX($K48,AJ$4),MIN($L48,EOMONTH(AJ$4,0)),Assumptions!$F$4:$F$44))/NETWORKDAYS($K48,$L48,Assumptions!$F$4:$F$44)) -> 0 | AK48: =IF($J48=0,0,MAX(0,NETWORKDAYS(MAX($K48,AK$4),MIN($L48,EOMONTH(AK$4,0)),Assumptions!$F$4:$F$44))/NETWORKDAYS($K48,$L48,Assumptions!$F$4:$F$44)) -> 0 | AL48: =IF($J48=0,0,MAX(0,NETWORKDAYS(MAX($K48,AL$4),MIN($L48,EOMONTH(AL$4,0)),Assumptions!$F$4:$F$44))/NETWORKDAYS($K48,$L48,Assumptions!$F$4:$F$44)) -> 0 | AM48: =IF($J48=0,0,MAX(0,NETWORKDAYS(MAX($K48,AM$4),MIN($L48,EOMONTH(AM$4,0)),Assumptions!$F$4:$F$44))/NETWORKDAYS($K48,$L48,Assumptions!$F$4:$F$44)) -> 0 | ... BC48: =IF($J48=0,0,MAX(0,NETWORKDAYS(MAX($K48,BC$4),MIN($L48,EOMONTH(BC$4,0)),Assumptions!$F$4:$F$44))/NETWORKDAYS($K48,$L48,Assumptions!$F$4:$F$44)) -> 0
A49: 45 | B49: 3.6 | C49: 2 | D49: Task | E49: Payment service, gateway, UPI and BBPS | F49: Phase 1 | G49: Platform | J49: =NETWORKDAYS(K49,L49,Assumptions!$F$4:$F$44) -> 44 | K49: =MIN(K50:K52) -> 46365 | L49: =MAX(L50:L52) -> 46426 | N49: =SUMPRODUCT(($C$50:$C$52=3)*(N50:N52)) -> 0 | O49: =SUMPRODUCT(($C$50:$C$52=3)*(O50:O52)) -> 0 | P49: =SUMPRODUCT(($C$50:$C$52=3)*(P50:P52)) -> 2 | Q49: =SUMPRODUCT(($C$50:$C$52=3)*(Q50:Q52)) -> 33 | R49: =SUMPRODUCT(($C$50:$C$52=3)*(R50:R52)) -> 5 | S49: =SUMPRODUCT(($C$50:$C$52=3)*(S50:S52)) -> 0 | T49: =SUMPRODUCT(($C$50:$C$52=3)*(T50:T52)) -> 0 | U49: =SUMPRODUCT(($C$50:$C$52=3)*(U50:U52)) -> 0 | ... X49: =SUMPRODUCT(($C$50:$C$52=3)*(X50:X52)) -> 0 | Y49: =SUM(N49:X49) -> 50 | Z49: =Y49*(1+Assumptions!$C$5) -> 57.5 | AA49: PLT-FR-008 | AF49: 0 | AG49: 0 | AH49: 0 | AI49: 0 | AJ49: 0 | AK49: 0 | AL49: 0 | AM49: 0 | AN49: 0 | AO49: 0 | AP49: 0 | AQ49: 0 | AR49: 0 | AS49: 0 | AT49: 0 | AU49: 0 | AV49: 0 | AW49: 0 | AX49: 0 | AY49: 0 | AZ49: 0 | BA49: 0 | BB49: 0 | BC49: 0
A50: 46 | B50: 3.6.1 | C50: 3 | D50: Subtask | E50: Detailed design and contracts | F50: Phase 1 | G50: Platform | H50: ARC | I50: 27 | J50: 9 | K50: =WORKDAY(Assumptions!$C$4,I50,Assumptions!$F$4:$F$44) -> 46365 | L50: =IF(J50=0,K50,WORKDAY(K50,J50-1,Assumptions!$F$4:$F$44)) -> 46377 | M50: 20 | N50: 0 | O50: 0 | P50: 2 | Q50: 3 | R50: 0 | S50: 0 | T50: 0 | U50: 0 | V50: 0 | W50: 0 | X50: 0 | Y50: =SUM(N50:X50) -> 5 | Z50: =Y50*(1+Assumptions!$C$5) -> 5.75 | AA50: Design note, OpenAPI and event schemas | AB50: Not started | AD50: 0 | AF50: =IF($J50=0,0,MAX(0,NETWORKDAYS(MAX($K50,AF$4),MIN($L50,EOMONTH(AF$4,0)),Assumptions!$F$4:$F$44))/NETWORKDAYS($K50,$L50,Assumptions!$F$4:$F$44)) -> 0 | AG50: =IF($J50=0,0,MAX(0,NETWORKDAYS(MAX($K50,AG$4),MIN($L50,EOMONTH(AG$4,0)),Assumptions!$F$4:$F$44))/NETWORKDAYS($K50,$L50,Assumptions!$F$4:$F$44)) -> 1 | AH50: =IF($J50=0,0,MAX(0,NETWORKDAYS(MAX($K50,AH$4),MIN($L50,EOMONTH(AH$4,0)),Assumptions!$F$4:$F$44))/NETWORKDAYS($K50,$L50,Assumptions!$F$4:$F$44)) -> 0 | AI50: =IF($J50=0,0,MAX(0,NETWORKDAYS(MAX($K50,AI$4),MIN($L50,EOMONTH(AI$4,0)),Assumptions!$F$4:$F$44))/NETWORKDAYS($K50,$L50,Assumptions!$F$4:$F$44)) -> 0 | AJ50: =IF($J50=0,0,MAX(0,NETWORKDAYS(MAX($K50,AJ$4),MIN($L50,EOMONTH(AJ$4,0)),Assumptions!$F$4:$F$44))/NETWORKDAYS($K50,$L50,Assumptions!$F$4:$F$44)) -> 0 | AK50: =IF($J50=0,0,MAX(0,NETWORKDAYS(MAX($K50,AK$4),MIN($L50,EOMONTH(AK$4,0)),Assumptions!$F$4:$F$44))/NETWORKDAYS($K50,$L50,Assumptions!$F$4:$F$44)) -> 0 | AL50: =IF($J50=0,0,MAX(0,NETWORKDAYS(MAX($K50,AL$4),MIN($L50,EOMONTH(AL$4,0)),Assumptions!$F$4:$F$44))/NETWORKDAYS($K50,$L50,Assumptions!$F$4:$F$44)) -> 0 | AM50: =IF($J50=0,0,MAX(0,NETWORKDAYS(MAX($K50,AM$4),MIN($L50,EOMONTH(AM$4,0)),Assumptions!$F$4:$F$44))/NETWORKDAYS($K50,$L50,Assumptions!$F$4:$F$44)) -> 0 | ... BC50: =IF($J50=0,0,MAX(0,NETWORKDAYS(MAX($K50,BC$4),MIN($L50,EOMONTH(BC$4,0)),Assumptions!$F$4:$F$44))/NETWORKDAYS($K50,$L50,Assumptions!$F$4:$F$44)) -> 0
A51: 47 | B51: 3.6.2 | C51: 3 | D51: Subtask | E51: Build and unit tests | F51: Phase 1 | G51: Platform | H51: BE | I51: 36 | J51: 27 | K51: =WORKDAY(Assumptions!$C$4,I51,Assumptions!$F$4:$F$44) -> 46378 | L51: =IF(J51=0,K51,WORKDAY(K51,J51-1,Assumptions!$F$4:$F$44)) -> 46414 | N51: 0 | O51: 0 | P51: 0 | Q51: 27 | R51: 5 | S51: 0 | T51: 0 | U51: 0 | V51: 0 | W51: 0 | X51: 0 | Y51: =SUM(N51:X51) -> 32 | Z51: =Y51*(1+Assumptions!$C$5) -> 36.8 | AA51: Working service | AB51: Not started | AD51: 0 | AF51: =IF($J51=0,0,MAX(0,NETWORKDAYS(MAX($K51,AF$4),MIN($L51,EOMONTH(AF$4,0)),Assumptions!$F$4:$F$44))/NETWORKDAYS($K51,$L51,Assumptions!$F$4:$F$44)) -> 0 | AG51: =IF($J51=0,0,MAX(0,NETWORKDAYS(MAX($K51,AG$4),MIN($L51,EOMONTH(AG$4,0)),Assumptions!$F$4:$F$44))/NETWORKDAYS($K51,$L51,Assumptions!$F$4:$F$44)) -> 0.2962963 | AH51: =IF($J51=0,0,MAX(0,NETWORKDAYS(MAX($K51,AH$4),MIN($L51,EOMONTH(AH$4,0)),Assumptions!$F$4:$F$44))/NETWORKDAYS($K51,$L51,Assumptions!$F$4:$F$44)) -> 0.7037037 | AI51: =IF($J51=0,0,MAX(0,NETWORKDAYS(MAX($K51,AI$4),MIN($L51,EOMONTH(AI$4,0)),Assumptions!$F$4:$F$44))/NETWORKDAYS($K51,$L51,Assumptions!$F$4:$F$44)) -> 0 | AJ51: =IF($J51=0,0,MAX(0,NETWORKDAYS(MAX($K51,AJ$4),MIN($L51,EOMONTH(AJ$4,0)),Assumptions!$F$4:$F$44))/NETWORKDAYS($K51,$L51,Assumptions!$F$4:$F$44)) -> 0 | AK51: =IF($J51=0,0,MAX(0,NETWORKDAYS(MAX($K51,AK$4),MIN($L51,EOMONTH(AK$4,0)),Assumptions!$F$4:$F$44))/NETWORKDAYS($K51,$L51,Assumptions!$F$4:$F$44)) -> 0 | AL51: =IF($J51=0,0,MAX(0,NETWORKDAYS(MAX($K51,AL$4),MIN($L51,EOMONTH(AL$4,0)),Assumptions!$F$4:$F$44))/NETWORKDAYS($K51,$L51,Assumptions!$F$4:$F$44)) -> 0 | AM51: =IF($J51=0,0,MAX(0,NETWORKDAYS(MAX($K51,AM$4),MIN($L51,EOMONTH(AM$4,0)),Assumptions!$F$4:$F$44))/NETWORKDAYS($K51,$L51,Assumptions!$F$4:$F$44)) -> 0 | ... BC51: =IF($J51=0,0,MAX(0,NETWORKDAYS(MAX($K51,BC$4),MIN($L51,EOMONTH(BC$4,0)),Assumptions!$F$4:$F$44))/NETWORKDAYS($K51,$L51,Assumptions!$F$4:$F$44)) -> 0
A52: 48 | B52: 3.6.3 | C52: 3 | D52: Subtask | E52: Component, security and contract tests | F52: Phase 1 | G52: Platform | H52: QA | I52: 60 | J52: 11 | K52: =WORKDAY(Assumptions!$C$4,I52,Assumptions!$F$4:$F$44) -> 46412 | L52: =IF(J52=0,K52,WORKDAY(K52,J52-1,Assumptions!$F$4:$F$44)) -> 46426 | N52: 0 | O52: 0 | P52: 0 | Q52: 3 | R52: 0 | S52: 0 | T52: 0 | U52: 0 | V52: 10 | W52: 0 | X52: 0 | Y52: =SUM(N52:X52) -> 13 | Z52: =Y52*(1+Assumptions!$C$5) -> 14.95 | AA52: Test report | AB52: Not started | AD52: 0 | AF52: =IF($J52=0,0,MAX(0,NETWORKDAYS(MAX($K52,AF$4),MIN($L52,EOMONTH(AF$4,0)),Assumptions!$F$4:$F$44))/NETWORKDAYS($K52,$L52,Assumptions!$F$4:$F$44)) -> 0 | AG52: =IF($J52=0,0,MAX(0,NETWORKDAYS(MAX($K52,AG$4),MIN($L52,EOMONTH(AG$4,0)),Assumptions!$F$4:$F$44))/NETWORKDAYS($K52,$L52,Assumptions!$F$4:$F$44)) -> 0 | AH52: =IF($J52=0,0,MAX(0,NETWORKDAYS(MAX($K52,AH$4),MIN($L52,EOMONTH(AH$4,0)),Assumptions!$F$4:$F$44))/NETWORKDAYS($K52,$L52,Assumptions!$F$4:$F$44)) -> 0.45454545 | AI52: =IF($J52=0,0,MAX(0,NETWORKDAYS(MAX($K52,AI$4),MIN($L52,EOMONTH(AI$4,0)),Assumptions!$F$4:$F$44))/NETWORKDAYS($K52,$L52,Assumptions!$F$4:$F$44)) -> 0.54545455 | AJ52: =IF($J52=0,0,MAX(0,NETWORKDAYS(MAX($K52,AJ$4),MIN($L52,EOMONTH(AJ$4,0)),Assumptions!$F$4:$F$44))/NETWORKDAYS($K52,$L52,Assumptions!$F$4:$F$44)) -> 0 | AK52: =IF($J52=0,0,MAX(0,NETWORKDAYS(MAX($K52,AK$4),MIN($L52,EOMONTH(AK$4,0)),Assumptions!$F$4:$F$44))/NETWORKDAYS($K52,$L52,Assumptions!$F$4:$F$44)) -> 0 | AL52: =IF($J52=0,0,MAX(0,NETWORKDAYS(MAX($K52,AL$4),MIN($L52,EOMONTH(AL$4,0)),Assumptions!$F$4:$F$44))/NETWORKDAYS($K52,$L52,Assumptions!$F$4:$F$44)) -> 0 | AM52: =IF($J52=0,0,MAX(0,NETWORKDAYS(MAX($K52,AM$4),MIN($L52,EOMONTH(AM$4,0)),Assumptions!$F$4:$F$44))/NETWORKDAYS($K52,$L52,Assumptions!$F$4:$F$44)) -> 0 | ... BC52: =IF($J52=0,0,MAX(0,NETWORKDAYS(MAX($K52,BC$4),MIN($L52,EOMONTH(BC$4,0)),Assumptions!$F$4:$F$44))/NETWORKDAYS($K52,$L52,Assumptions!$F$4:$F$44)) -> 0
A53: 49 | B53: 3.7 | C53: 2 | D53: Task | E53: Notification service (DLT SMS, WhatsApp, email, IVRS) | F53: Phase 1 | G53: Platform | J53: =NETWORKDAYS(K53,L53,Assumptions!$F$4:$F$44) -> 39 | K53: =MIN(K54:K56) -> 46365 | L53: =MAX(L54:L56) -> 46419 | N53: =SUMPRODUCT(($C$54:$C$56=3)*(N54:N56)) -> 0 | O53: =SUMPRODUCT(($C$54:$C$56=3)*(O54:O56)) -> 4 | P53: =SUMPRODUCT(($C$54:$C$56=3)*(P54:P56)) -> 2 | Q53: =SUMPRODUCT(($C$54:$C$56=3)*(Q54:Q56)) -> 20 | R53: =SUMPRODUCT(($C$54:$C$56=3)*(R54:R56)) -> 0 | S53: =SUMPRODUCT(($C$54:$C$56=3)*(S54:S56)) -> 0 | T53: =SUMPRODUCT(($C$54:$C$56=3)*(T54:T56)) -> 0 | U53: =SUMPRODUCT(($C$54:$C$56=3)*(U54:U56)) -> 0 | ... X53: =SUMPRODUCT(($C$54:$C$56=3)*(X54:X56)) -> 0 | Y53: =SUM(N53:X53) -> 32 | Z53: =Y53*(1+Assumptions!$C$5) -> 36.8 | AA53: PLT-FR-007 | AF53: 0 | AG53: 0 | AH53: 0 | AI53: 0 | AJ53: 0 | AK53: 0 | AL53: 0 | AM53: 0 | AN53: 0 | AO53: 0 | AP53: 0 | AQ53: 0 | AR53: 0 | AS53: 0 | AT53: 0 | AU53: 0 | AV53: 0 | AW53: 0 | AX53: 0 | AY53: 0 | AZ53: 0 | BA53: 0 | BB53: 0 | BC53: 0
A54: 50 | B54: 3.7.1 | C54: 3 | D54: Subtask | E54: Detailed design and contracts | F54: Phase 1 | G54: Platform | H54: ARC | I54: 27 | J54: 8 | K54: =WORKDAY(Assumptions!$C$4,I54,Assumptions!$F$4:$F$44) -> 46365 | L54: =IF(J54=0,K54,WORKDAY(K54,J54-1,Assumptions!$F$4:$F$44)) -> 46374 | M54: 20 | N54: 0 | O54: 0 | P54: 2 | Q54: 2 | R54: 0 | S54: 0 | T54: 0 | U54: 0 | V54: 0 | W54: 0 | X54: 0 | Y54: =SUM(N54:X54) -> 4 | Z54: =Y54*(1+Assumptions!$C$5) -> 4.6 | AA54: Design note, OpenAPI and event schemas | AB54: Not started | AD54: 0 | AF54: =IF($J54=0,0,MAX(0,NETWORKDAYS(MAX($K54,AF$4),MIN($L54,EOMONTH(AF$4,0)),Assumptions!$F$4:$F$44))/NETWORKDAYS($K54,$L54,Assumptions!$F$4:$F$44)) -> 0 | AG54: =IF($J54=0,0,MAX(0,NETWORKDAYS(MAX($K54,AG$4),MIN($L54,EOMONTH(AG$4,0)),Assumptions!$F$4:$F$44))/NETWORKDAYS($K54,$L54,Assumptions!$F$4:$F$44)) -> 1 | AH54: =IF($J54=0,0,MAX(0,NETWORKDAYS(MAX($K54,AH$4),MIN($L54,EOMONTH(AH$4,0)),Assumptions!$F$4:$F$44))/NETWORKDAYS($K54,$L54,Assumptions!$F$4:$F$44)) -> 0 | AI54: =IF($J54=0,0,MAX(0,NETWORKDAYS(MAX($K54,AI$4),MIN($L54,EOMONTH(AI$4,0)),Assumptions!$F$4:$F$44))/NETWORKDAYS($K54,$L54,Assumptions!$F$4:$F$44)) -> 0 | AJ54: =IF($J54=0,0,MAX(0,NETWORKDAYS(MAX($K54,AJ$4),MIN($L54,EOMONTH(AJ$4,0)),Assumptions!$F$4:$F$44))/NETWORKDAYS($K54,$L54,Assumptions!$F$4:$F$44)) -> 0 | AK54: =IF($J54=0,0,MAX(0,NETWORKDAYS(MAX($K54,AK$4),MIN($L54,EOMONTH(AK$4,0)),Assumptions!$F$4:$F$44))/NETWORKDAYS($K54,$L54,Assumptions!$F$4:$F$44)) -> 0 | AL54: =IF($J54=0,0,MAX(0,NETWORKDAYS(MAX($K54,AL$4),MIN($L54,EOMONTH(AL$4,0)),Assumptions!$F$4:$F$44))/NETWORKDAYS($K54,$L54,Assumptions!$F$4:$F$44)) -> 0 | AM54: =IF($J54=0,0,MAX(0,NETWORKDAYS(MAX($K54,AM$4),MIN($L54,EOMONTH(AM$4,0)),Assumptions!$F$4:$F$44))/NETWORKDAYS($K54,$L54,Assumptions!$F$4:$F$44)) -> 0 | ... BC54: =IF($J54=0,0,MAX(0,NETWORKDAYS(MAX($K54,BC$4),MIN($L54,EOMONTH(BC$4,0)),Assumptions!$F$4:$F$44))/NETWORKDAYS($K54,$L54,Assumptions!$F$4:$F$44)) -> 0
A55: 51 | B55: 3.7.2 | C55: 3 | D55: Subtask | E55: Build and unit tests | F55: Phase 1 | G55: Platform | H55: BE | I55: 35 | J55: 24 | K55: =WORKDAY(Assumptions!$C$4,I55,Assumptions!$F$4:$F$44) -> 46377 | L55: =IF(J55=0,K55,WORKDAY(K55,J55-1,Assumptions!$F$4:$F$44)) -> 46408 | N55: 0 | O55: 4 | P55: 0 | Q55: 16 | R55: 0 | S55: 0 | T55: 0 | U55: 0 | V55: 0 | W55: 0 | X55: 0 | Y55: =SUM(N55:X55) -> 20 | Z55: =Y55*(1+Assumptions!$C$5) -> 23 | AA55: Working service | AB55: Not started | AD55: 0 | AF55: =IF($J55=0,0,MAX(0,NETWORKDAYS(MAX($K55,AF$4),MIN($L55,EOMONTH(AF$4,0)),Assumptions!$F$4:$F$44))/NETWORKDAYS($K55,$L55,Assumptions!$F$4:$F$44)) -> 0 | AG55: =IF($J55=0,0,MAX(0,NETWORKDAYS(MAX($K55,AG$4),MIN($L55,EOMONTH(AG$4,0)),Assumptions!$F$4:$F$44))/NETWORKDAYS($K55,$L55,Assumptions!$F$4:$F$44)) -> 0.375 | AH55: =IF($J55=0,0,MAX(0,NETWORKDAYS(MAX($K55,AH$4),MIN($L55,EOMONTH(AH$4,0)),Assumptions!$F$4:$F$44))/NETWORKDAYS($K55,$L55,Assumptions!$F$4:$F$44)) -> 0.625 | AI55: =IF($J55=0,0,MAX(0,NETWORKDAYS(MAX($K55,AI$4),MIN($L55,EOMONTH(AI$4,0)),Assumptions!$F$4:$F$44))/NETWORKDAYS($K55,$L55,Assumptions!$F$4:$F$44)) -> 0 | AJ55: =IF($J55=0,0,MAX(0,NETWORKDAYS(MAX($K55,AJ$4),MIN($L55,EOMONTH(AJ$4,0)),Assumptions!$F$4:$F$44))/NETWORKDAYS($K55,$L55,Assumptions!$F$4:$F$44)) -> 0 | AK55: =IF($J55=0,0,MAX(0,NETWORKDAYS(MAX($K55,AK$4),MIN($L55,EOMONTH(AK$4,0)),Assumptions!$F$4:$F$44))/NETWORKDAYS($K55,$L55,Assumptions!$F$4:$F$44)) -> 0 | AL55: =IF($J55=0,0,MAX(0,NETWORKDAYS(MAX($K55,AL$4),MIN($L55,EOMONTH(AL$4,0)),Assumptions!$F$4:$F$44))/NETWORKDAYS($K55,$L55,Assumptions!$F$4:$F$44)) -> 0 | AM55: =IF($J55=0,0,MAX(0,NETWORKDAYS(MAX($K55,AM$4),MIN($L55,EOMONTH(AM$4,0)),Assumptions!$F$4:$F$44))/NETWORKDAYS($K55,$L55,Assumptions!$F$4:$F$44)) -> 0 | ... BC55: =IF($J55=0,0,MAX(0,NETWORKDAYS(MAX($K55,BC$4),MIN($L55,EOMONTH(BC$4,0)),Assumptions!$F$4:$F$44))/NETWORKDAYS($K55,$L55,Assumptions!$F$4:$F$44)) -> 0
A56: 52 | B56: 3.7.3 | C56: 3 | D56: Subtask | E56: Component, security and contract tests | F56: Phase 1 | G56: Platform | H56: QA | I56: 56 | J56: 10 | K56: =WORKDAY(Assumptions!$C$4,I56,Assumptions!$F$4:$F$44) -> 46406 | L56: =IF(J56=0,K56,WORKDAY(K56,J56-1,Assumptions!$F$4:$F$44)) -> 46419 | N56: 0 | O56: 0 | P56: 0 | Q56: 2 | R56: 0 | S56: 0 | T56: 0 | U56: 0 | V56: 6 | W56: 0 | X56: 0 | Y56: =SUM(N56:X56) -> 8 | Z56: =Y56*(1+Assumptions!$C$5) -> 9.2 | AA56: Test report | AB56: Not started | AD56: 0 | AF56: =IF($J56=0,0,MAX(0,NETWORKDAYS(MAX($K56,AF$4),MIN($L56,EOMONTH(AF$4,0)),Assumptions!$F$4:$F$44))/NETWORKDAYS($K56,$L56,Assumptions!$F$4:$F$44)) -> 0 | AG56: =IF($J56=0,0,MAX(0,NETWORKDAYS(MAX($K56,AG$4),MIN($L56,EOMONTH(AG$4,0)),Assumptions!$F$4:$F$44))/NETWORKDAYS($K56,$L56,Assumptions!$F$4:$F$44)) -> 0 | AH56: =IF($J56=0,0,MAX(0,NETWORKDAYS(MAX($K56,AH$4),MIN($L56,EOMONTH(AH$4,0)),Assumptions!$F$4:$F$44))/NETWORKDAYS($K56,$L56,Assumptions!$F$4:$F$44)) -> 0.9 | AI56: =IF($J56=0,0,MAX(0,NETWORKDAYS(MAX($K56,AI$4),MIN($L56,EOMONTH(AI$4,0)),Assumptions!$F$4:$F$44))/NETWORKDAYS($K56,$L56,Assumptions!$F$4:$F$44)) -> 0.1 | AJ56: =IF($J56=0,0,MAX(0,NETWORKDAYS(MAX($K56,AJ$4),MIN($L56,EOMONTH(AJ$4,0)),Assumptions!$F$4:$F$44))/NETWORKDAYS($K56,$L56,Assumptions!$F$4:$F$44)) -> 0 | AK56: =IF($J56=0,0,MAX(0,NETWORKDAYS(MAX($K56,AK$4),MIN($L56,EOMONTH(AK$4,0)),Assumptions!$F$4:$F$44))/NETWORKDAYS($K56,$L56,Assumptions!$F$4:$F$44)) -> 0 | AL56: =IF($J56=0,0,MAX(0,NETWORKDAYS(MAX($K56,AL$4),MIN($L56,EOMONTH(AL$4,0)),Assumptions!$F$4:$F$44))/NETWORKDAYS($K56,$L56,Assumptions!$F$4:$F$44)) -> 0 | AM56: =IF($J56=0,0,MAX(0,NETWORKDAYS(MAX($K56,AM$4),MIN($L56,EOMONTH(AM$4,0)),Assumptions!$F$4:$F$44))/NETWORKDAYS($K56,$L56,Assumptions!$F$4:$F$44)) -> 0 | ... BC56: =IF($J56=0,0,MAX(0,NETWORKDAYS(MAX($K56,BC$4),MIN($L56,EOMONTH(BC$4,0)),Assumptions!$F$4:$F$44))/NETWORKDAYS($K56,$L56,Assumptions!$F$4:$F$44)) -> 0
A57: 53 | B57: 3.8 | C57: 2 | D57: Task | E57: GIS base: PostGIS, GeoServer, base map, imagery, ward layers | F57: Phase 1 | G57: Platform | J57: =NETWORKDAYS(K57,L57,Assumptions!$F$4:$F$44) -> 56 | K57: =MIN(K58:K60) -> 46350 | L57: =MAX(L58:L60) -> 46427 | N57: =SUMPRODUCT(($C$58:$C$60=3)*(N58:N60)) -> 0 | O57: =SUMPRODUCT(($C$58:$C$60=3)*(O58:O60)) -> 0 | P57: =SUMPRODUCT(($C$58:$C$60=3)*(P58:P60)) -> 2 | Q57: =SUMPRODUCT(($C$58:$C$60=3)*(Q58:Q60)) -> 9 | R57: =SUMPRODUCT(($C$58:$C$60=3)*(R58:R60)) -> 9 | S57: =SUMPRODUCT(($C$58:$C$60=3)*(S58:S60)) -> 0 | T57: =SUMPRODUCT(($C$58:$C$60=3)*(T58:T60)) -> 32 | U57: =SUMPRODUCT(($C$58:$C$60=3)*(U58:U60)) -> 0 | ... X57: =SUMPRODUCT(($C$58:$C$60=3)*(X58:X60)) -> 0 | Y57: =SUM(N57:X57) -> 57 | Z57: =Y57*(1+Assumptions!$C$5) -> 65.55 | AA57: PLT-FR-005, I-20 interim | AF57: 0 | AG57: 0 | AH57: 0 | AI57: 0 | AJ57: 0 | AK57: 0 | AL57: 0 | AM57: 0 | AN57: 0 | AO57: 0 | AP57: 0 | AQ57: 0 | AR57: 0 | AS57: 0 | AT57: 0 | AU57: 0 | AV57: 0 | AW57: 0 | AX57: 0 | AY57: 0 | AZ57: 0 | BA57: 0 | BB57: 0 | BC57: 0
A58: 54 | B58: 3.8.1 | C58: 3 | D58: Subtask | E58: Detailed design and contracts | F58: Phase 1 | G58: Platform | H58: ARC | I58: 16 | J58: 11 | K58: =WORKDAY(Assumptions!$C$4,I58,Assumptions!$F$4:$F$44) -> 46350 | L58: =IF(J58=0,K58,WORKDAY(K58,J58-1,Assumptions!$F$4:$F$44)) -> 46364 | M58: 20 | N58: 0 | O58: 0 | P58: 2 | Q58: 1 | R58: 0 | S58: 0 | T58: 0 | U58: 0 | V58: 0 | W58: 0 | X58: 0 | Y58: =SUM(N58:X58) -> 3 | Z58: =Y58*(1+Assumptions!$C$5) -> 3.45 | AA58: Design note, OpenAPI and event schemas | AB58: Not started | AD58: 0 | AF58: =IF($J58=0,0,MAX(0,NETWORKDAYS(MAX($K58,AF$4),MIN($L58,EOMONTH(AF$4,0)),Assumptions!$F$4:$F$44))/NETWORKDAYS($K58,$L58,Assumptions!$F$4:$F$44)) -> 0.45454545 | AG58: =IF($J58=0,0,MAX(0,NETWORKDAYS(MAX($K58,AG$4),MIN($L58,EOMONTH(AG$4,0)),Assumptions!$F$4:$F$44))/NETWORKDAYS($K58,$L58,Assumptions!$F$4:$F$44)) -> 0.54545455 | AH58: =IF($J58=0,0,MAX(0,NETWORKDAYS(MAX($K58,AH$4),MIN($L58,EOMONTH(AH$4,0)),Assumptions!$F$4:$F$44))/NETWORKDAYS($K58,$L58,Assumptions!$F$4:$F$44)) -> 0 | AI58: =IF($J58=0,0,MAX(0,NETWORKDAYS(MAX($K58,AI$4),MIN($L58,EOMONTH(AI$4,0)),Assumptions!$F$4:$F$44))/NETWORKDAYS($K58,$L58,Assumptions!$F$4:$F$44)) -> 0 | AJ58: =IF($J58=0,0,MAX(0,NETWORKDAYS(MAX($K58,AJ$4),MIN($L58,EOMONTH(AJ$4,0)),Assumptions!$F$4:$F$44))/NETWORKDAYS($K58,$L58,Assumptions!$F$4:$F$44)) -> 0 | AK58: =IF($J58=0,0,MAX(0,NETWORKDAYS(MAX($K58,AK$4),MIN($L58,EOMONTH(AK$4,0)),Assumptions!$F$4:$F$44))/NETWORKDAYS($K58,$L58,Assumptions!$F$4:$F$44)) -> 0 | AL58: =IF($J58=0,0,MAX(0,NETWORKDAYS(MAX($K58,AL$4),MIN($L58,EOMONTH(AL$4,0)),Assumptions!$F$4:$F$44))/NETWORKDAYS($K58,$L58,Assumptions!$F$4:$F$44)) -> 0 | AM58: =IF($J58=0,0,MAX(0,NETWORKDAYS(MAX($K58,AM$4),MIN($L58,EOMONTH(AM$4,0)),Assumptions!$F$4:$F$44))/NETWORKDAYS($K58,$L58,Assumptions!$F$4:$F$44)) -> 0 | ... BC58: =IF($J58=0,0,MAX(0,NETWORKDAYS(MAX($K58,BC$4),MIN($L58,EOMONTH(BC$4,0)),Assumptions!$F$4:$F$44))/NETWORKDAYS($K58,$L58,Assumptions!$F$4:$F$44)) -> 0
A59: 55 | B59: 3.8.2 | C59: 3 | D59: Subtask | E59: Build and unit tests | F59: Phase 1 | G59: Platform | H59: GIS | I59: 27 | J59: 34 | K59: =WORKDAY(Assumptions!$C$4,I59,Assumptions!$F$4:$F$44) -> 46365 | L59: =IF(J59=0,K59,WORKDAY(K59,J59-1,Assumptions!$F$4:$F$44)) -> 46412 | N59: 0 | O59: 0 | P59: 0 | Q59: 7 | R59: 9 | S59: 0 | T59: 32 | U59: 0 | V59: 0 | W59: 0 | X59: 0 | Y59: =SUM(N59:X59) -> 48 | Z59: =Y59*(1+Assumptions!$C$5) -> 55.2 | AA59: Working service | AB59: Not started | AD59: 0 | AF59: =IF($J59=0,0,MAX(0,NETWORKDAYS(MAX($K59,AF$4),MIN($L59,EOMONTH(AF$4,0)),Assumptions!$F$4:$F$44))/NETWORKDAYS($K59,$L59,Assumptions!$F$4:$F$44)) -> 0 | AG59: =IF($J59=0,0,MAX(0,NETWORKDAYS(MAX($K59,AG$4),MIN($L59,EOMONTH(AG$4,0)),Assumptions!$F$4:$F$44))/NETWORKDAYS($K59,$L59,Assumptions!$F$4:$F$44)) -> 0.5 | AH59: =IF($J59=0,0,MAX(0,NETWORKDAYS(MAX($K59,AH$4),MIN($L59,EOMONTH(AH$4,0)),Assumptions!$F$4:$F$44))/NETWORKDAYS($K59,$L59,Assumptions!$F$4:$F$44)) -> 0.5 | AI59: =IF($J59=0,0,MAX(0,NETWORKDAYS(MAX($K59,AI$4),MIN($L59,EOMONTH(AI$4,0)),Assumptions!$F$4:$F$44))/NETWORKDAYS($K59,$L59,Assumptions!$F$4:$F$44)) -> 0 | AJ59: =IF($J59=0,0,MAX(0,NETWORKDAYS(MAX($K59,AJ$4),MIN($L59,EOMONTH(AJ$4,0)),Assumptions!$F$4:$F$44))/NETWORKDAYS($K59,$L59,Assumptions!$F$4:$F$44)) -> 0 | AK59: =IF($J59=0,0,MAX(0,NETWORKDAYS(MAX($K59,AK$4),MIN($L59,EOMONTH(AK$4,0)),Assumptions!$F$4:$F$44))/NETWORKDAYS($K59,$L59,Assumptions!$F$4:$F$44)) -> 0 | AL59: =IF($J59=0,0,MAX(0,NETWORKDAYS(MAX($K59,AL$4),MIN($L59,EOMONTH(AL$4,0)),Assumptions!$F$4:$F$44))/NETWORKDAYS($K59,$L59,Assumptions!$F$4:$F$44)) -> 0 | AM59: =IF($J59=0,0,MAX(0,NETWORKDAYS(MAX($K59,AM$4),MIN($L59,EOMONTH(AM$4,0)),Assumptions!$F$4:$F$44))/NETWORKDAYS($K59,$L59,Assumptions!$F$4:$F$44)) -> 0 | ... BC59: =IF($J59=0,0,MAX(0,NETWORKDAYS(MAX($K59,BC$4),MIN($L59,EOMONTH(BC$4,0)),Assumptions!$F$4:$F$44))/NETWORKDAYS($K59,$L59,Assumptions!$F$4:$F$44)) -> 0
A60: 56 | B60: 3.8.3 | C60: 3 | D60: Subtask | E60: Component, security and contract tests | F60: Phase 1 | G60: Platform | H60: QA | I60: 58 | J60: 14 | K60: =WORKDAY(Assumptions!$C$4,I60,Assumptions!$F$4:$F$44) -> 46408 | L60: =IF(J60=0,K60,WORKDAY(K60,J60-1,Assumptions!$F$4:$F$44)) -> 46427 | N60: 0 | O60: 0 | P60: 0 | Q60: 1 | R60: 0 | S60: 0 | T60: 0 | U60: 0 | V60: 5 | W60: 0 | X60: 0 | Y60: =SUM(N60:X60) -> 6 | Z60: =Y60*(1+Assumptions!$C$5) -> 6.9 | AA60: Test report | AB60: Not started | AD60: 0 | AF60: =IF($J60=0,0,MAX(0,NETWORKDAYS(MAX($K60,AF$4),MIN($L60,EOMONTH(AF$4,0)),Assumptions!$F$4:$F$44))/NETWORKDAYS($K60,$L60,Assumptions!$F$4:$F$44)) -> 0 | AG60: =IF($J60=0,0,MAX(0,NETWORKDAYS(MAX($K60,AG$4),MIN($L60,EOMONTH(AG$4,0)),Assumptions!$F$4:$F$44))/NETWORKDAYS($K60,$L60,Assumptions!$F$4:$F$44)) -> 0 | AH60: =IF($J60=0,0,MAX(0,NETWORKDAYS(MAX($K60,AH$4),MIN($L60,EOMONTH(AH$4,0)),Assumptions!$F$4:$F$44))/NETWORKDAYS($K60,$L60,Assumptions!$F$4:$F$44)) -> 0.5 | AI60: =IF($J60=0,0,MAX(0,NETWORKDAYS(MAX($K60,AI$4),MIN($L60,EOMONTH(AI$4,0)),Assumptions!$F$4:$F$44))/NETWORKDAYS($K60,$L60,Assumptions!$F$4:$F$44)) -> 0.5 | AJ60: =IF($J60=0,0,MAX(0,NETWORKDAYS(MAX($K60,AJ$4),MIN($L60,EOMONTH(AJ$4,0)),Assumptions!$F$4:$F$44))/NETWORKDAYS($K60,$L60,Assumptions!$F$4:$F$44)) -> 0 | AK60: =IF($J60=0,0,MAX(0,NETWORKDAYS(MAX($K60,AK$4),MIN($L60,EOMONTH(AK$4,0)),Assumptions!$F$4:$F$44))/NETWORKDAYS($K60,$L60,Assumptions!$F$4:$F$44)) -> 0 | AL60: =IF($J60=0,0,MAX(0,NETWORKDAYS(MAX($K60,AL$4),MIN($L60,EOMONTH(AL$4,0)),Assumptions!$F$4:$F$44))/NETWORKDAYS($K60,$L60,Assumptions!$F$4:$F$44)) -> 0 | AM60: =IF($J60=0,0,MAX(0,NETWORKDAYS(MAX($K60,AM$4),MIN($L60,EOMONTH(AM$4,0)),Assumptions!$F$4:$F$44))/NETWORKDAYS($K60,$L60,Assumptions!$F$4:$F$44)) -> 0 | ... BC60: =IF($J60=0,0,MAX(0,NETWORKDAYS(MAX($K60,BC$4),MIN($L60,EOMONTH(BC$4,0)),Assumptions!$F$4:$F$44))/NETWORKDAYS($K60,$L60,Assumptions!$F$4:$F$44)) -> 0
A61: 57 | B61: 3.9 | C61: 2 | D61: Task | E61: Document pipeline: OCR, translation, eSign, anchoring, DigiLocker | F61: Phase 1 | G61: Platform | J61: =NETWORKDAYS(K61,L61,Assumptions!$F$4:$F$44) -> 56 | K61: =MIN(K62:K64) -> 46357 | L61: =MAX(L62:L64) -> 46434 | N61: =SUMPRODUCT(($C$62:$C$64=3)*(N62:N64)) -> 0 | O61: =SUMPRODUCT(($C$62:$C$64=3)*(O62:O64)) -> 0 | P61: =SUMPRODUCT(($C$62:$C$64=3)*(P62:P64)) -> 4 | Q61: =SUMPRODUCT(($C$62:$C$64=3)*(Q62:Q64)) -> 40 | R61: =SUMPRODUCT(($C$62:$C$64=3)*(R62:R64)) -> 0 | S61: =SUMPRODUCT(($C$62:$C$64=3)*(S62:S64)) -> 0 | T61: =SUMPRODUCT(($C$62:$C$64=3)*(T62:T64)) -> 0 | U61: =SUMPRODUCT(($C$62:$C$64=3)*(U62:U64)) -> 4 | ... X61: =SUMPRODUCT(($C$62:$C$64=3)*(X62:X64)) -> 0 | Y61: =SUM(N61:X61) -> 58 | Z61: =Y61*(1+Assumptions!$C$5) -> 66.7 | AA61: PLT-FR-006, 025 to 027 | AF61: 0 | AG61: 0 | AH61: 0 | AI61: 0 | AJ61: 0 | AK61: 0 | AL61: 0 | AM61: 0 | AN61: 0 | AO61: 0 | AP61: 0 | AQ61: 0 | AR61: 0 | AS61: 0 | AT61: 0 | AU61: 0 | AV61: 0 | AW61: 0 | AX61: 0 | AY61: 0 | AZ61: 0 | BA61: 0 | BB61: 0 | BC61: 0
A62: 58 | B62: 3.9.1 | C62: 3 | D62: Subtask | E62: Detailed design and contracts | F62: Phase 1 | G62: Platform | H62: ARC | I62: 21 | J62: 11 | K62: =WORKDAY(Assumptions!$C$4,I62,Assumptions!$F$4:$F$44) -> 46357 | L62: =IF(J62=0,K62,WORKDAY(K62,J62-1,Assumptions!$F$4:$F$44)) -> 46371 | M62: 20 | N62: 0 | O62: 0 | P62: 4 | Q62: 4 | R62: 0 | S62: 0 | T62: 0 | U62: 0 | V62: 0 | W62: 0 | X62: 0 | Y62: =SUM(N62:X62) -> 8 | Z62: =Y62*(1+Assumptions!$C$5) -> 9.2 | AA62: Design note, OpenAPI and event schemas | AB62: Not started | AD62: 0 | AF62: =IF($J62=0,0,MAX(0,NETWORKDAYS(MAX($K62,AF$4),MIN($L62,EOMONTH(AF$4,0)),Assumptions!$F$4:$F$44))/NETWORKDAYS($K62,$L62,Assumptions!$F$4:$F$44)) -> 0 | AG62: =IF($J62=0,0,MAX(0,NETWORKDAYS(MAX($K62,AG$4),MIN($L62,EOMONTH(AG$4,0)),Assumptions!$F$4:$F$44))/NETWORKDAYS($K62,$L62,Assumptions!$F$4:$F$44)) -> 1 | AH62: =IF($J62=0,0,MAX(0,NETWORKDAYS(MAX($K62,AH$4),MIN($L62,EOMONTH(AH$4,0)),Assumptions!$F$4:$F$44))/NETWORKDAYS($K62,$L62,Assumptions!$F$4:$F$44)) -> 0 | AI62: =IF($J62=0,0,MAX(0,NETWORKDAYS(MAX($K62,AI$4),MIN($L62,EOMONTH(AI$4,0)),Assumptions!$F$4:$F$44))/NETWORKDAYS($K62,$L62,Assumptions!$F$4:$F$44)) -> 0 | AJ62: =IF($J62=0,0,MAX(0,NETWORKDAYS(MAX($K62,AJ$4),MIN($L62,EOMONTH(AJ$4,0)),Assumptions!$F$4:$F$44))/NETWORKDAYS($K62,$L62,Assumptions!$F$4:$F$44)) -> 0 | AK62: =IF($J62=0,0,MAX(0,NETWORKDAYS(MAX($K62,AK$4),MIN($L62,EOMONTH(AK$4,0)),Assumptions!$F$4:$F$44))/NETWORKDAYS($K62,$L62,Assumptions!$F$4:$F$44)) -> 0 | AL62: =IF($J62=0,0,MAX(0,NETWORKDAYS(MAX($K62,AL$4),MIN($L62,EOMONTH(AL$4,0)),Assumptions!$F$4:$F$44))/NETWORKDAYS($K62,$L62,Assumptions!$F$4:$F$44)) -> 0 | AM62: =IF($J62=0,0,MAX(0,NETWORKDAYS(MAX($K62,AM$4),MIN($L62,EOMONTH(AM$4,0)),Assumptions!$F$4:$F$44))/NETWORKDAYS($K62,$L62,Assumptions!$F$4:$F$44)) -> 0 | ... BC62: =IF($J62=0,0,MAX(0,NETWORKDAYS(MAX($K62,BC$4),MIN($L62,EOMONTH(BC$4,0)),Assumptions!$F$4:$F$44))/NETWORKDAYS($K62,$L62,Assumptions!$F$4:$F$44)) -> 0
A63: 59 | B63: 3.9.2 | C63: 3 | D63: Subtask | E63: Build and unit tests | F63: Phase 1 | G63: Platform | H63: BE | I63: 32 | J63: 34 | K63: =WORKDAY(Assumptions!$C$4,I63,Assumptions!$F$4:$F$44) -> 46372 | L63: =IF(J63=0,K63,WORKDAY(K63,J63-1,Assumptions!$F$4:$F$44)) -> 46419 | N63: 0 | O63: 0 | P63: 0 | Q63: 32 | R63: 0 | S63: 0 | T63: 0 | U63: 4 | V63: 0 | W63: 0 | X63: 0 | Y63: =SUM(N63:X63) -> 36 | Z63: =Y63*(1+Assumptions!$C$5) -> 41.4 | AA63: Working service | AB63: Not started | AD63: 0 | AF63: =IF($J63=0,0,MAX(0,NETWORKDAYS(MAX($K63,AF$4),MIN($L63,EOMONTH(AF$4,0)),Assumptions!$F$4:$F$44))/NETWORKDAYS($K63,$L63,Assumptions!$F$4:$F$44)) -> 0 | AG63: =IF($J63=0,0,MAX(0,NETWORKDAYS(MAX($K63,AG$4),MIN($L63,EOMONTH(AG$4,0)),Assumptions!$F$4:$F$44))/NETWORKDAYS($K63,$L63,Assumptions!$F$4:$F$44)) -> 0.35294118 | AH63: =IF($J63=0,0,MAX(0,NETWORKDAYS(MAX($K63,AH$4),MIN($L63,EOMONTH(AH$4,0)),Assumptions!$F$4:$F$44))/NETWORKDAYS($K63,$L63,Assumptions!$F$4:$F$44)) -> 0.61764706 | AI63: =IF($J63=0,0,MAX(0,NETWORKDAYS(MAX($K63,AI$4),MIN($L63,EOMONTH(AI$4,0)),Assumptions!$F$4:$F$44))/NETWORKDAYS($K63,$L63,Assumptions!$F$4:$F$44)) -> 0.029411765 | AJ63: =IF($J63=0,0,MAX(0,NETWORKDAYS(MAX($K63,AJ$4),MIN($L63,EOMONTH(AJ$4,0)),Assumptions!$F$4:$F$44))/NETWORKDAYS($K63,$L63,Assumptions!$F$4:$F$44)) -> 0 | AK63: =IF($J63=0,0,MAX(0,NETWORKDAYS(MAX($K63,AK$4),MIN($L63,EOMONTH(AK$4,0)),Assumptions!$F$4:$F$44))/NETWORKDAYS($K63,$L63,Assumptions!$F$4:$F$44)) -> 0 | AL63: =IF($J63=0,0,MAX(0,NETWORKDAYS(MAX($K63,AL$4),MIN($L63,EOMONTH(AL$4,0)),Assumptions!$F$4:$F$44))/NETWORKDAYS($K63,$L63,Assumptions!$F$4:$F$44)) -> 0 | AM63: =IF($J63=0,0,MAX(0,NETWORKDAYS(MAX($K63,AM$4),MIN($L63,EOMONTH(AM$4,0)),Assumptions!$F$4:$F$44))/NETWORKDAYS($K63,$L63,Assumptions!$F$4:$F$44)) -> 0 | ... BC63: =IF($J63=0,0,MAX(0,NETWORKDAYS(MAX($K63,BC$4),MIN($L63,EOMONTH(BC$4,0)),Assumptions!$F$4:$F$44))/NETWORKDAYS($K63,$L63,Assumptions!$F$4:$F$44)) -> 0
A64: 60 | B64: 3.9.3 | C64: 3 | D64: Subtask | E64: Component, security and contract tests | F64: Phase 1 | G64: Platform | H64: QA | I64: 63 | J64: 14 | K64: =WORKDAY(Assumptions!$C$4,I64,Assumptions!$F$4:$F$44) -> 46415 | L64: =IF(J64=0,K64,WORKDAY(K64,J64-1,Assumptions!$F$4:$F$44)) -> 46434 | N64: 0 | O64: 0 | P64: 0 | Q64: 4 | R64: 0 | S64: 0 | T64: 0 | U64: 0 | V64: 10 | W64: 0 | X64: 0 | Y64: =SUM(N64:X64) -> 14 | Z64: =Y64*(1+Assumptions!$C$5) -> 16.1 | AA64: Test report | AB64: Not started | AD64: 0 | AF64: =IF($J64=0,0,MAX(0,NETWORKDAYS(MAX($K64,AF$4),MIN($L64,EOMONTH(AF$4,0)),Assumptions!$F$4:$F$44))/NETWORKDAYS($K64,$L64,Assumptions!$F$4:$F$44)) -> 0 | AG64: =IF($J64=0,0,MAX(0,NETWORKDAYS(MAX($K64,AG$4),MIN($L64,EOMONTH(AG$4,0)),Assumptions!$F$4:$F$44))/NETWORKDAYS($K64,$L64,Assumptions!$F$4:$F$44)) -> 0 | AH64: =IF($J64=0,0,MAX(0,NETWORKDAYS(MAX($K64,AH$4),MIN($L64,EOMONTH(AH$4,0)),Assumptions!$F$4:$F$44))/NETWORKDAYS($K64,$L64,Assumptions!$F$4:$F$44)) -> 0.14285714 | AI64: =IF($J64=0,0,MAX(0,NETWORKDAYS(MAX($K64,AI$4),MIN($L64,EOMONTH(AI$4,0)),Assumptions!$F$4:$F$44))/NETWORKDAYS($K64,$L64,Assumptions!$F$4:$F$44)) -> 0.85714286 | AJ64: =IF($J64=0,0,MAX(0,NETWORKDAYS(MAX($K64,AJ$4),MIN($L64,EOMONTH(AJ$4,0)),Assumptions!$F$4:$F$44))/NETWORKDAYS($K64,$L64,Assumptions!$F$4:$F$44)) -> 0 | AK64: =IF($J64=0,0,MAX(0,NETWORKDAYS(MAX($K64,AK$4),MIN($L64,EOMONTH(AK$4,0)),Assumptions!$F$4:$F$44))/NETWORKDAYS($K64,$L64,Assumptions!$F$4:$F$44)) -> 0 | AL64: =IF($J64=0,0,MAX(0,NETWORKDAYS(MAX($K64,AL$4),MIN($L64,EOMONTH(AL$4,0)),Assumptions!$F$4:$F$44))/NETWORKDAYS($K64,$L64,Assumptions!$F$4:$F$44)) -> 0 | AM64: =IF($J64=0,0,MAX(0,NETWORKDAYS(MAX($K64,AM$4),MIN($L64,EOMONTH(AM$4,0)),Assumptions!$F$4:$F$44))/NETWORKDAYS($K64,$L64,Assumptions!$F$4:$F$44)) -> 0 | ... BC64: =IF($J64=0,0,MAX(0,NETWORKDAYS(MAX($K64,BC$4),MIN($L64,EOMONTH(BC$4,0)),Assumptions!$F$4:$F$44))/NETWORKDAYS($K64,$L64,Assumptions!$F$4:$F$44)) -> 0
A65: 61 | B65: 3.10 | C65: 2 | D65: Task | E65: Search service (OpenSearch, Indic analysers) | F65: Phase 1 | G65: Platform | J65: =NETWORKDAYS(K65,L65,Assumptions!$F$4:$F$44) -> 40 | K65: =MIN(K66:K68) -> 46372 | L65: =MAX(L66:L68) -> 46427 | N65: =SUMPRODUCT(($C$66:$C$68=3)*(N66:N68)) -> 0 | O65: =SUMPRODUCT(($C$66:$C$68=3)*(O66:O68)) -> 0 | P65: =SUMPRODUCT(($C$66:$C$68=3)*(P66:P68)) -> 2 | Q65: =SUMPRODUCT(($C$66:$C$68=3)*(Q66:Q68)) -> 18 | R65: =SUMPRODUCT(($C$66:$C$68=3)*(R66:R68)) -> 0 | S65: =SUMPRODUCT(($C$66:$C$68=3)*(S66:S68)) -> 0 | T65: =SUMPRODUCT(($C$66:$C$68=3)*(T66:T68)) -> 0 | U65: =SUMPRODUCT(($C$66:$C$68=3)*(U66:U68)) -> 0 | ... X65: =SUMPRODUCT(($C$66:$C$68=3)*(X66:X68)) -> 0 | Y65: =SUM(N65:X65) -> 24 | Z65: =Y65*(1+Assumptions!$C$5) -> 27.6 | AA65: PLT-FR-014 | AF65: 0 | AG65: 0 | AH65: 0 | AI65: 0 | AJ65: 0 | AK65: 0 | AL65: 0 | AM65: 0 | AN65: 0 | AO65: 0 | AP65: 0 | AQ65: 0 | AR65: 0 | AS65: 0 | AT65: 0 | AU65: 0 | AV65: 0 | AW65: 0 | AX65: 0 | AY65: 0 | AZ65: 0 | BA65: 0 | BB65: 0 | BC65: 0
A66: 62 | B66: 3.10.1 | C66: 3 | D66: Subtask | E66: Detailed design and contracts | F66: Phase 1 | G66: Platform | H66: ARC | I66: 32 | J66: 8 | K66: =WORKDAY(Assumptions!$C$4,I66,Assumptions!$F$4:$F$44) -> 46372 | L66: =IF(J66=0,K66,WORKDAY(K66,J66-1,Assumptions!$F$4:$F$44)) -> 46381 | M66: 20 | N66: 0 | O66: 0 | P66: 2 | Q66: 2 | R66: 0 | S66: 0 | T66: 0 | U66: 0 | V66: 0 | W66: 0 | X66: 0 | Y66: =SUM(N66:X66) -> 4 | Z66: =Y66*(1+Assumptions!$C$5) -> 4.6 | AA66: Design note, OpenAPI and event schemas | AB66: Not started | AD66: 0 | AF66: =IF($J66=0,0,MAX(0,NETWORKDAYS(MAX($K66,AF$4),MIN($L66,EOMONTH(AF$4,0)),Assumptions!$F$4:$F$44))/NETWORKDAYS($K66,$L66,Assumptions!$F$4:$F$44)) -> 0 | AG66: =IF($J66=0,0,MAX(0,NETWORKDAYS(MAX($K66,AG$4),MIN($L66,EOMONTH(AG$4,0)),Assumptions!$F$4:$F$44))/NETWORKDAYS($K66,$L66,Assumptions!$F$4:$F$44)) -> 1 | AH66: =IF($J66=0,0,MAX(0,NETWORKDAYS(MAX($K66,AH$4),MIN($L66,EOMONTH(AH$4,0)),Assumptions!$F$4:$F$44))/NETWORKDAYS($K66,$L66,Assumptions!$F$4:$F$44)) -> 0 | AI66: =IF($J66=0,0,MAX(0,NETWORKDAYS(MAX($K66,AI$4),MIN($L66,EOMONTH(AI$4,0)),Assumptions!$F$4:$F$44))/NETWORKDAYS($K66,$L66,Assumptions!$F$4:$F$44)) -> 0 | AJ66: =IF($J66=0,0,MAX(0,NETWORKDAYS(MAX($K66,AJ$4),MIN($L66,EOMONTH(AJ$4,0)),Assumptions!$F$4:$F$44))/NETWORKDAYS($K66,$L66,Assumptions!$F$4:$F$44)) -> 0 | AK66: =IF($J66=0,0,MAX(0,NETWORKDAYS(MAX($K66,AK$4),MIN($L66,EOMONTH(AK$4,0)),Assumptions!$F$4:$F$44))/NETWORKDAYS($K66,$L66,Assumptions!$F$4:$F$44)) -> 0 | AL66: =IF($J66=0,0,MAX(0,NETWORKDAYS(MAX($K66,AL$4),MIN($L66,EOMONTH(AL$4,0)),Assumptions!$F$4:$F$44))/NETWORKDAYS($K66,$L66,Assumptions!$F$4:$F$44)) -> 0 | AM66: =IF($J66=0,0,MAX(0,NETWORKDAYS(MAX($K66,AM$4),MIN($L66,EOMONTH(AM$4,0)),Assumptions!$F$4:$F$44))/NETWORKDAYS($K66,$L66,Assumptions!$F$4:$F$44)) -> 0 | ... BC66: =IF($J66=0,0,MAX(0,NETWORKDAYS(MAX($K66,BC$4),MIN($L66,EOMONTH(BC$4,0)),Assumptions!$F$4:$F$44))/NETWORKDAYS($K66,$L66,Assumptions!$F$4:$F$44)) -> 0
A67: 63 | B67: 3.10.2 | C67: 3 | D67: Subtask | E67: Build and unit tests | F67: Phase 1 | G67: Platform | H67: BE | I67: 40 | J67: 24 | K67: =WORKDAY(Assumptions!$C$4,I67,Assumptions!$F$4:$F$44) -> 46384 | L67: =IF(J67=0,K67,WORKDAY(K67,J67-1,Assumptions!$F$4:$F$44)) -> 46415 | N67: 0 | O67: 0 | P67: 0 | Q67: 14 | R67: 0 | S67: 0 | T67: 0 | U67: 0 | V67: 0 | W67: 0 | X67: 0 | Y67: =SUM(N67:X67) -> 14 | Z67: =Y67*(1+Assumptions!$C$5) -> 16.1 | AA67: Working service | AB67: Not started | AD67: 0 | AF67: =IF($J67=0,0,MAX(0,NETWORKDAYS(MAX($K67,AF$4),MIN($L67,EOMONTH(AF$4,0)),Assumptions!$F$4:$F$44))/NETWORKDAYS($K67,$L67,Assumptions!$F$4:$F$44)) -> 0 | AG67: =IF($J67=0,0,MAX(0,NETWORKDAYS(MAX($K67,AG$4),MIN($L67,EOMONTH(AG$4,0)),Assumptions!$F$4:$F$44))/NETWORKDAYS($K67,$L67,Assumptions!$F$4:$F$44)) -> 0.16666667 | AH67: =IF($J67=0,0,MAX(0,NETWORKDAYS(MAX($K67,AH$4),MIN($L67,EOMONTH(AH$4,0)),Assumptions!$F$4:$F$44))/NETWORKDAYS($K67,$L67,Assumptions!$F$4:$F$44)) -> 0.83333333 | AI67: =IF($J67=0,0,MAX(0,NETWORKDAYS(MAX($K67,AI$4),MIN($L67,EOMONTH(AI$4,0)),Assumptions!$F$4:$F$44))/NETWORKDAYS($K67,$L67,Assumptions!$F$4:$F$44)) -> 0 | AJ67: =IF($J67=0,0,MAX(0,NETWORKDAYS(MAX($K67,AJ$4),MIN($L67,EOMONTH(AJ$4,0)),Assumptions!$F$4:$F$44))/NETWORKDAYS($K67,$L67,Assumptions!$F$4:$F$44)) -> 0 | AK67: =IF($J67=0,0,MAX(0,NETWORKDAYS(MAX($K67,AK$4),MIN($L67,EOMONTH(AK$4,0)),Assumptions!$F$4:$F$44))/NETWORKDAYS($K67,$L67,Assumptions!$F$4:$F$44)) -> 0 | AL67: =IF($J67=0,0,MAX(0,NETWORKDAYS(MAX($K67,AL$4),MIN($L67,EOMONTH(AL$4,0)),Assumptions!$F$4:$F$44))/NETWORKDAYS($K67,$L67,Assumptions!$F$4:$F$44)) -> 0 | AM67: =IF($J67=0,0,MAX(0,NETWORKDAYS(MAX($K67,AM$4),MIN($L67,EOMONTH(AM$4,0)),Assumptions!$F$4:$F$44))/NETWORKDAYS($K67,$L67,Assumptions!$F$4:$F$44)) -> 0 | ... BC67: =IF($J67=0,0,MAX(0,NETWORKDAYS(MAX($K67,BC$4),MIN($L67,EOMONTH(BC$4,0)),Assumptions!$F$4:$F$44))/NETWORKDAYS($K67,$L67,Assumptions!$F$4:$F$44)) -> 0
A68: 64 | B68: 3.10.3 | C68: 3 | D68: Subtask | E68: Component, security and contract tests | F68: Phase 1 | G68: Platform | H68: QA | I68: 62 | J68: 10 | K68: =WORKDAY(Assumptions!$C$4,I68,Assumptions!$F$4:$F$44) -> 46414 | L68: =IF(J68=0,K68,WORKDAY(K68,J68-1,Assumptions!$F$4:$F$44)) -> 46427 | N68: 0 | O68: 0 | P68: 0 | Q68: 2 | R68: 0 | S68: 0 | T68: 0 | U68: 0 | V68: 4 | W68: 0 | X68: 0 | Y68: =SUM(N68:X68) -> 6 | Z68: =Y68*(1+Assumptions!$C$5) -> 6.9 | AA68: Test report | AB68: Not started | AD68: 0 | AF68: =IF($J68=0,0,MAX(0,NETWORKDAYS(MAX($K68,AF$4),MIN($L68,EOMONTH(AF$4,0)),Assumptions!$F$4:$F$44))/NETWORKDAYS($K68,$L68,Assumptions!$F$4:$F$44)) -> 0 | AG68: =IF($J68=0,0,MAX(0,NETWORKDAYS(MAX($K68,AG$4),MIN($L68,EOMONTH(AG$4,0)),Assumptions!$F$4:$F$44))/NETWORKDAYS($K68,$L68,Assumptions!$F$4:$F$44)) -> 0 | AH68: =IF($J68=0,0,MAX(0,NETWORKDAYS(MAX($K68,AH$4),MIN($L68,EOMONTH(AH$4,0)),Assumptions!$F$4:$F$44))/NETWORKDAYS($K68,$L68,Assumptions!$F$4:$F$44)) -> 0.3 | AI68: =IF($J68=0,0,MAX(0,NETWORKDAYS(MAX($K68,AI$4),MIN($L68,EOMONTH(AI$4,0)),Assumptions!$F$4:$F$44))/NETWORKDAYS($K68,$L68,Assumptions!$F$4:$F$44)) -> 0.7 | AJ68: =IF($J68=0,0,MAX(0,NETWORKDAYS(MAX($K68,AJ$4),MIN($L68,EOMONTH(AJ$4,0)),Assumptions!$F$4:$F$44))/NETWORKDAYS($K68,$L68,Assumptions!$F$4:$F$44)) -> 0 | AK68: =IF($J68=0,0,MAX(0,NETWORKDAYS(MAX($K68,AK$4),MIN($L68,EOMONTH(AK$4,0)),Assumptions!$F$4:$F$44))/NETWORKDAYS($K68,$L68,Assumptions!$F$4:$F$44)) -> 0 | AL68: =IF($J68=0,0,MAX(0,NETWORKDAYS(MAX($K68,AL$4),MIN($L68,EOMONTH(AL$4,0)),Assumptions!$F$4:$F$44))/NETWORKDAYS($K68,$L68,Assumptions!$F$4:$F$44)) -> 0 | AM68: =IF($J68=0,0,MAX(0,NETWORKDAYS(MAX($K68,AM$4),MIN($L68,EOMONTH(AM$4,0)),Assumptions!$F$4:$F$44))/NETWORKDAYS($K68,$L68,Assumptions!$F$4:$F$44)) -> 0 | ... BC68: =IF($J68=0,0,MAX(0,NETWORKDAYS(MAX($K68,BC$4),MIN($L68,EOMONTH(BC$4,0)),Assumptions!$F$4:$F$44))/NETWORKDAYS($K68,$L68,Assumptions!$F$4:$F$44)) -> 0
A69: 65 | B69: 3.11 | C69: 2 | D69: Task | E69: Audit service, SIEM feed and CERT-In logging | F69: Phase 1 | G69: Platform | J69: =NETWORKDAYS(K69,L69,Assumptions!$F$4:$F$44) -> 40 | K69: =MIN(K70:K72) -> 46372 | L69: =MAX(L70:L72) -> 46427 | N69: =SUMPRODUCT(($C$70:$C$72=3)*(N70:N72)) -> 0 | O69: =SUMPRODUCT(($C$70:$C$72=3)*(O70:O72)) -> 0 | P69: =SUMPRODUCT(($C$70:$C$72=3)*(P70:P72)) -> 2 | Q69: =SUMPRODUCT(($C$70:$C$72=3)*(Q70:Q72)) -> 11 | R69: =SUMPRODUCT(($C$70:$C$72=3)*(R70:R72)) -> 0 | S69: =SUMPRODUCT(($C$70:$C$72=3)*(S70:S72)) -> 0 | T69: =SUMPRODUCT(($C$70:$C$72=3)*(T70:T72)) -> 0 | U69: =SUMPRODUCT(($C$70:$C$72=3)*(U70:U72)) -> 9 | ... X69: =SUMPRODUCT(($C$70:$C$72=3)*(X70:X72)) -> 0 | Y69: =SUM(N69:X69) -> 26 | Z69: =Y69*(1+Assumptions!$C$5) -> 29.9 | AA69: PLT-FR-012, 035 | AF69: 0 | AG69: 0 | AH69: 0 | AI69: 0 | AJ69: 0 | AK69: 0 | AL69: 0 | AM69: 0 | AN69: 0 | AO69: 0 | AP69: 0 | AQ69: 0 | AR69: 0 | AS69: 0 | AT69: 0 | AU69: 0 | AV69: 0 | AW69: 0 | AX69: 0 | AY69: 0 | AZ69: 0 | BA69: 0 | BB69: 0 | BC69: 0
A70: 66 | B70: 3.11.1 | C70: 3 | D70: Subtask | E70: Detailed design and contracts | F70: Phase 1 | G70: Platform | H70: ARC | I70: 32 | J70: 8 | K70: =WORKDAY(Assumptions!$C$4,I70,Assumptions!$F$4:$F$44) -> 46372 | L70: =IF(J70=0,K70,WORKDAY(K70,J70-1,Assumptions!$F$4:$F$44)) -> 46381 | M70: 20 | N70: 0 | O70: 0 | P70: 2 | Q70: 1 | R70: 0 | S70: 0 | T70: 0 | U70: 0 | V70: 0 | W70: 0 | X70: 0 | Y70: =SUM(N70:X70) -> 3 | Z70: =Y70*(1+Assumptions!$C$5) -> 3.45 | AA70: Design note, OpenAPI and event schemas | AB70: Not started | AD70: 0 | AF70: =IF($J70=0,0,MAX(0,NETWORKDAYS(MAX($K70,AF$4),MIN($L70,EOMONTH(AF$4,0)),Assumptions!$F$4:$F$44))/NETWORKDAYS($K70,$L70,Assumptions!$F$4:$F$44)) -> 0 | AG70: =IF($J70=0,0,MAX(0,NETWORKDAYS(MAX($K70,AG$4),MIN($L70,EOMONTH(AG$4,0)),Assumptions!$F$4:$F$44))/NETWORKDAYS($K70,$L70,Assumptions!$F$4:$F$44)) -> 1 | AH70: =IF($J70=0,0,MAX(0,NETWORKDAYS(MAX($K70,AH$4),MIN($L70,EOMONTH(AH$4,0)),Assumptions!$F$4:$F$44))/NETWORKDAYS($K70,$L70,Assumptions!$F$4:$F$44)) -> 0 | AI70: =IF($J70=0,0,MAX(0,NETWORKDAYS(MAX($K70,AI$4),MIN($L70,EOMONTH(AI$4,0)),Assumptions!$F$4:$F$44))/NETWORKDAYS($K70,$L70,Assumptions!$F$4:$F$44)) -> 0 | AJ70: =IF($J70=0,0,MAX(0,NETWORKDAYS(MAX($K70,AJ$4),MIN($L70,EOMONTH(AJ$4,0)),Assumptions!$F$4:$F$44))/NETWORKDAYS($K70,$L70,Assumptions!$F$4:$F$44)) -> 0 | AK70: =IF($J70=0,0,MAX(0,NETWORKDAYS(MAX($K70,AK$4),MIN($L70,EOMONTH(AK$4,0)),Assumptions!$F$4:$F$44))/NETWORKDAYS($K70,$L70,Assumptions!$F$4:$F$44)) -> 0 | AL70: =IF($J70=0,0,MAX(0,NETWORKDAYS(MAX($K70,AL$4),MIN($L70,EOMONTH(AL$4,0)),Assumptions!$F$4:$F$44))/NETWORKDAYS($K70,$L70,Assumptions!$F$4:$F$44)) -> 0 | AM70: =IF($J70=0,0,MAX(0,NETWORKDAYS(MAX($K70,AM$4),MIN($L70,EOMONTH(AM$4,0)),Assumptions!$F$4:$F$44))/NETWORKDAYS($K70,$L70,Assumptions!$F$4:$F$44)) -> 0 | ... BC70: =IF($J70=0,0,MAX(0,NETWORKDAYS(MAX($K70,BC$4),MIN($L70,EOMONTH(BC$4,0)),Assumptions!$F$4:$F$44))/NETWORKDAYS($K70,$L70,Assumptions!$F$4:$F$44)) -> 0
A71: 67 | B71: 3.11.2 | C71: 3 | D71: Subtask | E71: Build and unit tests | F71: Phase 1 | G71: Platform | H71: BE | I71: 40 | J71: 24 | K71: =WORKDAY(Assumptions!$C$4,I71,Assumptions!$F$4:$F$44) -> 46384 | L71: =IF(J71=0,K71,WORKDAY(K71,J71-1,Assumptions!$F$4:$F$44)) -> 46415 | N71: 0 | O71: 0 | P71: 0 | Q71: 9 | R71: 0 | S71: 0 | T71: 0 | U71: 9 | V71: 0 | W71: 0 | X71: 0 | Y71: =SUM(N71:X71) -> 18 | Z71: =Y71*(1+Assumptions!$C$5) -> 20.7 | AA71: Working service | AB71: Not started | AD71: 0 | AF71: =IF($J71=0,0,MAX(0,NETWORKDAYS(MAX($K71,AF$4),MIN($L71,EOMONTH(AF$4,0)),Assumptions!$F$4:$F$44))/NETWORKDAYS($K71,$L71,Assumptions!$F$4:$F$44)) -> 0 | AG71: =IF($J71=0,0,MAX(0,NETWORKDAYS(MAX($K71,AG$4),MIN($L71,EOMONTH(AG$4,0)),Assumptions!$F$4:$F$44))/NETWORKDAYS($K71,$L71,Assumptions!$F$4:$F$44)) -> 0.16666667 | AH71: =IF($J71=0,0,MAX(0,NETWORKDAYS(MAX($K71,AH$4),MIN($L71,EOMONTH(AH$4,0)),Assumptions!$F$4:$F$44))/NETWORKDAYS($K71,$L71,Assumptions!$F$4:$F$44)) -> 0.83333333 | AI71: =IF($J71=0,0,MAX(0,NETWORKDAYS(MAX($K71,AI$4),MIN($L71,EOMONTH(AI$4,0)),Assumptions!$F$4:$F$44))/NETWORKDAYS($K71,$L71,Assumptions!$F$4:$F$44)) -> 0 | AJ71: =IF($J71=0,0,MAX(0,NETWORKDAYS(MAX($K71,AJ$4),MIN($L71,EOMONTH(AJ$4,0)),Assumptions!$F$4:$F$44))/NETWORKDAYS($K71,$L71,Assumptions!$F$4:$F$44)) -> 0 | AK71: =IF($J71=0,0,MAX(0,NETWORKDAYS(MAX($K71,AK$4),MIN($L71,EOMONTH(AK$4,0)),Assumptions!$F$4:$F$44))/NETWORKDAYS($K71,$L71,Assumptions!$F$4:$F$44)) -> 0 | AL71: =IF($J71=0,0,MAX(0,NETWORKDAYS(MAX($K71,AL$4),MIN($L71,EOMONTH(AL$4,0)),Assumptions!$F$4:$F$44))/NETWORKDAYS($K71,$L71,Assumptions!$F$4:$F$44)) -> 0 | AM71: =IF($J71=0,0,MAX(0,NETWORKDAYS(MAX($K71,AM$4),MIN($L71,EOMONTH(AM$4,0)),Assumptions!$F$4:$F$44))/NETWORKDAYS($K71,$L71,Assumptions!$F$4:$F$44)) -> 0 | ... BC71: =IF($J71=0,0,MAX(0,NETWORKDAYS(MAX($K71,BC$4),MIN($L71,EOMONTH(BC$4,0)),Assumptions!$F$4:$F$44))/NETWORKDAYS($K71,$L71,Assumptions!$F$4:$F$44)) -> 0
A72: 68 | B72: 3.11.3 | C72: 3 | D72: Subtask | E72: Component, security and contract tests | F72: Phase 1 | G72: Platform | H72: QA | I72: 62 | J72: 10 | K72: =WORKDAY(Assumptions!$C$4,I72,Assumptions!$F$4:$F$44) -> 46414 | L72: =IF(J72=0,K72,WORKDAY(K72,J72-1,Assumptions!$F$4:$F$44)) -> 46427 | N72: 0 | O72: 0 | P72: 0 | Q72: 1 | R72: 0 | S72: 0 | T72: 0 | U72: 0 | V72: 4 | W72: 0 | X72: 0 | Y72: =SUM(N72:X72) -> 5 | Z72: =Y72*(1+Assumptions!$C$5) -> 5.75 | AA72: Test report | AB72: Not started | AD72: 0 | AF72: =IF($J72=0,0,MAX(0,NETWORKDAYS(MAX($K72,AF$4),MIN($L72,EOMONTH(AF$4,0)),Assumptions!$F$4:$F$44))/NETWORKDAYS($K72,$L72,Assumptions!$F$4:$F$44)) -> 0 | AG72: =IF($J72=0,0,MAX(0,NETWORKDAYS(MAX($K72,AG$4),MIN($L72,EOMONTH(AG$4,0)),Assumptions!$F$4:$F$44))/NETWORKDAYS($K72,$L72,Assumptions!$F$4:$F$44)) -> 0 | AH72: =IF($J72=0,0,MAX(0,NETWORKDAYS(MAX($K72,AH$4),MIN($L72,EOMONTH(AH$4,0)),Assumptions!$F$4:$F$44))/NETWORKDAYS($K72,$L72,Assumptions!$F$4:$F$44)) -> 0.3 | AI72: =IF($J72=0,0,MAX(0,NETWORKDAYS(MAX($K72,AI$4),MIN($L72,EOMONTH(AI$4,0)),Assumptions!$F$4:$F$44))/NETWORKDAYS($K72,$L72,Assumptions!$F$4:$F$44)) -> 0.7 | AJ72: =IF($J72=0,0,MAX(0,NETWORKDAYS(MAX($K72,AJ$4),MIN($L72,EOMONTH(AJ$4,0)),Assumptions!$F$4:$F$44))/NETWORKDAYS($K72,$L72,Assumptions!$F$4:$F$44)) -> 0 | AK72: =IF($J72=0,0,MAX(0,NETWORKDAYS(MAX($K72,AK$4),MIN($L72,EOMONTH(AK$4,0)),Assumptions!$F$4:$F$44))/NETWORKDAYS($K72,$L72,Assumptions!$F$4:$F$44)) -> 0 | AL72: =IF($J72=0,0,MAX(0,NETWORKDAYS(MAX($K72,AL$4),MIN($L72,EOMONTH(AL$4,0)),Assumptions!$F$4:$F$44))/NETWORKDAYS($K72,$L72,Assumptions!$F$4:$F$44)) -> 0 | AM72: =IF($J72=0,0,MAX(0,NETWORKDAYS(MAX($K72,AM$4),MIN($L72,EOMONTH(AM$4,0)),Assumptions!$F$4:$F$44))/NETWORKDAYS($K72,$L72,Assumptions!$F$4:$F$44)) -> 0 | ... BC72: =IF($J72=0,0,MAX(0,NETWORKDAYS(MAX($K72,BC$4),MIN($L72,EOMONTH(BC$4,0)),Assumptions!$F$4:$F$44))/NETWORKDAYS($K72,$L72,Assumptions!$F$4:$F$44)) -> 0
A73: 69 | B73: 3.12 | C73: 2 | D73: Task | E73: Aadhaar Data Vault with HSM | F73: Phase 1 | G73: Platform | J73: =NETWORKDAYS(K73,L73,Assumptions!$F$4:$F$44) -> 34 | K73: =MIN(K74:K76) -> 46372 | L73: =MAX(L74:L76) -> 46419 | N73: =SUMPRODUCT(($C$74:$C$76=3)*(N74:N76)) -> 0 | O73: =SUMPRODUCT(($C$74:$C$76=3)*(O74:O76)) -> 0 | P73: =SUMPRODUCT(($C$74:$C$76=3)*(P74:P76)) -> 3 | Q73: =SUMPRODUCT(($C$74:$C$76=3)*(Q74:Q76)) -> 13 | R73: =SUMPRODUCT(($C$74:$C$76=3)*(R74:R76)) -> 0 | S73: =SUMPRODUCT(($C$74:$C$76=3)*(S74:S76)) -> 0 | T73: =SUMPRODUCT(($C$74:$C$76=3)*(T74:T76)) -> 0 | U73: =SUMPRODUCT(($C$74:$C$76=3)*(U74:U76)) -> 5 | ... X73: =SUMPRODUCT(($C$74:$C$76=3)*(X74:X76)) -> 0 | Y73: =SUM(N73:X73) -> 25 | Z73: =Y73*(1+Assumptions!$C$5) -> 28.75 | AA73: PLT-FR-034 | AF73: 0 | AG73: 0 | AH73: 0 | AI73: 0 | AJ73: 0 | AK73: 0 | AL73: 0 | AM73: 0 | AN73: 0 | AO73: 0 | AP73: 0 | AQ73: 0 | AR73: 0 | AS73: 0 | AT73: 0 | AU73: 0 | AV73: 0 | AW73: 0 | AX73: 0 | AY73: 0 | AZ73: 0 | BA73: 0 | BB73: 0 | BC73: 0
A74: 70 | B74: 3.12.1 | C74: 3 | D74: Subtask | E74: Detailed design and contracts | F74: Phase 1 | G74: Platform | H74: ARC | I74: 32 | J74: 7 | K74: =WORKDAY(Assumptions!$C$4,I74,Assumptions!$F$4:$F$44) -> 46372 | L74: =IF(J74=0,K74,WORKDAY(K74,J74-1,Assumptions!$F$4:$F$44)) -> 46380 | M74: 20 | N74: 0 | O74: 0 | P74: 3 | Q74: 1 | R74: 0 | S74: 0 | T74: 0 | U74: 0 | V74: 0 | W74: 0 | X74: 0 | Y74: =SUM(N74:X74) -> 4 | Z74: =Y74*(1+Assumptions!$C$5) -> 4.6 | AA74: Design note, OpenAPI and event schemas | AB74: Not started | AD74: 0 | AF74: =IF($J74=0,0,MAX(0,NETWORKDAYS(MAX($K74,AF$4),MIN($L74,EOMONTH(AF$4,0)),Assumptions!$F$4:$F$44))/NETWORKDAYS($K74,$L74,Assumptions!$F$4:$F$44)) -> 0 | AG74: =IF($J74=0,0,MAX(0,NETWORKDAYS(MAX($K74,AG$4),MIN($L74,EOMONTH(AG$4,0)),Assumptions!$F$4:$F$44))/NETWORKDAYS($K74,$L74,Assumptions!$F$4:$F$44)) -> 1 | AH74: =IF($J74=0,0,MAX(0,NETWORKDAYS(MAX($K74,AH$4),MIN($L74,EOMONTH(AH$4,0)),Assumptions!$F$4:$F$44))/NETWORKDAYS($K74,$L74,Assumptions!$F$4:$F$44)) -> 0 | AI74: =IF($J74=0,0,MAX(0,NETWORKDAYS(MAX($K74,AI$4),MIN($L74,EOMONTH(AI$4,0)),Assumptions!$F$4:$F$44))/NETWORKDAYS($K74,$L74,Assumptions!$F$4:$F$44)) -> 0 | AJ74: =IF($J74=0,0,MAX(0,NETWORKDAYS(MAX($K74,AJ$4),MIN($L74,EOMONTH(AJ$4,0)),Assumptions!$F$4:$F$44))/NETWORKDAYS($K74,$L74,Assumptions!$F$4:$F$44)) -> 0 | AK74: =IF($J74=0,0,MAX(0,NETWORKDAYS(MAX($K74,AK$4),MIN($L74,EOMONTH(AK$4,0)),Assumptions!$F$4:$F$44))/NETWORKDAYS($K74,$L74,Assumptions!$F$4:$F$44)) -> 0 | AL74: =IF($J74=0,0,MAX(0,NETWORKDAYS(MAX($K74,AL$4),MIN($L74,EOMONTH(AL$4,0)),Assumptions!$F$4:$F$44))/NETWORKDAYS($K74,$L74,Assumptions!$F$4:$F$44)) -> 0 | AM74: =IF($J74=0,0,MAX(0,NETWORKDAYS(MAX($K74,AM$4),MIN($L74,EOMONTH(AM$4,0)),Assumptions!$F$4:$F$44))/NETWORKDAYS($K74,$L74,Assumptions!$F$4:$F$44)) -> 0 | ... BC74: =IF($J74=0,0,MAX(0,NETWORKDAYS(MAX($K74,BC$4),MIN($L74,EOMONTH(BC$4,0)),Assumptions!$F$4:$F$44))/NETWORKDAYS($K74,$L74,Assumptions!$F$4:$F$44)) -> 0
A75: 71 | B75: 3.12.2 | C75: 3 | D75: Subtask | E75: Build and unit tests | F75: Phase 1 | G75: Platform | H75: BE | I75: 39 | J75: 20 | K75: =WORKDAY(Assumptions!$C$4,I75,Assumptions!$F$4:$F$44) -> 46381 | L75: =IF(J75=0,K75,WORKDAY(K75,J75-1,Assumptions!$F$4:$F$44)) -> 46408 | N75: 0 | O75: 0 | P75: 0 | Q75: 11 | R75: 0 | S75: 0 | T75: 0 | U75: 5 | V75: 0 | W75: 0 | X75: 0 | Y75: =SUM(N75:X75) -> 16 | Z75: =Y75*(1+Assumptions!$C$5) -> 18.4 | AA75: Working service | AB75: Not started | AD75: 0 | AF75: =IF($J75=0,0,MAX(0,NETWORKDAYS(MAX($K75,AF$4),MIN($L75,EOMONTH(AF$4,0)),Assumptions!$F$4:$F$44))/NETWORKDAYS($K75,$L75,Assumptions!$F$4:$F$44)) -> 0 | AG75: =IF($J75=0,0,MAX(0,NETWORKDAYS(MAX($K75,AG$4),MIN($L75,EOMONTH(AG$4,0)),Assumptions!$F$4:$F$44))/NETWORKDAYS($K75,$L75,Assumptions!$F$4:$F$44)) -> 0.25 | AH75: =IF($J75=0,0,MAX(0,NETWORKDAYS(MAX($K75,AH$4),MIN($L75,EOMONTH(AH$4,0)),Assumptions!$F$4:$F$44))/NETWORKDAYS($K75,$L75,Assumptions!$F$4:$F$44)) -> 0.75 | AI75: =IF($J75=0,0,MAX(0,NETWORKDAYS(MAX($K75,AI$4),MIN($L75,EOMONTH(AI$4,0)),Assumptions!$F$4:$F$44))/NETWORKDAYS($K75,$L75,Assumptions!$F$4:$F$44)) -> 0 | AJ75: =IF($J75=0,0,MAX(0,NETWORKDAYS(MAX($K75,AJ$4),MIN($L75,EOMONTH(AJ$4,0)),Assumptions!$F$4:$F$44))/NETWORKDAYS($K75,$L75,Assumptions!$F$4:$F$44)) -> 0 | AK75: =IF($J75=0,0,MAX(0,NETWORKDAYS(MAX($K75,AK$4),MIN($L75,EOMONTH(AK$4,0)),Assumptions!$F$4:$F$44))/NETWORKDAYS($K75,$L75,Assumptions!$F$4:$F$44)) -> 0 | AL75: =IF($J75=0,0,MAX(0,NETWORKDAYS(MAX($K75,AL$4),MIN($L75,EOMONTH(AL$4,0)),Assumptions!$F$4:$F$44))/NETWORKDAYS($K75,$L75,Assumptions!$F$4:$F$44)) -> 0 | AM75: =IF($J75=0,0,MAX(0,NETWORKDAYS(MAX($K75,AM$4),MIN($L75,EOMONTH(AM$4,0)),Assumptions!$F$4:$F$44))/NETWORKDAYS($K75,$L75,Assumptions!$F$4:$F$44)) -> 0 | ... BC75: =IF($J75=0,0,MAX(0,NETWORKDAYS(MAX($K75,BC$4),MIN($L75,EOMONTH(BC$4,0)),Assumptions!$F$4:$F$44))/NETWORKDAYS($K75,$L75,Assumptions!$F$4:$F$44)) -> 0
A76: 72 | B76: 3.12.3 | C76: 3 | D76: Subtask | E76: Component, security and contract tests | F76: Phase 1 | G76: Platform | H76: QA | I76: 58 | J76: 8 | K76: =WORKDAY(Assumptions!$C$4,I76,Assumptions!$F$4:$F$44) -> 46408 | L76: =IF(J76=0,K76,WORKDAY(K76,J76-1,Assumptions!$F$4:$F$44)) -> 46419 | N76: 0 | O76: 0 | P76: 0 | Q76: 1 | R76: 0 | S76: 0 | T76: 0 | U76: 0 | V76: 4 | W76: 0 | X76: 0 | Y76: =SUM(N76:X76) -> 5 | Z76: =Y76*(1+Assumptions!$C$5) -> 5.75 | AA76: Test report | AB76: Not started | AD76: 0 | AF76: =IF($J76=0,0,MAX(0,NETWORKDAYS(MAX($K76,AF$4),MIN($L76,EOMONTH(AF$4,0)),Assumptions!$F$4:$F$44))/NETWORKDAYS($K76,$L76,Assumptions!$F$4:$F$44)) -> 0 | AG76: =IF($J76=0,0,MAX(0,NETWORKDAYS(MAX($K76,AG$4),MIN($L76,EOMONTH(AG$4,0)),Assumptions!$F$4:$F$44))/NETWORKDAYS($K76,$L76,Assumptions!$F$4:$F$44)) -> 0 | AH76: =IF($J76=0,0,MAX(0,NETWORKDAYS(MAX($K76,AH$4),MIN($L76,EOMONTH(AH$4,0)),Assumptions!$F$4:$F$44))/NETWORKDAYS($K76,$L76,Assumptions!$F$4:$F$44)) -> 0.875 | AI76: =IF($J76=0,0,MAX(0,NETWORKDAYS(MAX($K76,AI$4),MIN($L76,EOMONTH(AI$4,0)),Assumptions!$F$4:$F$44))/NETWORKDAYS($K76,$L76,Assumptions!$F$4:$F$44)) -> 0.125 | AJ76: =IF($J76=0,0,MAX(0,NETWORKDAYS(MAX($K76,AJ$4),MIN($L76,EOMONTH(AJ$4,0)),Assumptions!$F$4:$F$44))/NETWORKDAYS($K76,$L76,Assumptions!$F$4:$F$44)) -> 0 | AK76: =IF($J76=0,0,MAX(0,NETWORKDAYS(MAX($K76,AK$4),MIN($L76,EOMONTH(AK$4,0)),Assumptions!$F$4:$F$44))/NETWORKDAYS($K76,$L76,Assumptions!$F$4:$F$44)) -> 0 | AL76: =IF($J76=0,0,MAX(0,NETWORKDAYS(MAX($K76,AL$4),MIN($L76,EOMONTH(AL$4,0)),Assumptions!$F$4:$F$44))/NETWORKDAYS($K76,$L76,Assumptions!$F$4:$F$44)) -> 0 | AM76: =IF($J76=0,0,MAX(0,NETWORKDAYS(MAX($K76,AM$4),MIN($L76,EOMONTH(AM$4,0)),Assumptions!$F$4:$F$44))/NETWORKDAYS($K76,$L76,Assumptions!$F$4:$F$44)) -> 0 | ... BC76: =IF($J76=0,0,MAX(0,NETWORKDAYS(MAX($K76,BC$4),MIN($L76,EOMONTH(BC$4,0)),Assumptions!$F$4:$F$44))/NETWORKDAYS($K76,$L76,Assumptions!$F$4:$F$44)) -> 0
A77: 73 | B77: 3.13 | C77: 2 | D77: Task | E77: Adapter hub framework | F77: Phase 1 | G77: Platform | J77: =NETWORKDAYS(K77,L77,Assumptions!$F$4:$F$44) -> 33 | K77: =MIN(K78:K80) -> 46357 | L77: =MAX(L78:L80) -> 46401 | N77: =SUMPRODUCT(($C$78:$C$80=3)*(N78:N80)) -> 0 | O77: =SUMPRODUCT(($C$78:$C$80=3)*(O78:O80)) -> 0 | P77: =SUMPRODUCT(($C$78:$C$80=3)*(P78:P80)) -> 3 | Q77: =SUMPRODUCT(($C$78:$C$80=3)*(Q78:Q80)) -> 13 | R77: =SUMPRODUCT(($C$78:$C$80=3)*(R78:R80)) -> 0 | S77: =SUMPRODUCT(($C$78:$C$80=3)*(S78:S80)) -> 0 | T77: =SUMPRODUCT(($C$78:$C$80=3)*(T78:T80)) -> 0 | U77: =SUMPRODUCT(($C$78:$C$80=3)*(U78:U80)) -> 0 | ... X77: =SUMPRODUCT(($C$78:$C$80=3)*(X78:X80)) -> 0 | Y77: =SUM(N77:X77) -> 19 | Z77: =Y77*(1+Assumptions!$C$5) -> 21.85 | AA77: PLT-FR-019 | AF77: 0 | AG77: 0 | AH77: 0 | AI77: 0 | AJ77: 0 | AK77: 0 | AL77: 0 | AM77: 0 | AN77: 0 | AO77: 0 | AP77: 0 | AQ77: 0 | AR77: 0 | AS77: 0 | AT77: 0 | AU77: 0 | AV77: 0 | AW77: 0 | AX77: 0 | AY77: 0 | AZ77: 0 | BA77: 0 | BB77: 0 | BC77: 0
A78: 74 | B78: 3.13.1 | C78: 3 | D78: Subtask | E78: Detailed design and contracts | F78: Phase 1 | G78: Platform | H78: ARC | I78: 21 | J78: 7 | K78: =WORKDAY(Assumptions!$C$4,I78,Assumptions!$F$4:$F$44) -> 46357 | L78: =IF(J78=0,K78,WORKDAY(K78,J78-1,Assumptions!$F$4:$F$44)) -> 46365 | M78: 20 | N78: 0 | O78: 0 | P78: 3 | Q78: 1 | R78: 0 | S78: 0 | T78: 0 | U78: 0 | V78: 0 | W78: 0 | X78: 0 | Y78: =SUM(N78:X78) -> 4 | Z78: =Y78*(1+Assumptions!$C$5) -> 4.6 | AA78: Design note, OpenAPI and event schemas | AB78: Not started | AD78: 0 | AF78: =IF($J78=0,0,MAX(0,NETWORKDAYS(MAX($K78,AF$4),MIN($L78,EOMONTH(AF$4,0)),Assumptions!$F$4:$F$44))/NETWORKDAYS($K78,$L78,Assumptions!$F$4:$F$44)) -> 0 | AG78: =IF($J78=0,0,MAX(0,NETWORKDAYS(MAX($K78,AG$4),MIN($L78,EOMONTH(AG$4,0)),Assumptions!$F$4:$F$44))/NETWORKDAYS($K78,$L78,Assumptions!$F$4:$F$44)) -> 1 | AH78: =IF($J78=0,0,MAX(0,NETWORKDAYS(MAX($K78,AH$4),MIN($L78,EOMONTH(AH$4,0)),Assumptions!$F$4:$F$44))/NETWORKDAYS($K78,$L78,Assumptions!$F$4:$F$44)) -> 0 | AI78: =IF($J78=0,0,MAX(0,NETWORKDAYS(MAX($K78,AI$4),MIN($L78,EOMONTH(AI$4,0)),Assumptions!$F$4:$F$44))/NETWORKDAYS($K78,$L78,Assumptions!$F$4:$F$44)) -> 0 | AJ78: =IF($J78=0,0,MAX(0,NETWORKDAYS(MAX($K78,AJ$4),MIN($L78,EOMONTH(AJ$4,0)),Assumptions!$F$4:$F$44))/NETWORKDAYS($K78,$L78,Assumptions!$F$4:$F$44)) -> 0 | AK78: =IF($J78=0,0,MAX(0,NETWORKDAYS(MAX($K78,AK$4),MIN($L78,EOMONTH(AK$4,0)),Assumptions!$F$4:$F$44))/NETWORKDAYS($K78,$L78,Assumptions!$F$4:$F$44)) -> 0 | AL78: =IF($J78=0,0,MAX(0,NETWORKDAYS(MAX($K78,AL$4),MIN($L78,EOMONTH(AL$4,0)),Assumptions!$F$4:$F$44))/NETWORKDAYS($K78,$L78,Assumptions!$F$4:$F$44)) -> 0 | AM78: =IF($J78=0,0,MAX(0,NETWORKDAYS(MAX($K78,AM$4),MIN($L78,EOMONTH(AM$4,0)),Assumptions!$F$4:$F$44))/NETWORKDAYS($K78,$L78,Assumptions!$F$4:$F$44)) -> 0 | ... BC78: =IF($J78=0,0,MAX(0,NETWORKDAYS(MAX($K78,BC$4),MIN($L78,EOMONTH(BC$4,0)),Assumptions!$F$4:$F$44))/NETWORKDAYS($K78,$L78,Assumptions!$F$4:$F$44)) -> 0
A79: 75 | B79: 3.13.2 | C79: 3 | D79: Subtask | E79: Build and unit tests | F79: Phase 1 | G79: Platform | H79: BE | I79: 28 | J79: 20 | K79: =WORKDAY(Assumptions!$C$4,I79,Assumptions!$F$4:$F$44) -> 46366 | L79: =IF(J79=0,K79,WORKDAY(K79,J79-1,Assumptions!$F$4:$F$44)) -> 46393 | N79: 0 | O79: 0 | P79: 0 | Q79: 11 | R79: 0 | S79: 0 | T79: 0 | U79: 0 | V79: 0 | W79: 0 | X79: 0 | Y79: =SUM(N79:X79) -> 11 | Z79: =Y79*(1+Assumptions!$C$5) -> 12.65 | AA79: Working service | AB79: Not started | AD79: 0 | AF79: =IF($J79=0,0,MAX(0,NETWORKDAYS(MAX($K79,AF$4),MIN($L79,EOMONTH(AF$4,0)),Assumptions!$F$4:$F$44))/NETWORKDAYS($K79,$L79,Assumptions!$F$4:$F$44)) -> 0 | AG79: =IF($J79=0,0,MAX(0,NETWORKDAYS(MAX($K79,AG$4),MIN($L79,EOMONTH(AG$4,0)),Assumptions!$F$4:$F$44))/NETWORKDAYS($K79,$L79,Assumptions!$F$4:$F$44)) -> 0.8 | AH79: =IF($J79=0,0,MAX(0,NETWORKDAYS(MAX($K79,AH$4),MIN($L79,EOMONTH(AH$4,0)),Assumptions!$F$4:$F$44))/NETWORKDAYS($K79,$L79,Assumptions!$F$4:$F$44)) -> 0.2 | AI79: =IF($J79=0,0,MAX(0,NETWORKDAYS(MAX($K79,AI$4),MIN($L79,EOMONTH(AI$4,0)),Assumptions!$F$4:$F$44))/NETWORKDAYS($K79,$L79,Assumptions!$F$4:$F$44)) -> 0 | AJ79: =IF($J79=0,0,MAX(0,NETWORKDAYS(MAX($K79,AJ$4),MIN($L79,EOMONTH(AJ$4,0)),Assumptions!$F$4:$F$44))/NETWORKDAYS($K79,$L79,Assumptions!$F$4:$F$44)) -> 0 | AK79: =IF($J79=0,0,MAX(0,NETWORKDAYS(MAX($K79,AK$4),MIN($L79,EOMONTH(AK$4,0)),Assumptions!$F$4:$F$44))/NETWORKDAYS($K79,$L79,Assumptions!$F$4:$F$44)) -> 0 | AL79: =IF($J79=0,0,MAX(0,NETWORKDAYS(MAX($K79,AL$4),MIN($L79,EOMONTH(AL$4,0)),Assumptions!$F$4:$F$44))/NETWORKDAYS($K79,$L79,Assumptions!$F$4:$F$44)) -> 0 | AM79: =IF($J79=0,0,MAX(0,NETWORKDAYS(MAX($K79,AM$4),MIN($L79,EOMONTH(AM$4,0)),Assumptions!$F$4:$F$44))/NETWORKDAYS($K79,$L79,Assumptions!$F$4:$F$44)) -> 0 | ... BC79: =IF($J79=0,0,MAX(0,NETWORKDAYS(MAX($K79,BC$4),MIN($L79,EOMONTH(BC$4,0)),Assumptions!$F$4:$F$44))/NETWORKDAYS($K79,$L79,Assumptions!$F$4:$F$44)) -> 0
A80: 76 | B80: 3.13.3 | C80: 3 | D80: Subtask | E80: Component, security and contract tests | F80: Phase 1 | G80: Platform | H80: QA | I80: 46 | J80: 8 | K80: =WORKDAY(Assumptions!$C$4,I80,Assumptions!$F$4:$F$44) -> 46392 | L80: =IF(J80=0,K80,WORKDAY(K80,J80-1,Assumptions!$F$4:$F$44)) -> 46401 | N80: 0 | O80: 0 | P80: 0 | Q80: 1 | R80: 0 | S80: 0 | T80: 0 | U80: 0 | V80: 3 | W80: 0 | X80: 0 | Y80: =SUM(N80:X80) -> 4 | Z80: =Y80*(1+Assumptions!$C$5) -> 4.6 | AA80: Test report | AB80: Not started | AD80: 0 | AF80: =IF($J80=0,0,MAX(0,NETWORKDAYS(MAX($K80,AF$4),MIN($L80,EOMONTH(AF$4,0)),Assumptions!$F$4:$F$44))/NETWORKDAYS($K80,$L80,Assumptions!$F$4:$F$44)) -> 0 | AG80: =IF($J80=0,0,MAX(0,NETWORKDAYS(MAX($K80,AG$4),MIN($L80,EOMONTH(AG$4,0)),Assumptions!$F$4:$F$44))/NETWORKDAYS($K80,$L80,Assumptions!$F$4:$F$44)) -> 0 | AH80: =IF($J80=0,0,MAX(0,NETWORKDAYS(MAX($K80,AH$4),MIN($L80,EOMONTH(AH$4,0)),Assumptions!$F$4:$F$44))/NETWORKDAYS($K80,$L80,Assumptions!$F$4:$F$44)) -> 1 | AI80: =IF($J80=0,0,MAX(0,NETWORKDAYS(MAX($K80,AI$4),MIN($L80,EOMONTH(AI$4,0)),Assumptions!$F$4:$F$44))/NETWORKDAYS($K80,$L80,Assumptions!$F$4:$F$44)) -> 0 | AJ80: =IF($J80=0,0,MAX(0,NETWORKDAYS(MAX($K80,AJ$4),MIN($L80,EOMONTH(AJ$4,0)),Assumptions!$F$4:$F$44))/NETWORKDAYS($K80,$L80,Assumptions!$F$4:$F$44)) -> 0 | AK80: =IF($J80=0,0,MAX(0,NETWORKDAYS(MAX($K80,AK$4),MIN($L80,EOMONTH(AK$4,0)),Assumptions!$F$4:$F$44))/NETWORKDAYS($K80,$L80,Assumptions!$F$4:$F$44)) -> 0 | AL80: =IF($J80=0,0,MAX(0,NETWORKDAYS(MAX($K80,AL$4),MIN($L80,EOMONTH(AL$4,0)),Assumptions!$F$4:$F$44))/NETWORKDAYS($K80,$L80,Assumptions!$F$4:$F$44)) -> 0 | AM80: =IF($J80=0,0,MAX(0,NETWORKDAYS(MAX($K80,AM$4),MIN($L80,EOMONTH(AM$4,0)),Assumptions!$F$4:$F$44))/NETWORKDAYS($K80,$L80,Assumptions!$F$4:$F$44)) -> 0 | ... BC80: =IF($J80=0,0,MAX(0,NETWORKDAYS(MAX($K80,BC$4),MIN($L80,EOMONTH(BC$4,0)),Assumptions!$F$4:$F$44))/NETWORKDAYS($K80,$L80,Assumptions!$F$4:$F$44)) -> 0
A81: 77 | B81: 3.14 | C81: 2 | D81: Task | E81: Citizen portal and app shell (MyGWMC branding, 22-language i18n) | F81: Phase 1 | G81: Platform | J81: =NETWORKDAYS(K81,L81,Assumptions!$F$4:$F$44) -> 56 | K81: =MIN(K82:K84) -> 46357 | L81: =MAX(L82:L84) -> 46434 | N81: =SUMPRODUCT(($C$82:$C$84=3)*(N82:N84)) -> 0 | O81: =SUMPRODUCT(($C$82:$C$84=3)*(O82:O84)) -> 4 | P81: =SUMPRODUCT(($C$82:$C$84=3)*(P82:P84)) -> 2 | Q81: =SUMPRODUCT(($C$82:$C$84=3)*(Q82:Q84)) -> 0 | R81: =SUMPRODUCT(($C$82:$C$84=3)*(R82:R84)) -> 27 | S81: =SUMPRODUCT(($C$82:$C$84=3)*(S82:S84)) -> 22 | T81: =SUMPRODUCT(($C$82:$C$84=3)*(T82:T84)) -> 0 | U81: =SUMPRODUCT(($C$82:$C$84=3)*(U82:U84)) -> 0 | ... X81: =SUMPRODUCT(($C$82:$C$84=3)*(X82:X84)) -> 0 | Y81: =SUM(N81:X81) -> 65 | Z81: =Y81*(1+Assumptions!$C$5) -> 74.75 | AA81: PLT-FR-009, 021, 022 | AF81: 0 | AG81: 0 | AH81: 0 | AI81: 0 | AJ81: 0 | AK81: 0 | AL81: 0 | AM81: 0 | AN81: 0 | AO81: 0 | AP81: 0 | AQ81: 0 | AR81: 0 | AS81: 0 | AT81: 0 | AU81: 0 | AV81: 0 | AW81: 0 | AX81: 0 | AY81: 0 | AZ81: 0 | BA81: 0 | BB81: 0 | BC81: 0
A82: 78 | B82: 3.14.1 | C82: 3 | D82: Subtask | E82: Detailed design and contracts | F82: Phase 1 | G82: Platform | H82: ARC | I82: 21 | J82: 11 | K82: =WORKDAY(Assumptions!$C$4,I82,Assumptions!$F$4:$F$44) -> 46357 | L82: =IF(J82=0,K82,WORKDAY(K82,J82-1,Assumptions!$F$4:$F$44)) -> 46371 | M82: 20 | N82: 0 | O82: 0 | P82: 2 | Q82: 0 | R82: 0 | S82: 0 | T82: 0 | U82: 0 | V82: 0 | W82: 0 | X82: 0 | Y82: =SUM(N82:X82) -> 2 | Z82: =Y82*(1+Assumptions!$C$5) -> 2.3 | AA82: Design note, OpenAPI and event schemas | AB82: Not started | AD82: 0 | AF82: =IF($J82=0,0,MAX(0,NETWORKDAYS(MAX($K82,AF$4),MIN($L82,EOMONTH(AF$4,0)),Assumptions!$F$4:$F$44))/NETWORKDAYS($K82,$L82,Assumptions!$F$4:$F$44)) -> 0 | AG82: =IF($J82=0,0,MAX(0,NETWORKDAYS(MAX($K82,AG$4),MIN($L82,EOMONTH(AG$4,0)),Assumptions!$F$4:$F$44))/NETWORKDAYS($K82,$L82,Assumptions!$F$4:$F$44)) -> 1 | AH82: =IF($J82=0,0,MAX(0,NETWORKDAYS(MAX($K82,AH$4),MIN($L82,EOMONTH(AH$4,0)),Assumptions!$F$4:$F$44))/NETWORKDAYS($K82,$L82,Assumptions!$F$4:$F$44)) -> 0 | AI82: =IF($J82=0,0,MAX(0,NETWORKDAYS(MAX($K82,AI$4),MIN($L82,EOMONTH(AI$4,0)),Assumptions!$F$4:$F$44))/NETWORKDAYS($K82,$L82,Assumptions!$F$4:$F$44)) -> 0 | AJ82: =IF($J82=0,0,MAX(0,NETWORKDAYS(MAX($K82,AJ$4),MIN($L82,EOMONTH(AJ$4,0)),Assumptions!$F$4:$F$44))/NETWORKDAYS($K82,$L82,Assumptions!$F$4:$F$44)) -> 0 | AK82: =IF($J82=0,0,MAX(0,NETWORKDAYS(MAX($K82,AK$4),MIN($L82,EOMONTH(AK$4,0)),Assumptions!$F$4:$F$44))/NETWORKDAYS($K82,$L82,Assumptions!$F$4:$F$44)) -> 0 | AL82: =IF($J82=0,0,MAX(0,NETWORKDAYS(MAX($K82,AL$4),MIN($L82,EOMONTH(AL$4,0)),Assumptions!$F$4:$F$44))/NETWORKDAYS($K82,$L82,Assumptions!$F$4:$F$44)) -> 0 | AM82: =IF($J82=0,0,MAX(0,NETWORKDAYS(MAX($K82,AM$4),MIN($L82,EOMONTH(AM$4,0)),Assumptions!$F$4:$F$44))/NETWORKDAYS($K82,$L82,Assumptions!$F$4:$F$44)) -> 0 | ... BC82: =IF($J82=0,0,MAX(0,NETWORKDAYS(MAX($K82,BC$4),MIN($L82,EOMONTH(BC$4,0)),Assumptions!$F$4:$F$44))/NETWORKDAYS($K82,$L82,Assumptions!$F$4:$F$44)) -> 0
A83: 79 | B83: 3.14.2 | C83: 3 | D83: Subtask | E83: Build and unit tests | F83: Phase 1 | G83: Platform | H83: FE | I83: 32 | J83: 34 | K83: =WORKDAY(Assumptions!$C$4,I83,Assumptions!$F$4:$F$44) -> 46372 | L83: =IF(J83=0,K83,WORKDAY(K83,J83-1,Assumptions!$F$4:$F$44)) -> 46419 | N83: 0 | O83: 4 | P83: 0 | Q83: 0 | R83: 27 | S83: 22 | T83: 0 | U83: 0 | V83: 0 | W83: 0 | X83: 0 | Y83: =SUM(N83:X83) -> 53 | Z83: =Y83*(1+Assumptions!$C$5) -> 60.95 | AA83: Working service | AB83: Not started | AD83: 0 | AF83: =IF($J83=0,0,MAX(0,NETWORKDAYS(MAX($K83,AF$4),MIN($L83,EOMONTH(AF$4,0)),Assumptions!$F$4:$F$44))/NETWORKDAYS($K83,$L83,Assumptions!$F$4:$F$44)) -> 0 | AG83: =IF($J83=0,0,MAX(0,NETWORKDAYS(MAX($K83,AG$4),MIN($L83,EOMONTH(AG$4,0)),Assumptions!$F$4:$F$44))/NETWORKDAYS($K83,$L83,Assumptions!$F$4:$F$44)) -> 0.35294118 | AH83: =IF($J83=0,0,MAX(0,NETWORKDAYS(MAX($K83,AH$4),MIN($L83,EOMONTH(AH$4,0)),Assumptions!$F$4:$F$44))/NETWORKDAYS($K83,$L83,Assumptions!$F$4:$F$44)) -> 0.61764706 | AI83: =IF($J83=0,0,MAX(0,NETWORKDAYS(MAX($K83,AI$4),MIN($L83,EOMONTH(AI$4,0)),Assumptions!$F$4:$F$44))/NETWORKDAYS($K83,$L83,Assumptions!$F$4:$F$44)) -> 0.029411765 | AJ83: =IF($J83=0,0,MAX(0,NETWORKDAYS(MAX($K83,AJ$4),MIN($L83,EOMONTH(AJ$4,0)),Assumptions!$F$4:$F$44))/NETWORKDAYS($K83,$L83,Assumptions!$F$4:$F$44)) -> 0 | AK83: =IF($J83=0,0,MAX(0,NETWORKDAYS(MAX($K83,AK$4),MIN($L83,EOMONTH(AK$4,0)),Assumptions!$F$4:$F$44))/NETWORKDAYS($K83,$L83,Assumptions!$F$4:$F$44)) -> 0 | AL83: =IF($J83=0,0,MAX(0,NETWORKDAYS(MAX($K83,AL$4),MIN($L83,EOMONTH(AL$4,0)),Assumptions!$F$4:$F$44))/NETWORKDAYS($K83,$L83,Assumptions!$F$4:$F$44)) -> 0 | AM83: =IF($J83=0,0,MAX(0,NETWORKDAYS(MAX($K83,AM$4),MIN($L83,EOMONTH(AM$4,0)),Assumptions!$F$4:$F$44))/NETWORKDAYS($K83,$L83,Assumptions!$F$4:$F$44)) -> 0 | ... BC83: =IF($J83=0,0,MAX(0,NETWORKDAYS(MAX($K83,BC$4),MIN($L83,EOMONTH(BC$4,0)),Assumptions!$F$4:$F$44))/NETWORKDAYS($K83,$L83,Assumptions!$F$4:$F$44)) -> 0
A84: 80 | B84: 3.14.3 | C84: 3 | D84: Subtask | E84: Component, security and contract tests | F84: Phase 1 | G84: Platform | H84: QA | I84: 63 | J84: 14 | K84: =WORKDAY(Assumptions!$C$4,I84,Assumptions!$F$4:$F$44) -> 46415 | L84: =IF(J84=0,K84,WORKDAY(K84,J84-1,Assumptions!$F$4:$F$44)) -> 46434 | N84: 0 | O84: 0 | P84: 0 | Q84: 0 | R84: 0 | S84: 0 | T84: 0 | U84: 0 | V84: 10 | W84: 0 | X84: 0 | Y84: =SUM(N84:X84) -> 10 | Z84: =Y84*(1+Assumptions!$C$5) -> 11.5 | AA84: Test report | AB84: Not started | AD84: 0 | AF84: =IF($J84=0,0,MAX(0,NETWORKDAYS(MAX($K84,AF$4),MIN($L84,EOMONTH(AF$4,0)),Assumptions!$F$4:$F$44))/NETWORKDAYS($K84,$L84,Assumptions!$F$4:$F$44)) -> 0 | AG84: =IF($J84=0,0,MAX(0,NETWORKDAYS(MAX($K84,AG$4),MIN($L84,EOMONTH(AG$4,0)),Assumptions!$F$4:$F$44))/NETWORKDAYS($K84,$L84,Assumptions!$F$4:$F$44)) -> 0 | AH84: =IF($J84=0,0,MAX(0,NETWORKDAYS(MAX($K84,AH$4),MIN($L84,EOMONTH(AH$4,0)),Assumptions!$F$4:$F$44))/NETWORKDAYS($K84,$L84,Assumptions!$F$4:$F$44)) -> 0.14285714 | AI84: =IF($J84=0,0,MAX(0,NETWORKDAYS(MAX($K84,AI$4),MIN($L84,EOMONTH(AI$4,0)),Assumptions!$F$4:$F$44))/NETWORKDAYS($K84,$L84,Assumptions!$F$4:$F$44)) -> 0.85714286 | AJ84: =IF($J84=0,0,MAX(0,NETWORKDAYS(MAX($K84,AJ$4),MIN($L84,EOMONTH(AJ$4,0)),Assumptions!$F$4:$F$44))/NETWORKDAYS($K84,$L84,Assumptions!$F$4:$F$44)) -> 0 | AK84: =IF($J84=0,0,MAX(0,NETWORKDAYS(MAX($K84,AK$4),MIN($L84,EOMONTH(AK$4,0)),Assumptions!$F$4:$F$44))/NETWORKDAYS($K84,$L84,Assumptions!$F$4:$F$44)) -> 0 | AL84: =IF($J84=0,0,MAX(0,NETWORKDAYS(MAX($K84,AL$4),MIN($L84,EOMONTH(AL$4,0)),Assumptions!$F$4:$F$44))/NETWORKDAYS($K84,$L84,Assumptions!$F$4:$F$44)) -> 0 | AM84: =IF($J84=0,0,MAX(0,NETWORKDAYS(MAX($K84,AM$4),MIN($L84,EOMONTH(AM$4,0)),Assumptions!$F$4:$F$44))/NETWORKDAYS($K84,$L84,Assumptions!$F$4:$F$44)) -> 0 | ... BC84: =IF($J84=0,0,MAX(0,NETWORKDAYS(MAX($K84,BC$4),MIN($L84,EOMONTH(BC$4,0)),Assumptions!$F$4:$F$44))/NETWORKDAYS($K84,$L84,Assumptions!$F$4:$F$44)) -> 0
A85: 81 | B85: 3.15 | C85: 2 | D85: Task | E85: Staff console shell, work queues and maps | F85: Phase 1 | G85: Platform | J85: =NETWORKDAYS(K85,L85,Assumptions!$F$4:$F$44) -> 45 | K85: =MIN(K86:K88) -> 46357 | L85: =MAX(L86:L88) -> 46419 | N85: =SUMPRODUCT(($C$86:$C$88=3)*(N86:N88)) -> 0 | O85: =SUMPRODUCT(($C$86:$C$88=3)*(O86:O88)) -> 0 | P85: =SUMPRODUCT(($C$86:$C$88=3)*(P86:P88)) -> 2 | Q85: =SUMPRODUCT(($C$86:$C$88=3)*(Q86:Q88)) -> 0 | R85: =SUMPRODUCT(($C$86:$C$88=3)*(R86:R88)) -> 22 | S85: =SUMPRODUCT(($C$86:$C$88=3)*(S86:S88)) -> 0 | T85: =SUMPRODUCT(($C$86:$C$88=3)*(T86:T88)) -> 0 | U85: =SUMPRODUCT(($C$86:$C$88=3)*(U86:U88)) -> 0 | ... X85: =SUMPRODUCT(($C$86:$C$88=3)*(X86:X88)) -> 0 | Y85: =SUM(N85:X85) -> 30 | Z85: =Y85*(1+Assumptions!$C$5) -> 34.5 | AA85: Console | AF85: 0 | AG85: 0 | AH85: 0 | AI85: 0 | AJ85: 0 | AK85: 0 | AL85: 0 | AM85: 0 | AN85: 0 | AO85: 0 | AP85: 0 | AQ85: 0 | AR85: 0 | AS85: 0 | AT85: 0 | AU85: 0 | AV85: 0 | AW85: 0 | AX85: 0 | AY85: 0 | AZ85: 0 | BA85: 0 | BB85: 0 | BC85: 0
A86: 82 | B86: 3.15.1 | C86: 3 | D86: Subtask | E86: Detailed design and contracts | F86: Phase 1 | G86: Platform | H86: ARC | I86: 21 | J86: 9 | K86: =WORKDAY(Assumptions!$C$4,I86,Assumptions!$F$4:$F$44) -> 46357 | L86: =IF(J86=0,K86,WORKDAY(K86,J86-1,Assumptions!$F$4:$F$44)) -> 46367 | M86: 20 | N86: 0 | O86: 0 | P86: 2 | Q86: 0 | R86: 0 | S86: 0 | T86: 0 | U86: 0 | V86: 0 | W86: 0 | X86: 0 | Y86: =SUM(N86:X86) -> 2 | Z86: =Y86*(1+Assumptions!$C$5) -> 2.3 | AA86: Design note, OpenAPI and event schemas | AB86: Not started | AD86: 0 | AF86: =IF($J86=0,0,MAX(0,NETWORKDAYS(MAX($K86,AF$4),MIN($L86,EOMONTH(AF$4,0)),Assumptions!$F$4:$F$44))/NETWORKDAYS($K86,$L86,Assumptions!$F$4:$F$44)) -> 0 | AG86: =IF($J86=0,0,MAX(0,NETWORKDAYS(MAX($K86,AG$4),MIN($L86,EOMONTH(AG$4,0)),Assumptions!$F$4:$F$44))/NETWORKDAYS($K86,$L86,Assumptions!$F$4:$F$44)) -> 1 | AH86: =IF($J86=0,0,MAX(0,NETWORKDAYS(MAX($K86,AH$4),MIN($L86,EOMONTH(AH$4,0)),Assumptions!$F$4:$F$44))/NETWORKDAYS($K86,$L86,Assumptions!$F$4:$F$44)) -> 0 | AI86: =IF($J86=0,0,MAX(0,NETWORKDAYS(MAX($K86,AI$4),MIN($L86,EOMONTH(AI$4,0)),Assumptions!$F$4:$F$44))/NETWORKDAYS($K86,$L86,Assumptions!$F$4:$F$44)) -> 0 | AJ86: =IF($J86=0,0,MAX(0,NETWORKDAYS(MAX($K86,AJ$4),MIN($L86,EOMONTH(AJ$4,0)),Assumptions!$F$4:$F$44))/NETWORKDAYS($K86,$L86,Assumptions!$F$4:$F$44)) -> 0 | AK86: =IF($J86=0,0,MAX(0,NETWORKDAYS(MAX($K86,AK$4),MIN($L86,EOMONTH(AK$4,0)),Assumptions!$F$4:$F$44))/NETWORKDAYS($K86,$L86,Assumptions!$F$4:$F$44)) -> 0 | AL86: =IF($J86=0,0,MAX(0,NETWORKDAYS(MAX($K86,AL$4),MIN($L86,EOMONTH(AL$4,0)),Assumptions!$F$4:$F$44))/NETWORKDAYS($K86,$L86,Assumptions!$F$4:$F$44)) -> 0 | AM86: =IF($J86=0,0,MAX(0,NETWORKDAYS(MAX($K86,AM$4),MIN($L86,EOMONTH(AM$4,0)),Assumptions!$F$4:$F$44))/NETWORKDAYS($K86,$L86,Assumptions!$F$4:$F$44)) -> 0 | ... BC86: =IF($J86=0,0,MAX(0,NETWORKDAYS(MAX($K86,BC$4),MIN($L86,EOMONTH(BC$4,0)),Assumptions!$F$4:$F$44))/NETWORKDAYS($K86,$L86,Assumptions!$F$4:$F$44)) -> 0
A87: 83 | B87: 3.15.2 | C87: 3 | D87: Subtask | E87: Build and unit tests | F87: Phase 1 | G87: Platform | H87: FE | I87: 30 | J87: 27 | K87: =WORKDAY(Assumptions!$C$4,I87,Assumptions!$F$4:$F$44) -> 46370 | L87: =IF(J87=0,K87,WORKDAY(K87,J87-1,Assumptions!$F$4:$F$44)) -> 46406 | N87: 0 | O87: 0 | P87: 0 | Q87: 0 | R87: 22 | S87: 0 | T87: 0 | U87: 0 | V87: 0 | W87: 0 | X87: 0 | Y87: =SUM(N87:X87) -> 22 | Z87: =Y87*(1+Assumptions!$C$5) -> 25.3 | AA87: Working service | AB87: Not started | AD87: 0 | AF87: =IF($J87=0,0,MAX(0,NETWORKDAYS(MAX($K87,AF$4),MIN($L87,EOMONTH(AF$4,0)),Assumptions!$F$4:$F$44))/NETWORKDAYS($K87,$L87,Assumptions!$F$4:$F$44)) -> 0 | AG87: =IF($J87=0,0,MAX(0,NETWORKDAYS(MAX($K87,AG$4),MIN($L87,EOMONTH(AG$4,0)),Assumptions!$F$4:$F$44))/NETWORKDAYS($K87,$L87,Assumptions!$F$4:$F$44)) -> 0.51851852 | AH87: =IF($J87=0,0,MAX(0,NETWORKDAYS(MAX($K87,AH$4),MIN($L87,EOMONTH(AH$4,0)),Assumptions!$F$4:$F$44))/NETWORKDAYS($K87,$L87,Assumptions!$F$4:$F$44)) -> 0.48148148 | AI87: =IF($J87=0,0,MAX(0,NETWORKDAYS(MAX($K87,AI$4),MIN($L87,EOMONTH(AI$4,0)),Assumptions!$F$4:$F$44))/NETWORKDAYS($K87,$L87,Assumptions!$F$4:$F$44)) -> 0 | AJ87: =IF($J87=0,0,MAX(0,NETWORKDAYS(MAX($K87,AJ$4),MIN($L87,EOMONTH(AJ$4,0)),Assumptions!$F$4:$F$44))/NETWORKDAYS($K87,$L87,Assumptions!$F$4:$F$44)) -> 0 | AK87: =IF($J87=0,0,MAX(0,NETWORKDAYS(MAX($K87,AK$4),MIN($L87,EOMONTH(AK$4,0)),Assumptions!$F$4:$F$44))/NETWORKDAYS($K87,$L87,Assumptions!$F$4:$F$44)) -> 0 | AL87: =IF($J87=0,0,MAX(0,NETWORKDAYS(MAX($K87,AL$4),MIN($L87,EOMONTH(AL$4,0)),Assumptions!$F$4:$F$44))/NETWORKDAYS($K87,$L87,Assumptions!$F$4:$F$44)) -> 0 | AM87: =IF($J87=0,0,MAX(0,NETWORKDAYS(MAX($K87,AM$4),MIN($L87,EOMONTH(AM$4,0)),Assumptions!$F$4:$F$44))/NETWORKDAYS($K87,$L87,Assumptions!$F$4:$F$44)) -> 0 | ... BC87: =IF($J87=0,0,MAX(0,NETWORKDAYS(MAX($K87,BC$4),MIN($L87,EOMONTH(BC$4,0)),Assumptions!$F$4:$F$44))/NETWORKDAYS($K87,$L87,Assumptions!$F$4:$F$44)) -> 0
A88: 84 | B88: 3.15.3 | C88: 3 | D88: Subtask | E88: Component, security and contract tests | F88: Phase 1 | G88: Platform | H88: QA | I88: 55 | J88: 11 | K88: =WORKDAY(Assumptions!$C$4,I88,Assumptions!$F$4:$F$44) -> 46405 | L88: =IF(J88=0,K88,WORKDAY(K88,J88-1,Assumptions!$F$4:$F$44)) -> 46419 | N88: 0 | O88: 0 | P88: 0 | Q88: 0 | R88: 0 | S88: 0 | T88: 0 | U88: 0 | V88: 6 | W88: 0 | X88: 0 | Y88: =SUM(N88:X88) -> 6 | Z88: =Y88*(1+Assumptions!$C$5) -> 6.9 | AA88: Test report | AB88: Not started | AD88: 0 | AF88: =IF($J88=0,0,MAX(0,NETWORKDAYS(MAX($K88,AF$4),MIN($L88,EOMONTH(AF$4,0)),Assumptions!$F$4:$F$44))/NETWORKDAYS($K88,$L88,Assumptions!$F$4:$F$44)) -> 0 | AG88: =IF($J88=0,0,MAX(0,NETWORKDAYS(MAX($K88,AG$4),MIN($L88,EOMONTH(AG$4,0)),Assumptions!$F$4:$F$44))/NETWORKDAYS($K88,$L88,Assumptions!$F$4:$F$44)) -> 0 | AH88: =IF($J88=0,0,MAX(0,NETWORKDAYS(MAX($K88,AH$4),MIN($L88,EOMONTH(AH$4,0)),Assumptions!$F$4:$F$44))/NETWORKDAYS($K88,$L88,Assumptions!$F$4:$F$44)) -> 0.90909091 | AI88: =IF($J88=0,0,MAX(0,NETWORKDAYS(MAX($K88,AI$4),MIN($L88,EOMONTH(AI$4,0)),Assumptions!$F$4:$F$44))/NETWORKDAYS($K88,$L88,Assumptions!$F$4:$F$44)) -> 0.090909091 | AJ88: =IF($J88=0,0,MAX(0,NETWORKDAYS(MAX($K88,AJ$4),MIN($L88,EOMONTH(AJ$4,0)),Assumptions!$F$4:$F$44))/NETWORKDAYS($K88,$L88,Assumptions!$F$4:$F$44)) -> 0 | AK88: =IF($J88=0,0,MAX(0,NETWORKDAYS(MAX($K88,AK$4),MIN($L88,EOMONTH(AK$4,0)),Assumptions!$F$4:$F$44))/NETWORKDAYS($K88,$L88,Assumptions!$F$4:$F$44)) -> 0 | AL88: =IF($J88=0,0,MAX(0,NETWORKDAYS(MAX($K88,AL$4),MIN($L88,EOMONTH(AL$4,0)),Assumptions!$F$4:$F$44))/NETWORKDAYS($K88,$L88,Assumptions!$F$4:$F$44)) -> 0 | AM88: =IF($J88=0,0,MAX(0,NETWORKDAYS(MAX($K88,AM$4),MIN($L88,EOMONTH(AM$4,0)),Assumptions!$F$4:$F$44))/NETWORKDAYS($K88,$L88,Assumptions!$F$4:$F$44)) -> 0 | ... BC88: =IF($J88=0,0,MAX(0,NETWORKDAYS(MAX($K88,BC$4),MIN($L88,EOMONTH(BC$4,0)),Assumptions!$F$4:$F$44))/NETWORKDAYS($K88,$L88,Assumptions!$F$4:$F$44)) -> 0
A89: 85 | B89: 3.16 | C89: 2 | D89: Task | E89: Field app shell and offline sync service | F89: Phase 1 | G89: Platform | J89: =NETWORKDAYS(K89,L89,Assumptions!$F$4:$F$44) -> 51 | K89: =MIN(K90:K92) -> 46365 | L89: =MAX(L90:L92) -> 46435 | N89: =SUMPRODUCT(($C$90:$C$92=3)*(N90:N92)) -> 0 | O89: =SUMPRODUCT(($C$90:$C$92=3)*(O90:O92)) -> 0 | P89: =SUMPRODUCT(($C$90:$C$92=3)*(P90:P92)) -> 2 | Q89: =SUMPRODUCT(($C$90:$C$92=3)*(Q90:Q92)) -> 13 | R89: =SUMPRODUCT(($C$90:$C$92=3)*(R90:R92)) -> 0 | S89: =SUMPRODUCT(($C$90:$C$92=3)*(S90:S92)) -> 27 | T89: =SUMPRODUCT(($C$90:$C$92=3)*(T90:T92)) -> 0 | U89: =SUMPRODUCT(($C$90:$C$92=3)*(U90:U92)) -> 0 | ... X89: =SUMPRODUCT(($C$90:$C$92=3)*(X90:X92)) -> 0 | Y89: =SUM(N89:X89) -> 50 | Z89: =Y89*(1+Assumptions!$C$5) -> 57.5 | AA89: PLT-FR-013 | AF89: 0 | AG89: 0 | AH89: 0 | AI89: 0 | AJ89: 0 | AK89: 0 | AL89: 0 | AM89: 0 | AN89: 0 | AO89: 0 | AP89: 0 | AQ89: 0 | AR89: 0 | AS89: 0 | AT89: 0 | AU89: 0 | AV89: 0 | AW89: 0 | AX89: 0 | AY89: 0 | AZ89: 0 | BA89: 0 | BB89: 0 | BC89: 0
A90: 86 | B90: 3.16.1 | C90: 3 | D90: Subtask | E90: Detailed design and contracts | F90: Phase 1 | G90: Platform | H90: ARC | I90: 27 | J90: 10 | K90: =WORKDAY(Assumptions!$C$4,I90,Assumptions!$F$4:$F$44) -> 46365 | L90: =IF(J90=0,K90,WORKDAY(K90,J90-1,Assumptions!$F$4:$F$44)) -> 46378 | M90: 20 | N90: 0 | O90: 0 | P90: 2 | Q90: 1 | R90: 0 | S90: 0 | T90: 0 | U90: 0 | V90: 0 | W90: 0 | X90: 0 | Y90: =SUM(N90:X90) -> 3 | Z90: =Y90*(1+Assumptions!$C$5) -> 3.45 | AA90: Design note, OpenAPI and event schemas | AB90: Not started | AD90: 0 | AF90: =IF($J90=0,0,MAX(0,NETWORKDAYS(MAX($K90,AF$4),MIN($L90,EOMONTH(AF$4,0)),Assumptions!$F$4:$F$44))/NETWORKDAYS($K90,$L90,Assumptions!$F$4:$F$44)) -> 0 | AG90: =IF($J90=0,0,MAX(0,NETWORKDAYS(MAX($K90,AG$4),MIN($L90,EOMONTH(AG$4,0)),Assumptions!$F$4:$F$44))/NETWORKDAYS($K90,$L90,Assumptions!$F$4:$F$44)) -> 1 | AH90: =IF($J90=0,0,MAX(0,NETWORKDAYS(MAX($K90,AH$4),MIN($L90,EOMONTH(AH$4,0)),Assumptions!$F$4:$F$44))/NETWORKDAYS($K90,$L90,Assumptions!$F$4:$F$44)) -> 0 | AI90: =IF($J90=0,0,MAX(0,NETWORKDAYS(MAX($K90,AI$4),MIN($L90,EOMONTH(AI$4,0)),Assumptions!$F$4:$F$44))/NETWORKDAYS($K90,$L90,Assumptions!$F$4:$F$44)) -> 0 | AJ90: =IF($J90=0,0,MAX(0,NETWORKDAYS(MAX($K90,AJ$4),MIN($L90,EOMONTH(AJ$4,0)),Assumptions!$F$4:$F$44))/NETWORKDAYS($K90,$L90,Assumptions!$F$4:$F$44)) -> 0 | AK90: =IF($J90=0,0,MAX(0,NETWORKDAYS(MAX($K90,AK$4),MIN($L90,EOMONTH(AK$4,0)),Assumptions!$F$4:$F$44))/NETWORKDAYS($K90,$L90,Assumptions!$F$4:$F$44)) -> 0 | AL90: =IF($J90=0,0,MAX(0,NETWORKDAYS(MAX($K90,AL$4),MIN($L90,EOMONTH(AL$4,0)),Assumptions!$F$4:$F$44))/NETWORKDAYS($K90,$L90,Assumptions!$F$4:$F$44)) -> 0 | AM90: =IF($J90=0,0,MAX(0,NETWORKDAYS(MAX($K90,AM$4),MIN($L90,EOMONTH(AM$4,0)),Assumptions!$F$4:$F$44))/NETWORKDAYS($K90,$L90,Assumptions!$F$4:$F$44)) -> 0 | ... BC90: =IF($J90=0,0,MAX(0,NETWORKDAYS(MAX($K90,BC$4),MIN($L90,EOMONTH(BC$4,0)),Assumptions!$F$4:$F$44))/NETWORKDAYS($K90,$L90,Assumptions!$F$4:$F$44)) -> 0
A91: 87 | B91: 3.16.2 | C91: 3 | D91: Subtask | E91: Build and unit tests | F91: Phase 1 | G91: Platform | H91: MOB | I91: 37 | J91: 30 | K91: =WORKDAY(Assumptions!$C$4,I91,Assumptions!$F$4:$F$44) -> 46379 | L91: =IF(J91=0,K91,WORKDAY(K91,J91-1,Assumptions!$F$4:$F$44)) -> 46420 | N91: 0 | O91: 0 | P91: 0 | Q91: 11 | R91: 0 | S91: 27 | T91: 0 | U91: 0 | V91: 0 | W91: 0 | X91: 0 | Y91: =SUM(N91:X91) -> 38 | Z91: =Y91*(1+Assumptions!$C$5) -> 43.7 | AA91: Working service | AB91: Not started | AD91: 0 | AF91: =IF($J91=0,0,MAX(0,NETWORKDAYS(MAX($K91,AF$4),MIN($L91,EOMONTH(AF$4,0)),Assumptions!$F$4:$F$44))/NETWORKDAYS($K91,$L91,Assumptions!$F$4:$F$44)) -> 0 | AG91: =IF($J91=0,0,MAX(0,NETWORKDAYS(MAX($K91,AG$4),MIN($L91,EOMONTH(AG$4,0)),Assumptions!$F$4:$F$44))/NETWORKDAYS($K91,$L91,Assumptions!$F$4:$F$44)) -> 0.23333333 | AH91: =IF($J91=0,0,MAX(0,NETWORKDAYS(MAX($K91,AH$4),MIN($L91,EOMONTH(AH$4,0)),Assumptions!$F$4:$F$44))/NETWORKDAYS($K91,$L91,Assumptions!$F$4:$F$44)) -> 0.7 | AI91: =IF($J91=0,0,MAX(0,NETWORKDAYS(MAX($K91,AI$4),MIN($L91,EOMONTH(AI$4,0)),Assumptions!$F$4:$F$44))/NETWORKDAYS($K91,$L91,Assumptions!$F$4:$F$44)) -> 0.066666667 | AJ91: =IF($J91=0,0,MAX(0,NETWORKDAYS(MAX($K91,AJ$4),MIN($L91,EOMONTH(AJ$4,0)),Assumptions!$F$4:$F$44))/NETWORKDAYS($K91,$L91,Assumptions!$F$4:$F$44)) -> 0 | AK91: =IF($J91=0,0,MAX(0,NETWORKDAYS(MAX($K91,AK$4),MIN($L91,EOMONTH(AK$4,0)),Assumptions!$F$4:$F$44))/NETWORKDAYS($K91,$L91,Assumptions!$F$4:$F$44)) -> 0 | AL91: =IF($J91=0,0,MAX(0,NETWORKDAYS(MAX($K91,AL$4),MIN($L91,EOMONTH(AL$4,0)),Assumptions!$F$4:$F$44))/NETWORKDAYS($K91,$L91,Assumptions!$F$4:$F$44)) -> 0 | AM91: =IF($J91=0,0,MAX(0,NETWORKDAYS(MAX($K91,AM$4),MIN($L91,EOMONTH(AM$4,0)),Assumptions!$F$4:$F$44))/NETWORKDAYS($K91,$L91,Assumptions!$F$4:$F$44)) -> 0 | ... BC91: =IF($J91=0,0,MAX(0,NETWORKDAYS(MAX($K91,BC$4),MIN($L91,EOMONTH(BC$4,0)),Assumptions!$F$4:$F$44))/NETWORKDAYS($K91,$L91,Assumptions!$F$4:$F$44)) -> 0
A92: 88 | B92: 3.16.3 | C92: 3 | D92: Subtask | E92: Component, security and contract tests | F92: Phase 1 | G92: Platform | H92: QA | I92: 65 | J92: 13 | K92: =WORKDAY(Assumptions!$C$4,I92,Assumptions!$F$4:$F$44) -> 46419 | L92: =IF(J92=0,K92,WORKDAY(K92,J92-1,Assumptions!$F$4:$F$44)) -> 46435 | N92: 0 | O92: 0 | P92: 0 | Q92: 1 | R92: 0 | S92: 0 | T92: 0 | U92: 0 | V92: 8 | W92: 0 | X92: 0 | Y92: =SUM(N92:X92) -> 9 | Z92: =Y92*(1+Assumptions!$C$5) -> 10.35 | AA92: Test report | AB92: Not started | AD92: 0 | AF92: =IF($J92=0,0,MAX(0,NETWORKDAYS(MAX($K92,AF$4),MIN($L92,EOMONTH(AF$4,0)),Assumptions!$F$4:$F$44))/NETWORKDAYS($K92,$L92,Assumptions!$F$4:$F$44)) -> 0 | AG92: =IF($J92=0,0,MAX(0,NETWORKDAYS(MAX($K92,AG$4),MIN($L92,EOMONTH(AG$4,0)),Assumptions!$F$4:$F$44))/NETWORKDAYS($K92,$L92,Assumptions!$F$4:$F$44)) -> 0 | AH92: =IF($J92=0,0,MAX(0,NETWORKDAYS(MAX($K92,AH$4),MIN($L92,EOMONTH(AH$4,0)),Assumptions!$F$4:$F$44))/NETWORKDAYS($K92,$L92,Assumptions!$F$4:$F$44)) -> 0 | AI92: =IF($J92=0,0,MAX(0,NETWORKDAYS(MAX($K92,AI$4),MIN($L92,EOMONTH(AI$4,0)),Assumptions!$F$4:$F$44))/NETWORKDAYS($K92,$L92,Assumptions!$F$4:$F$44)) -> 1 | AJ92: =IF($J92=0,0,MAX(0,NETWORKDAYS(MAX($K92,AJ$4),MIN($L92,EOMONTH(AJ$4,0)),Assumptions!$F$4:$F$44))/NETWORKDAYS($K92,$L92,Assumptions!$F$4:$F$44)) -> 0 | AK92: =IF($J92=0,0,MAX(0,NETWORKDAYS(MAX($K92,AK$4),MIN($L92,EOMONTH(AK$4,0)),Assumptions!$F$4:$F$44))/NETWORKDAYS($K92,$L92,Assumptions!$F$4:$F$44)) -> 0 | AL92: =IF($J92=0,0,MAX(0,NETWORKDAYS(MAX($K92,AL$4),MIN($L92,EOMONTH(AL$4,0)),Assumptions!$F$4:$F$44))/NETWORKDAYS($K92,$L92,Assumptions!$F$4:$F$44)) -> 0 | AM92: =IF($J92=0,0,MAX(0,NETWORKDAYS(MAX($K92,AM$4),MIN($L92,EOMONTH(AM$4,0)),Assumptions!$F$4:$F$44))/NETWORKDAYS($K92,$L92,Assumptions!$F$4:$F$44)) -> 0 | ... BC92: =IF($J92=0,0,MAX(0,NETWORKDAYS(MAX($K92,BC$4),MIN($L92,EOMONTH(BC$4,0)),Assumptions!$F$4:$F$44))/NETWORKDAYS($K92,$L92,Assumptions!$F$4:$F$44)) -> 0
A93: 89 | B93: 3.17 | C93: 2 | D93: Task | E93: Reporting warehouse, ELT and Superset dashboards | F93: Phase 1 | G93: Platform | J93: =NETWORKDAYS(K93,L93,Assumptions!$F$4:$F$44) -> 45 | K93: =MIN(K94:K96) -> 46395 | L93: =MAX(L94:L96) -> 46457 | N93: =SUMPRODUCT(($C$94:$C$96=3)*(N94:N96)) -> 0 | O93: =SUMPRODUCT(($C$94:$C$96=3)*(O94:O96)) -> 0 | P93: =SUMPRODUCT(($C$94:$C$96=3)*(P94:P96)) -> 2 | Q93: =SUMPRODUCT(($C$94:$C$96=3)*(Q94:Q96)) -> 18 | R93: =SUMPRODUCT(($C$94:$C$96=3)*(R94:R96)) -> 4 | S93: =SUMPRODUCT(($C$94:$C$96=3)*(S94:S96)) -> 0 | T93: =SUMPRODUCT(($C$94:$C$96=3)*(T94:T96)) -> 0 | U93: =SUMPRODUCT(($C$94:$C$96=3)*(U94:U96)) -> 0 | ... X93: =SUMPRODUCT(($C$94:$C$96=3)*(X94:X96)) -> 0 | Y93: =SUM(N93:X93) -> 37 | Z93: =Y93*(1+Assumptions!$C$5) -> 42.55 | AA93: PLT-FR-011 | AF93: 0 | AG93: 0 | AH93: 0 | AI93: 0 | AJ93: 0 | AK93: 0 | AL93: 0 | AM93: 0 | AN93: 0 | AO93: 0 | AP93: 0 | AQ93: 0 | AR93: 0 | AS93: 0 | AT93: 0 | AU93: 0 | AV93: 0 | AW93: 0 | AX93: 0 | AY93: 0 | AZ93: 0 | BA93: 0 | BB93: 0 | BC93: 0
A94: 90 | B94: 3.17.1 | C94: 3 | D94: Subtask | E94: Detailed design and contracts | F94: Phase 1 | G94: Platform | H94: ARC | I94: 49 | J94: 9 | K94: =WORKDAY(Assumptions!$C$4,I94,Assumptions!$F$4:$F$44) -> 46395 | L94: =IF(J94=0,K94,WORKDAY(K94,J94-1,Assumptions!$F$4:$F$44)) -> 46407 | M94: 20 | N94: 0 | O94: 0 | P94: 2 | Q94: 2 | R94: 0 | S94: 0 | T94: 0 | U94: 0 | V94: 0 | W94: 0 | X94: 0 | Y94: =SUM(N94:X94) -> 4 | Z94: =Y94*(1+Assumptions!$C$5) -> 4.6 | AA94: Design note, OpenAPI and event schemas | AB94: Not started | AD94: 0 | AF94: =IF($J94=0,0,MAX(0,NETWORKDAYS(MAX($K94,AF$4),MIN($L94,EOMONTH(AF$4,0)),Assumptions!$F$4:$F$44))/NETWORKDAYS($K94,$L94,Assumptions!$F$4:$F$44)) -> 0 | AG94: =IF($J94=0,0,MAX(0,NETWORKDAYS(MAX($K94,AG$4),MIN($L94,EOMONTH(AG$4,0)),Assumptions!$F$4:$F$44))/NETWORKDAYS($K94,$L94,Assumptions!$F$4:$F$44)) -> 0 | AH94: =IF($J94=0,0,MAX(0,NETWORKDAYS(MAX($K94,AH$4),MIN($L94,EOMONTH(AH$4,0)),Assumptions!$F$4:$F$44))/NETWORKDAYS($K94,$L94,Assumptions!$F$4:$F$44)) -> 1 | AI94: =IF($J94=0,0,MAX(0,NETWORKDAYS(MAX($K94,AI$4),MIN($L94,EOMONTH(AI$4,0)),Assumptions!$F$4:$F$44))/NETWORKDAYS($K94,$L94,Assumptions!$F$4:$F$44)) -> 0 | AJ94: =IF($J94=0,0,MAX(0,NETWORKDAYS(MAX($K94,AJ$4),MIN($L94,EOMONTH(AJ$4,0)),Assumptions!$F$4:$F$44))/NETWORKDAYS($K94,$L94,Assumptions!$F$4:$F$44)) -> 0 | AK94: =IF($J94=0,0,MAX(0,NETWORKDAYS(MAX($K94,AK$4),MIN($L94,EOMONTH(AK$4,0)),Assumptions!$F$4:$F$44))/NETWORKDAYS($K94,$L94,Assumptions!$F$4:$F$44)) -> 0 | AL94: =IF($J94=0,0,MAX(0,NETWORKDAYS(MAX($K94,AL$4),MIN($L94,EOMONTH(AL$4,0)),Assumptions!$F$4:$F$44))/NETWORKDAYS($K94,$L94,Assumptions!$F$4:$F$44)) -> 0 | AM94: =IF($J94=0,0,MAX(0,NETWORKDAYS(MAX($K94,AM$4),MIN($L94,EOMONTH(AM$4,0)),Assumptions!$F$4:$F$44))/NETWORKDAYS($K94,$L94,Assumptions!$F$4:$F$44)) -> 0 | ... BC94: =IF($J94=0,0,MAX(0,NETWORKDAYS(MAX($K94,BC$4),MIN($L94,EOMONTH(BC$4,0)),Assumptions!$F$4:$F$44))/NETWORKDAYS($K94,$L94,Assumptions!$F$4:$F$44)) -> 0
A95: 91 | B95: 3.17.2 | C95: 3 | D95: Subtask | E95: Build and unit tests | F95: Phase 1 | G95: Platform | H95: BE | I95: 58 | J95: 27 | K95: =WORKDAY(Assumptions!$C$4,I95,Assumptions!$F$4:$F$44) -> 46408 | L95: =IF(J95=0,K95,WORKDAY(K95,J95-1,Assumptions!$F$4:$F$44)) -> 46444 | N95: 0 | O95: 0 | P95: 0 | Q95: 14 | R95: 4 | S95: 0 | T95: 0 | U95: 0 | V95: 0 | W95: 9 | X95: 0 | Y95: =SUM(N95:X95) -> 27 | Z95: =Y95*(1+Assumptions!$C$5) -> 31.05 | AA95: Working service | AB95: Not started | AD95: 0 | AF95: =IF($J95=0,0,MAX(0,NETWORKDAYS(MAX($K95,AF$4),MIN($L95,EOMONTH(AF$4,0)),Assumptions!$F$4:$F$44))/NETWORKDAYS($K95,$L95,Assumptions!$F$4:$F$44)) -> 0 | AG95: =IF($J95=0,0,MAX(0,NETWORKDAYS(MAX($K95,AG$4),MIN($L95,EOMONTH(AG$4,0)),Assumptions!$F$4:$F$44))/NETWORKDAYS($K95,$L95,Assumptions!$F$4:$F$44)) -> 0 | AH95: =IF($J95=0,0,MAX(0,NETWORKDAYS(MAX($K95,AH$4),MIN($L95,EOMONTH(AH$4,0)),Assumptions!$F$4:$F$44))/NETWORKDAYS($K95,$L95,Assumptions!$F$4:$F$44)) -> 0.25925926 | AI95: =IF($J95=0,0,MAX(0,NETWORKDAYS(MAX($K95,AI$4),MIN($L95,EOMONTH(AI$4,0)),Assumptions!$F$4:$F$44))/NETWORKDAYS($K95,$L95,Assumptions!$F$4:$F$44)) -> 0.74074074 | AJ95: =IF($J95=0,0,MAX(0,NETWORKDAYS(MAX($K95,AJ$4),MIN($L95,EOMONTH(AJ$4,0)),Assumptions!$F$4:$F$44))/NETWORKDAYS($K95,$L95,Assumptions!$F$4:$F$44)) -> 0 | AK95: =IF($J95=0,0,MAX(0,NETWORKDAYS(MAX($K95,AK$4),MIN($L95,EOMONTH(AK$4,0)),Assumptions!$F$4:$F$44))/NETWORKDAYS($K95,$L95,Assumptions!$F$4:$F$44)) -> 0 | AL95: =IF($J95=0,0,MAX(0,NETWORKDAYS(MAX($K95,AL$4),MIN($L95,EOMONTH(AL$4,0)),Assumptions!$F$4:$F$44))/NETWORKDAYS($K95,$L95,Assumptions!$F$4:$F$44)) -> 0 | AM95: =IF($J95=0,0,MAX(0,NETWORKDAYS(MAX($K95,AM$4),MIN($L95,EOMONTH(AM$4,0)),Assumptions!$F$4:$F$44))/NETWORKDAYS($K95,$L95,Assumptions!$F$4:$F$44)) -> 0 | ... BC95: =IF($J95=0,0,MAX(0,NETWORKDAYS(MAX($K95,BC$4),MIN($L95,EOMONTH(BC$4,0)),Assumptions!$F$4:$F$44))/NETWORKDAYS($K95,$L95,Assumptions!$F$4:$F$44)) -> 0
A96: 92 | B96: 3.17.3 | C96: 3 | D96: Subtask | E96: Component, security and contract tests | F96: Phase 1 | G96: Platform | H96: QA | I96: 83 | J96: 11 | K96: =WORKDAY(Assumptions!$C$4,I96,Assumptions!$F$4:$F$44) -> 46443 | L96: =IF(J96=0,K96,WORKDAY(K96,J96-1,Assumptions!$F$4:$F$44)) -> 46457 | N96: 0 | O96: 0 | P96: 0 | Q96: 2 | R96: 0 | S96: 0 | T96: 0 | U96: 0 | V96: 4 | W96: 0 | X96: 0 | Y96: =SUM(N96:X96) -> 6 | Z96: =Y96*(1+Assumptions!$C$5) -> 6.9 | AA96: Test report | AB96: Not started | AD96: 0 | AF96: =IF($J96=0,0,MAX(0,NETWORKDAYS(MAX($K96,AF$4),MIN($L96,EOMONTH(AF$4,0)),Assumptions!$F$4:$F$44))/NETWORKDAYS($K96,$L96,Assumptions!$F$4:$F$44)) -> 0 | AG96: =IF($J96=0,0,MAX(0,NETWORKDAYS(MAX($K96,AG$4),MIN($L96,EOMONTH(AG$4,0)),Assumptions!$F$4:$F$44))/NETWORKDAYS($K96,$L96,Assumptions!$F$4:$F$44)) -> 0 | AH96: =IF($J96=0,0,MAX(0,NETWORKDAYS(MAX($K96,AH$4),MIN($L96,EOMONTH(AH$4,0)),Assumptions!$F$4:$F$44))/NETWORKDAYS($K96,$L96,Assumptions!$F$4:$F$44)) -> 0 | AI96: =IF($J96=0,0,MAX(0,NETWORKDAYS(MAX($K96,AI$4),MIN($L96,EOMONTH(AI$4,0)),Assumptions!$F$4:$F$44))/NETWORKDAYS($K96,$L96,Assumptions!$F$4:$F$44)) -> 0.18181818 | AJ96: =IF($J96=0,0,MAX(0,NETWORKDAYS(MAX($K96,AJ$4),MIN($L96,EOMONTH(AJ$4,0)),Assumptions!$F$4:$F$44))/NETWORKDAYS($K96,$L96,Assumptions!$F$4:$F$44)) -> 0.81818182 | AK96: =IF($J96=0,0,MAX(0,NETWORKDAYS(MAX($K96,AK$4),MIN($L96,EOMONTH(AK$4,0)),Assumptions!$F$4:$F$44))/NETWORKDAYS($K96,$L96,Assumptions!$F$4:$F$44)) -> 0 | AL96: =IF($J96=0,0,MAX(0,NETWORKDAYS(MAX($K96,AL$4),MIN($L96,EOMONTH(AL$4,0)),Assumptions!$F$4:$F$44))/NETWORKDAYS($K96,$L96,Assumptions!$F$4:$F$44)) -> 0 | AM96: =IF($J96=0,0,MAX(0,NETWORKDAYS(MAX($K96,AM$4),MIN($L96,EOMONTH(AM$4,0)),Assumptions!$F$4:$F$44))/NETWORKDAYS($K96,$L96,Assumptions!$F$4:$F$44)) -> 0 | ... BC96: =IF($J96=0,0,MAX(0,NETWORKDAYS(MAX($K96,BC$4),MIN($L96,EOMONTH(BC$4,0)),Assumptions!$F$4:$F$44))/NETWORKDAYS($K96,$L96,Assumptions!$F$4:$F$44)) -> 0
A97: 93 | B97: 3.18 | C97: 2 | D97: Task | E97: Observability: OpenTelemetry, Prometheus, Grafana, Loki | F97: Phase 1 | G97: Platform | J97: =NETWORKDAYS(K97,L97,Assumptions!$F$4:$F$44) -> 39 | K97: =MIN(K98:K100) -> 46350 | L97: =MAX(L98:L100) -> 46402 | N97: =SUMPRODUCT(($C$98:$C$100=3)*(N98:N100)) -> 0 | O97: =SUMPRODUCT(($C$98:$C$100=3)*(O98:O100)) -> 0 | P97: =SUMPRODUCT(($C$98:$C$100=3)*(P98:P100)) -> 2 | Q97: =SUMPRODUCT(($C$98:$C$100=3)*(Q98:Q100)) -> 4 | R97: =SUMPRODUCT(($C$98:$C$100=3)*(R98:R100)) -> 0 | S97: =SUMPRODUCT(($C$98:$C$100=3)*(S98:S100)) -> 0 | T97: =SUMPRODUCT(($C$98:$C$100=3)*(T98:T100)) -> 0 | U97: =SUMPRODUCT(($C$98:$C$100=3)*(U98:U100)) -> 11 | ... X97: =SUMPRODUCT(($C$98:$C$100=3)*(X98:X100)) -> 0 | Y97: =SUM(N97:X97) -> 20 | Z97: =Y97*(1+Assumptions!$C$5) -> 23 | AA97: NFR-018 | AF97: 0 | AG97: 0 | AH97: 0 | AI97: 0 | AJ97: 0 | AK97: 0 | AL97: 0 | AM97: 0 | AN97: 0 | AO97: 0 | AP97: 0 | AQ97: 0 | AR97: 0 | AS97: 0 | AT97: 0 | AU97: 0 | AV97: 0 | AW97: 0 | AX97: 0 | AY97: 0 | AZ97: 0 | BA97: 0 | BB97: 0 | BC97: 0
A98: 94 | B98: 3.18.1 | C98: 3 | D98: Subtask | E98: Detailed design and contracts | F98: Phase 1 | G98: Platform | H98: ARC | I98: 16 | J98: 8 | K98: =WORKDAY(Assumptions!$C$4,I98,Assumptions!$F$4:$F$44) -> 46350 | L98: =IF(J98=0,K98,WORKDAY(K98,J98-1,Assumptions!$F$4:$F$44)) -> 46359 | M98: 20 | N98: 0 | O98: 0 | P98: 2 | Q98: 0 | R98: 0 | S98: 0 | T98: 0 | U98: 0 | V98: 0 | W98: 0 | X98: 0 | Y98: =SUM(N98:X98) -> 2 | Z98: =Y98*(1+Assumptions!$C$5) -> 2.3 | AA98: Design note, OpenAPI and event schemas | AB98: Not started | AD98: 0 | AF98: =IF($J98=0,0,MAX(0,NETWORKDAYS(MAX($K98,AF$4),MIN($L98,EOMONTH(AF$4,0)),Assumptions!$F$4:$F$44))/NETWORKDAYS($K98,$L98,Assumptions!$F$4:$F$44)) -> 0.625 | AG98: =IF($J98=0,0,MAX(0,NETWORKDAYS(MAX($K98,AG$4),MIN($L98,EOMONTH(AG$4,0)),Assumptions!$F$4:$F$44))/NETWORKDAYS($K98,$L98,Assumptions!$F$4:$F$44)) -> 0.375 | AH98: =IF($J98=0,0,MAX(0,NETWORKDAYS(MAX($K98,AH$4),MIN($L98,EOMONTH(AH$4,0)),Assumptions!$F$4:$F$44))/NETWORKDAYS($K98,$L98,Assumptions!$F$4:$F$44)) -> 0 | AI98: =IF($J98=0,0,MAX(0,NETWORKDAYS(MAX($K98,AI$4),MIN($L98,EOMONTH(AI$4,0)),Assumptions!$F$4:$F$44))/NETWORKDAYS($K98,$L98,Assumptions!$F$4:$F$44)) -> 0 | AJ98: =IF($J98=0,0,MAX(0,NETWORKDAYS(MAX($K98,AJ$4),MIN($L98,EOMONTH(AJ$4,0)),Assumptions!$F$4:$F$44))/NETWORKDAYS($K98,$L98,Assumptions!$F$4:$F$44)) -> 0 | AK98: =IF($J98=0,0,MAX(0,NETWORKDAYS(MAX($K98,AK$4),MIN($L98,EOMONTH(AK$4,0)),Assumptions!$F$4:$F$44))/NETWORKDAYS($K98,$L98,Assumptions!$F$4:$F$44)) -> 0 | AL98: =IF($J98=0,0,MAX(0,NETWORKDAYS(MAX($K98,AL$4),MIN($L98,EOMONTH(AL$4,0)),Assumptions!$F$4:$F$44))/NETWORKDAYS($K98,$L98,Assumptions!$F$4:$F$44)) -> 0 | AM98: =IF($J98=0,0,MAX(0,NETWORKDAYS(MAX($K98,AM$4),MIN($L98,EOMONTH(AM$4,0)),Assumptions!$F$4:$F$44))/NETWORKDAYS($K98,$L98,Assumptions!$F$4:$F$44)) -> 0 | ... BC98: =IF($J98=0,0,MAX(0,NETWORKDAYS(MAX($K98,BC$4),MIN($L98,EOMONTH(BC$4,0)),Assumptions!$F$4:$F$44))/NETWORKDAYS($K98,$L98,Assumptions!$F$4:$F$44)) -> 0
A99: 95 | B99: 3.18.2 | C99: 3 | D99: Subtask | E99: Build and unit tests | F99: Phase 1 | G99: Platform | H99: DEV | I99: 23 | J99: 24 | K99: =WORKDAY(Assumptions!$C$4,I99,Assumptions!$F$4:$F$44) -> 46359 | L99: =IF(J99=0,K99,WORKDAY(K99,J99-1,Assumptions!$F$4:$F$44)) -> 46392 | N99: 0 | O99: 0 | P99: 0 | Q99: 4 | R99: 0 | S99: 0 | T99: 0 | U99: 11 | V99: 0 | W99: 0 | X99: 0 | Y99: =SUM(N99:X99) -> 15 | Z99: =Y99*(1+Assumptions!$C$5) -> 17.25 | AA99: Working service | AB99: Not started | AD99: 0 | AF99: =IF($J99=0,0,MAX(0,NETWORKDAYS(MAX($K99,AF$4),MIN($L99,EOMONTH(AF$4,0)),Assumptions!$F$4:$F$44))/NETWORKDAYS($K99,$L99,Assumptions!$F$4:$F$44)) -> 0 | AG99: =IF($J99=0,0,MAX(0,NETWORKDAYS(MAX($K99,AG$4),MIN($L99,EOMONTH(AG$4,0)),Assumptions!$F$4:$F$44))/NETWORKDAYS($K99,$L99,Assumptions!$F$4:$F$44)) -> 0.875 | AH99: =IF($J99=0,0,MAX(0,NETWORKDAYS(MAX($K99,AH$4),MIN($L99,EOMONTH(AH$4,0)),Assumptions!$F$4:$F$44))/NETWORKDAYS($K99,$L99,Assumptions!$F$4:$F$44)) -> 0.125 | AI99: =IF($J99=0,0,MAX(0,NETWORKDAYS(MAX($K99,AI$4),MIN($L99,EOMONTH(AI$4,0)),Assumptions!$F$4:$F$44))/NETWORKDAYS($K99,$L99,Assumptions!$F$4:$F$44)) -> 0 | AJ99: =IF($J99=0,0,MAX(0,NETWORKDAYS(MAX($K99,AJ$4),MIN($L99,EOMONTH(AJ$4,0)),Assumptions!$F$4:$F$44))/NETWORKDAYS($K99,$L99,Assumptions!$F$4:$F$44)) -> 0 | AK99: =IF($J99=0,0,MAX(0,NETWORKDAYS(MAX($K99,AK$4),MIN($L99,EOMONTH(AK$4,0)),Assumptions!$F$4:$F$44))/NETWORKDAYS($K99,$L99,Assumptions!$F$4:$F$44)) -> 0 | AL99: =IF($J99=0,0,MAX(0,NETWORKDAYS(MAX($K99,AL$4),MIN($L99,EOMONTH(AL$4,0)),Assumptions!$F$4:$F$44))/NETWORKDAYS($K99,$L99,Assumptions!$F$4:$F$44)) -> 0 | AM99: =IF($J99=0,0,MAX(0,NETWORKDAYS(MAX($K99,AM$4),MIN($L99,EOMONTH(AM$4,0)),Assumptions!$F$4:$F$44))/NETWORKDAYS($K99,$L99,Assumptions!$F$4:$F$44)) -> 0 | ... BC99: =IF($J99=0,0,MAX(0,NETWORKDAYS(MAX($K99,BC$4),MIN($L99,EOMONTH(BC$4,0)),Assumptions!$F$4:$F$44))/NETWORKDAYS($K99,$L99,Assumptions!$F$4:$F$44)) -> 0
A100: 96 | B100: 3.18.3 | C100: 3 | D100: Subtask | E100: Component, security and contract tests | F100: Phase 1 | G100: Platform | H100: QA | I100: 45 | J100: 10 | K100: =WORKDAY(Assumptions!$C$4,I100,Assumptions!$F$4:$F$44) -> 46391 | L100: =IF(J100=0,K100,WORKDAY(K100,J100-1,Assumptions!$F$4:$F$44)) -> 46402 | N100: 0 | O100: 0 | P100: 0 | Q100: 0 | R100: 0 | S100: 0 | T100: 0 | U100: 0 | V100: 3 | W100: 0 | X100: 0 | Y100: =SUM(N100:X100) -> 3 | Z100: =Y100*(1+Assumptions!$C$5) -> 3.45 | AA100: Test report | AB100: Not started | AD100: 0 | AF100: =IF($J100=0,0,MAX(0,NETWORKDAYS(MAX($K100,AF$4),MIN($L100,EOMONTH(AF$4,0)),Assumptions!$F$4:$F$44))/NETWORKDAYS($K100,$L100,Assumptions!$F$4:$F$44)) -> 0 | AG100: =IF($J100=0,0,MAX(0,NETWORKDAYS(MAX($K100,AG$4),MIN($L100,EOMONTH(AG$4,0)),Assumptions!$F$4:$F$44))/NETWORKDAYS($K100,$L100,Assumptions!$F$4:$F$44)) -> 0 | AH100: =IF($J100=0,0,MAX(0,NETWORKDAYS(MAX($K100,AH$4),MIN($L100,EOMONTH(AH$4,0)),Assumptions!$F$4:$F$44))/NETWORKDAYS($K100,$L100,Assumptions!$F$4:$F$44)) -> 1 | AI100: =IF($J100=0,0,MAX(0,NETWORKDAYS(MAX($K100,AI$4),MIN($L100,EOMONTH(AI$4,0)),Assumptions!$F$4:$F$44))/NETWORKDAYS($K100,$L100,Assumptions!$F$4:$F$44)) -> 0 | AJ100: =IF($J100=0,0,MAX(0,NETWORKDAYS(MAX($K100,AJ$4),MIN($L100,EOMONTH(AJ$4,0)),Assumptions!$F$4:$F$44))/NETWORKDAYS($K100,$L100,Assumptions!$F$4:$F$44)) -> 0 | AK100: =IF($J100=0,0,MAX(0,NETWORKDAYS(MAX($K100,AK$4),MIN($L100,EOMONTH(AK$4,0)),Assumptions!$F$4:$F$44))/NETWORKDAYS($K100,$L100,Assumptions!$F$4:$F$44)) -> 0 | AL100: =IF($J100=0,0,MAX(0,NETWORKDAYS(MAX($K100,AL$4),MIN($L100,EOMONTH(AL$4,0)),Assumptions!$F$4:$F$44))/NETWORKDAYS($K100,$L100,Assumptions!$F$4:$F$44)) -> 0 | AM100: =IF($J100=0,0,MAX(0,NETWORKDAYS(MAX($K100,AM$4),MIN($L100,EOMONTH(AM$4,0)),Assumptions!$F$4:$F$44))/NETWORKDAYS($K100,$L100,Assumptions!$F$4:$F$44)) -> 0 | ... BC100: =IF($J100=0,0,MAX(0,NETWORKDAYS(MAX($K100,BC$4),MIN($L100,EOMONTH(BC$4,0)),Assumptions!$F$4:$F$44))/NETWORKDAYS($K100,$L100,Assumptions!$F$4:$F$44)) -> 0
...

Sheet Team Summary
A1: Effort by team role (person-days)
A2: From subtask estimates in the Project Plan. Contingency and day rates come from the Assumptions sheet.
A4: By phase
A5: Group | B5: PM | C5: BA | D5: ARC | E5: BE | F5: FE | G5: MOB | H5: GIS | I5: DEV | J5: QA | K5: DATA | L5: TRN | M5: Total | N5: With contingency | O5: Cost (optional)
A6: All | B6: =SUMPRODUCT(('Project Plan'!$C$5:$C$480=3)*('Project Plan'!$F$5:$F$480=$A6)*('Project Plan'!$N$5:$N$480)) -> 345 | C6: =SUMPRODUCT(('Project Plan'!$C$5:$C$480=3)*('Project Plan'!$F$5:$F$480=$A6)*('Project Plan'!$O$5:$O$480)) -> 30 | D6: =SUMPRODUCT(('Project Plan'!$C$5:$C$480=3)*('Project Plan'!$F$5:$F$480=$A6)*('Project Plan'!$P$5:$P$480)) -> 89 | E6: =SUMPRODUCT(('Project Plan'!$C$5:$C$480=3)*('Project Plan'!$F$5:$F$480=$A6)*('Project Plan'!$Q$5:$Q$480)) -> 30 | F6: =SUMPRODUCT(('Project Plan'!$C$5:$C$480=3)*('Project Plan'!$F$5:$F$480=$A6)*('Project Plan'!$R$5:$R$480)) -> 0 | G6: =SUMPRODUCT(('Project Plan'!$C$5:$C$480=3)*('Project Plan'!$F$5:$F$480=$A6)*('Project Plan'!$S$5:$S$480)) -> 0 | H6: =SUMPRODUCT(('Project Plan'!$C$5:$C$480=3)*('Project Plan'!$F$5:$F$480=$A6)*('Project Plan'!$T$5:$T$480)) -> 0 | I6: =SUMPRODUCT(('Project Plan'!$C$5:$C$480=3)*('Project Plan'!$F$5:$F$480=$A6)*('Project Plan'!$U$5:$U$480)) -> 15 | J6: =SUMPRODUCT(('Project Plan'!$C$5:$C$480=3)*('Project Plan'!$F$5:$F$480=$A6)*('Project Plan'!$V$5:$V$480)) -> 8 | K6: =SUMPRODUCT(('Project Plan'!$C$5:$C$480=3)*('Project Plan'!$F$5:$F$480=$A6)*('Project Plan'!$W$5:$W$480)) -> 0 | L6: =SUMPRODUCT(('Project Plan'!$C$5:$C$480=3)*('Project Plan'!$F$5:$F$480=$A6)*('Project Plan'!$X$5:$X$480)) -> 10 | M6: =SUM(B6:L6) -> 527 | N6: =M6*(1+Assumptions!$C$5) -> 606.05 | O6: =(B6*Assumptions!$C$12+C6*Assumptions!$C$13+D6*Assumptions!$C$14+E6*Assumptions!$C$15+F6*Assumptions!$C$16+G6*Assumptions!$C$17+H6*Assumptions!$C$18+I6*Assumptions!$C$19+J6*Assumptions!$C$20+K6*Assumptions!$C$21+L6*Assumptions!$C$22)*(1+Assumptions!$C$5) -> 0
A7: Phase 0 | B7: =SUMPRODUCT(('Project Plan'!$C$5:$C$480=3)*('Project Plan'!$F$5:$F$480=$A7)*('Project Plan'!$N$5:$N$480)) -> 18 | C7: =SUMPRODUCT(('Project Plan'!$C$5:$C$480=3)*('Project Plan'!$F$5:$F$480=$A7)*('Project Plan'!$O$5:$O$480)) -> 50 | D7: =SUMPRODUCT(('Project Plan'!$C$5:$C$480=3)*('Project Plan'!$F$5:$F$480=$A7)*('Project Plan'!$P$5:$P$480)) -> 30 | E7: =SUMPRODUCT(('Project Plan'!$C$5:$C$480=3)*('Project Plan'!$F$5:$F$480=$A7)*('Project Plan'!$Q$5:$Q$480)) -> 3 | F7: =SUMPRODUCT(('Project Plan'!$C$5:$C$480=3)*('Project Plan'!$F$5:$F$480=$A7)*('Project Plan'!$R$5:$R$480)) -> 15 | G7: =SUMPRODUCT(('Project Plan'!$C$5:$C$480=3)*('Project Plan'!$F$5:$F$480=$A7)*('Project Plan'!$S$5:$S$480)) -> 0 | H7: =SUMPRODUCT(('Project Plan'!$C$5:$C$480=3)*('Project Plan'!$F$5:$F$480=$A7)*('Project Plan'!$T$5:$T$480)) -> 0 | I7: =SUMPRODUCT(('Project Plan'!$C$5:$C$480=3)*('Project Plan'!$F$5:$F$480=$A7)*('Project Plan'!$U$5:$U$480)) -> 34 | J7: =SUMPRODUCT(('Project Plan'!$C$5:$C$480=3)*('Project Plan'!$F$5:$F$480=$A7)*('Project Plan'!$V$5:$V$480)) -> 0 | K7: =SUMPRODUCT(('Project Plan'!$C$5:$C$480=3)*('Project Plan'!$F$5:$F$480=$A7)*('Project Plan'!$W$5:$W$480)) -> 10 | L7: =SUMPRODUCT(('Project Plan'!$C$5:$C$480=3)*('Project Plan'!$F$5:$F$480=$A7)*('Project Plan'!$X$5:$X$480)) -> 0 | M7: =SUM(B7:L7) -> 160 | N7: =M7*(1+Assumptions!$C$5) -> 184 | O7: =(B7*Assumptions!$C$12+C7*Assumptions!$C$13+D7*Assumptions!$C$14+E7*Assumptions!$C$15+F7*Assumptions!$C$16+G7*Assumptions!$C$17+H7*Assumptions!$C$18+I7*Assumptions!$C$19+J7*Assumptions!$C$20+K7*Assumptions!$C$21+L7*Assumptions!$C$22)*(1+Assumptions!$C$5) -> 0
A8: Phase 1 | B8: =SUMPRODUCT(('Project Plan'!$C$5:$C$480=3)*('Project Plan'!$F$5:$F$480=$A8)*('Project Plan'!$N$5:$N$480)) -> 5 | C8: =SUMPRODUCT(('Project Plan'!$C$5:$C$480=3)*('Project Plan'!$F$5:$F$480=$A8)*('Project Plan'!$O$5:$O$480)) -> 228 | D8: =SUMPRODUCT(('Project Plan'!$C$5:$C$480=3)*('Project Plan'!$F$5:$F$480=$A8)*('Project Plan'!$P$5:$P$480)) -> 116 | E8: =SUMPRODUCT(('Project Plan'!$C$5:$C$480=3)*('Project Plan'!$F$5:$F$480=$A8)*('Project Plan'!$Q$5:$Q$480)) -> 1013 | F8: =SUMPRODUCT(('Project Plan'!$C$5:$C$480=3)*('Project Plan'!$F$5:$F$480=$A8)*('Project Plan'!$R$5:$R$480)) -> 499 | G8: =SUMPRODUCT(('Project Plan'!$C$5:$C$480=3)*('Project Plan'!$F$5:$F$480=$A8)*('Project Plan'!$S$5:$S$480)) -> 129 | H8: =SUMPRODUCT(('Project Plan'!$C$5:$C$480=3)*('Project Plan'!$F$5:$F$480=$A8)*('Project Plan'!$T$5:$T$480)) -> 82 | I8: =SUMPRODUCT(('Project Plan'!$C$5:$C$480=3)*('Project Plan'!$F$5:$F$480=$A8)*('Project Plan'!$U$5:$U$480)) -> 115 | J8: =SUMPRODUCT(('Project Plan'!$C$5:$C$480=3)*('Project Plan'!$F$5:$F$480=$A8)*('Project Plan'!$V$5:$V$480)) -> 409 | K8: =SUMPRODUCT(('Project Plan'!$C$5:$C$480=3)*('Project Plan'!$F$5:$F$480=$A8)*('Project Plan'!$W$5:$W$480)) -> 98 | L8: =SUMPRODUCT(('Project Plan'!$C$5:$C$480=3)*('Project Plan'!$F$5:$F$480=$A8)*('Project Plan'!$X$5:$X$480)) -> 63 | M8: =SUM(B8:L8) -> 2757 | N8: =M8*(1+Assumptions!$C$5) -> 3170.55 | O8: =(B8*Assumptions!$C$12+C8*Assumptions!$C$13+D8*Assumptions!$C$14+E8*Assumptions!$C$15+F8*Assumptions!$C$16+G8*Assumptions!$C$17+H8*Assumptions!$C$18+I8*Assumptions!$C$19+J8*Assumptions!$C$20+K8*Assumptions!$C$21+L8*Assumptions!$C$22)*(1+Assumptions!$C$5) -> 0
A9: Phase 2 | B9: =SUMPRODUCT(('Project Plan'!$C$5:$C$480=3)*('Project Plan'!$F$5:$F$480=$A9)*('Project Plan'!$N$5:$N$480)) -> 5 | C9: =SUMPRODUCT(('Project Plan'!$C$5:$C$480=3)*('Project Plan'!$F$5:$F$480=$A9)*('Project Plan'!$O$5:$O$480)) -> 153 | D9: =SUMPRODUCT(('Project Plan'!$C$5:$C$480=3)*('Project Plan'!$F$5:$F$480=$A9)*('Project Plan'!$P$5:$P$480)) -> 42 | E9: =SUMPRODUCT(('Project Plan'!$C$5:$C$480=3)*('Project Plan'!$F$5:$F$480=$A9)*('Project Plan'!$Q$5:$Q$480)) -> 558 | F9: =SUMPRODUCT(('Project Plan'!$C$5:$C$480=3)*('Project Plan'!$F$5:$F$480=$A9)*('Project Plan'!$R$5:$R$480)) -> 303 | G9: =SUMPRODUCT(('Project Plan'!$C$5:$C$480=3)*('Project Plan'!$F$5:$F$480=$A9)*('Project Plan'!$S$5:$S$480)) -> 102 | H9: =SUMPRODUCT(('Project Plan'!$C$5:$C$480=3)*('Project Plan'!$F$5:$F$480=$A9)*('Project Plan'!$T$5:$T$480)) -> 88 | I9: =SUMPRODUCT(('Project Plan'!$C$5:$C$480=3)*('Project Plan'!$F$5:$F$480=$A9)*('Project Plan'!$U$5:$U$480)) -> 20 | J9: =SUMPRODUCT(('Project Plan'!$C$5:$C$480=3)*('Project Plan'!$F$5:$F$480=$A9)*('Project Plan'!$V$5:$V$480)) -> 229 | K9: =SUMPRODUCT(('Project Plan'!$C$5:$C$480=3)*('Project Plan'!$F$5:$F$480=$A9)*('Project Plan'!$W$5:$W$480)) -> 73 | L9: =SUMPRODUCT(('Project Plan'!$C$5:$C$480=3)*('Project Plan'!$F$5:$F$480=$A9)*('Project Plan'!$X$5:$X$480)) -> 49 | M9: =SUM(B9:L9) -> 1622 | N9: =M9*(1+Assumptions!$C$5) -> 1865.3 | O9: =(B9*Assumptions!$C$12+C9*Assumptions!$C$13+D9*Assumptions!$C$14+E9*Assumptions!$C$15+F9*Assumptions!$C$16+G9*Assumptions!$C$17+H9*Assumptions!$C$18+I9*Assumptions!$C$19+J9*Assumptions!$C$20+K9*Assumptions!$C$21+L9*Assumptions!$C$22)*(1+Assumptions!$C$5) -> 0
A10: Phase 3 | B10: =SUMPRODUCT(('Project Plan'!$C$5:$C$480=3)*('Project Plan'!$F$5:$F$480=$A10)*('Project Plan'!$N$5:$N$480)) -> 5 | C10: =SUMPRODUCT(('Project Plan'!$C$5:$C$480=3)*('Project Plan'!$F$5:$F$480=$A10)*('Project Plan'!$O$5:$O$480)) -> 114 | D10: =SUMPRODUCT(('Project Plan'!$C$5:$C$480=3)*('Project Plan'!$F$5:$F$480=$A10)*('Project Plan'!$P$5:$P$480)) -> 32 | E10: =SUMPRODUCT(('Project Plan'!$C$5:$C$480=3)*('Project Plan'!$F$5:$F$480=$A10)*('Project Plan'!$Q$5:$Q$480)) -> 399 | F10: =SUMPRODUCT(('Project Plan'!$C$5:$C$480=3)*('Project Plan'!$F$5:$F$480=$A10)*('Project Plan'!$R$5:$R$480)) -> 184 | G10: =SUMPRODUCT(('Project Plan'!$C$5:$C$480=3)*('Project Plan'!$F$5:$F$480=$A10)*('Project Plan'!$S$5:$S$480)) -> 57 | H10: =SUMPRODUCT(('Project Plan'!$C$5:$C$480=3)*('Project Plan'!$F$5:$F$480=$A10)*('Project Plan'!$T$5:$T$480)) -> 39 | I10: =SUMPRODUCT(('Project Plan'!$C$5:$C$480=3)*('Project Plan'!$F$5:$F$480=$A10)*('Project Plan'!$U$5:$U$480)) -> 24 | J10: =SUMPRODUCT(('Project Plan'!$C$5:$C$480=3)*('Project Plan'!$F$5:$F$480=$A10)*('Project Plan'!$V$5:$V$480)) -> 179 | K10: =SUMPRODUCT(('Project Plan'!$C$5:$C$480=3)*('Project Plan'!$F$5:$F$480=$A10)*('Project Plan'!$W$5:$W$480)) -> 15 | L10: =SUMPRODUCT(('Project Plan'!$C$5:$C$480=3)*('Project Plan'!$F$5:$F$480=$A10)*('Project Plan'!$X$5:$X$480)) -> 40 | M10: =SUM(B10:L10) -> 1088 | N10: =M10*(1+Assumptions!$C$5) -> 1251.2 | O10: =(B10*Assumptions!$C$12+C10*Assumptions!$C$13+D10*Assumptions!$C$14+E10*Assumptions!$C$15+F10*Assumptions!$C$16+G10*Assumptions!$C$17+H10*Assumptions!$C$18+I10*Assumptions!$C$19+J10*Assumptions!$C$20+K10*Assumptions!$C$21+L10*Assumptions!$C$22)*(1+Assumptions!$C$5) -> 0
A11: Phase 4 | B11: =SUMPRODUCT(('Project Plan'!$C$5:$C$480=3)*('Project Plan'!$F$5:$F$480=$A11)*('Project Plan'!$N$5:$N$480)) -> 4 | C11: =SUMPRODUCT(('Project Plan'!$C$5:$C$480=3)*('Project Plan'!$F$5:$F$480=$A11)*('Project Plan'!$O$5:$O$480)) -> 101 | D11: =SUMPRODUCT(('Project Plan'!$C$5:$C$480=3)*('Project Plan'!$F$5:$F$480=$A11)*('Project Plan'!$P$5:$P$480)) -> 27 | E11: =SUMPRODUCT(('Project Plan'!$C$5:$C$480=3)*('Project Plan'!$F$5:$F$480=$A11)*('Project Plan'!$Q$5:$Q$480)) -> 306 | F11: =SUMPRODUCT(('Project Plan'!$C$5:$C$480=3)*('Project Plan'!$F$5:$F$480=$A11)*('Project Plan'!$R$5:$R$480)) -> 151 | G11: =SUMPRODUCT(('Project Plan'!$C$5:$C$480=3)*('Project Plan'!$F$5:$F$480=$A11)*('Project Plan'!$S$5:$S$480)) -> 32 | H11: =SUMPRODUCT(('Project Plan'!$C$5:$C$480=3)*('Project Plan'!$F$5:$F$480=$A11)*('Project Plan'!$T$5:$T$480)) -> 8 | I11: =SUMPRODUCT(('Project Plan'!$C$5:$C$480=3)*('Project Plan'!$F$5:$F$480=$A11)*('Project Plan'!$U$5:$U$480)) -> 20 | J11: =SUMPRODUCT(('Project Plan'!$C$5:$C$480=3)*('Project Plan'!$F$5:$F$480=$A11)*('Project Plan'!$V$5:$V$480)) -> 147 | K11: =SUMPRODUCT(('Project Plan'!$C$5:$C$480=3)*('Project Plan'!$F$5:$F$480=$A11)*('Project Plan'!$W$5:$W$480)) -> 66 | L11: =SUMPRODUCT(('Project Plan'!$C$5:$C$480=3)*('Project Plan'!$F$5:$F$480=$A11)*('Project Plan'!$X$5:$X$480)) -> 34 | M11: =SUM(B11:L11) -> 896 | N11: =M11*(1+Assumptions!$C$5) -> 1030.4 | O11: =(B11*Assumptions!$C$12+C11*Assumptions!$C$13+D11*Assumptions!$C$14+E11*Assumptions!$C$15+F11*Assumptions!$C$16+G11*Assumptions!$C$17+H11*Assumptions!$C$18+I11*Assumptions!$C$19+J11*Assumptions!$C$20+K11*Assumptions!$C$21+L11*Assumptions!$C$22)*(1+Assumptions!$C$5) -> 0
A12: Total | B12: =SUM(B6:B11) -> 382 | C12: =SUM(C6:C11) -> 676 | D12: =SUM(D6:D11) -> 336 | E12: =SUM(E6:E11) -> 2309 | F12: =SUM(F6:F11) -> 1152 | G12: =SUM(G6:G11) -> 320 | H12: =SUM(H6:H11) -> 217 | I12: =SUM(I6:I11) -> 228 | ... O12: =SUM(O6:O11) -> 0
A15: By module (Platform, modules, release activities; blank = governance and inception)
A16: Group | B16: PM | C16: BA | D16: ARC | E16: BE | F16: FE | G16: MOB | H16: GIS | I16: DEV | J16: QA | K16: DATA | L16: TRN | M16: Total | N16: With contingency | O16: Cost (optional)
A17: Platform | B17: =SUMPRODUCT(('Project Plan'!$C$5:$C$480=3)*('Project Plan'!$G$5:$G$480=$A17)*('Project Plan'!$N$5:$N$480)) -> 0 | C17: =SUMPRODUCT(('Project Plan'!$C$5:$C$480=3)*('Project Plan'!$G$5:$G$480=$A17)*('Project Plan'!$O$5:$O$480)) -> 15 | D17: =SUMPRODUCT(('Project Plan'!$C$5:$C$480=3)*('Project Plan'!$G$5:$G$480=$A17)*('Project Plan'!$P$5:$P$480)) -> 56 | E17: =SUMPRODUCT(('Project Plan'!$C$5:$C$480=3)*('Project Plan'!$G$5:$G$480=$A17)*('Project Plan'!$Q$5:$Q$480)) -> 371 | F17: =SUMPRODUCT(('Project Plan'!$C$5:$C$480=3)*('Project Plan'!$G$5:$G$480=$A17)*('Project Plan'!$R$5:$R$480)) -> 111 | G17: =SUMPRODUCT(('Project Plan'!$C$5:$C$480=3)*('Project Plan'!$G$5:$G$480=$A17)*('Project Plan'!$S$5:$S$480)) -> 59 | H17: =SUMPRODUCT(('Project Plan'!$C$5:$C$480=3)*('Project Plan'!$G$5:$G$480=$A17)*('Project Plan'!$T$5:$T$480)) -> 68 | I17: =SUMPRODUCT(('Project Plan'!$C$5:$C$480=3)*('Project Plan'!$G$5:$G$480=$A17)*('Project Plan'!$U$5:$U$480)) -> 99 | J17: =SUMPRODUCT(('Project Plan'!$C$5:$C$480=3)*('Project Plan'!$G$5:$G$480=$A17)*('Project Plan'!$V$5:$V$480)) -> 134 | K17: =SUMPRODUCT(('Project Plan'!$C$5:$C$480=3)*('Project Plan'!$G$5:$G$480=$A17)*('Project Plan'!$W$5:$W$480)) -> 31 | L17: =SUMPRODUCT(('Project Plan'!$C$5:$C$480=3)*('Project Plan'!$G$5:$G$480=$A17)*('Project Plan'!$X$5:$X$480)) -> 0 | M17: =SUM(B17:L17) -> 944 | N17: =M17*(1+Assumptions!$C$5) -> 1085.6 | O17: =(B17*Assumptions!$C$12+C17*Assumptions!$C$13+D17*Assumptions!$C$14+E17*Assumptions!$C$15+F17*Assumptions!$C$16+G17*Assumptions!$C$17+H17*Assumptions!$C$18+I17*Assumptions!$C$19+J17*Assumptions!$C$20+K17*Assumptions!$C$21+L17*Assumptions!$C$22)*(1+Assumptions!$C$5) -> 0
A18: 1 Property Tax | B18: =SUMPRODUCT(('Project Plan'!$C$5:$C$480=3)*('Project Plan'!$G$5:$G$480=$A18)*('Project Plan'!$N$5:$N$480)) -> 1 | C18: =SUMPRODUCT(('Project Plan'!$C$5:$C$480=3)*('Project Plan'!$G$5:$G$480=$A18)*('Project Plan'!$O$5:$O$480)) -> 46 | D18: =SUMPRODUCT(('Project Plan'!$C$5:$C$480=3)*('Project Plan'!$G$5:$G$480=$A18)*('Project Plan'!$P$5:$P$480)) -> 13 | E18: =SUMPRODUCT(('Project Plan'!$C$5:$C$480=3)*('Project Plan'!$G$5:$G$480=$A18)*('Project Plan'!$Q$5:$Q$480)) -> 160 | F18: =SUMPRODUCT(('Project Plan'!$C$5:$C$480=3)*('Project Plan'!$G$5:$G$480=$A18)*('Project Plan'!$R$5:$R$480)) -> 92 | G18: =SUMPRODUCT(('Project Plan'!$C$5:$C$480=3)*('Project Plan'!$G$5:$G$480=$A18)*('Project Plan'!$S$5:$S$480)) -> 32 | H18: =SUMPRODUCT(('Project Plan'!$C$5:$C$480=3)*('Project Plan'!$G$5:$G$480=$A18)*('Project Plan'!$T$5:$T$480)) -> 18 | I18: =SUMPRODUCT(('Project Plan'!$C$5:$C$480=3)*('Project Plan'!$G$5:$G$480=$A18)*('Project Plan'!$U$5:$U$480)) -> 0 | J18: =SUMPRODUCT(('Project Plan'!$C$5:$C$480=3)*('Project Plan'!$G$5:$G$480=$A18)*('Project Plan'!$V$5:$V$480)) -> 59 | K18: =SUMPRODUCT(('Project Plan'!$C$5:$C$480=3)*('Project Plan'!$G$5:$G$480=$A18)*('Project Plan'!$W$5:$W$480)) -> 21 | L18: =SUMPRODUCT(('Project Plan'!$C$5:$C$480=3)*('Project Plan'!$G$5:$G$480=$A18)*('Project Plan'!$X$5:$X$480)) -> 11 | M18: =SUM(B18:L18) -> 453 | N18: =M18*(1+Assumptions!$C$5) -> 520.95 | O18: =(B18*Assumptions!$C$12+C18*Assumptions!$C$13+D18*Assumptions!$C$14+E18*Assumptions!$C$15+F18*Assumptions!$C$16+G18*Assumptions!$C$17+H18*Assumptions!$C$18+I18*Assumptions!$C$19+J18*Assumptions!$C$20+K18*Assumptions!$C$21+L18*Assumptions!$C$22)*(1+Assumptions!$C$5) -> 0
A19: 2 Water & Sewerage | B19: =SUMPRODUCT(('Project Plan'!$C$5:$C$480=3)*('Project Plan'!$G$5:$G$480=$A19)*('Project Plan'!$N$5:$N$480)) -> 1 | C19: =SUMPRODUCT(('Project Plan'!$C$5:$C$480=3)*('Project Plan'!$G$5:$G$480=$A19)*('Project Plan'!$O$5:$O$480)) -> 40 | D19: =SUMPRODUCT(('Project Plan'!$C$5:$C$480=3)*('Project Plan'!$G$5:$G$480=$A19)*('Project Plan'!$P$5:$P$480)) -> 11 | E19: =SUMPRODUCT(('Project Plan'!$C$5:$C$480=3)*('Project Plan'!$G$5:$G$480=$A19)*('Project Plan'!$Q$5:$Q$480)) -> 131 | F19: =SUMPRODUCT(('Project Plan'!$C$5:$C$480=3)*('Project Plan'!$G$5:$G$480=$A19)*('Project Plan'!$R$5:$R$480)) -> 87 | G19: =SUMPRODUCT(('Project Plan'!$C$5:$C$480=3)*('Project Plan'!$G$5:$G$480=$A19)*('Project Plan'!$S$5:$S$480)) -> 30 | H19: =SUMPRODUCT(('Project Plan'!$C$5:$C$480=3)*('Project Plan'!$G$5:$G$480=$A19)*('Project Plan'!$T$5:$T$480)) -> 17 | I19: =SUMPRODUCT(('Project Plan'!$C$5:$C$480=3)*('Project Plan'!$G$5:$G$480=$A19)*('Project Plan'!$U$5:$U$480)) -> 0 | J19: =SUMPRODUCT(('Project Plan'!$C$5:$C$480=3)*('Project Plan'!$G$5:$G$480=$A19)*('Project Plan'!$V$5:$V$480)) -> 51 | K19: =SUMPRODUCT(('Project Plan'!$C$5:$C$480=3)*('Project Plan'!$G$5:$G$480=$A19)*('Project Plan'!$W$5:$W$480)) -> 20 | L19: =SUMPRODUCT(('Project Plan'!$C$5:$C$480=3)*('Project Plan'!$G$5:$G$480=$A19)*('Project Plan'!$X$5:$X$480)) -> 10 | M19: =SUM(B19:L19) -> 398 | N19: =M19*(1+Assumptions!$C$5) -> 457.7 | O19: =(B19*Assumptions!$C$12+C19*Assumptions!$C$13+D19*Assumptions!$C$14+E19*Assumptions!$C$15+F19*Assumptions!$C$16+G19*Assumptions!$C$17+H19*Assumptions!$C$18+I19*Assumptions!$C$19+J19*Assumptions!$C$20+K19*Assumptions!$C$21+L19*Assumptions!$C$22)*(1+Assumptions!$C$5) -> 0
A20: 3 Citizen Desk & RTI | B20: =SUMPRODUCT(('Project Plan'!$C$5:$C$480=3)*('Project Plan'!$G$5:$G$480=$A20)*('Project Plan'!$N$5:$N$480)) -> 1 | C20: =SUMPRODUCT(('Project Plan'!$C$5:$C$480=3)*('Project Plan'!$G$5:$G$480=$A20)*('Project Plan'!$O$5:$O$480)) -> 35 | D20: =SUMPRODUCT(('Project Plan'!$C$5:$C$480=3)*('Project Plan'!$G$5:$G$480=$A20)*('Project Plan'!$P$5:$P$480)) -> 11 | E20: =SUMPRODUCT(('Project Plan'!$C$5:$C$480=3)*('Project Plan'!$G$5:$G$480=$A20)*('Project Plan'!$Q$5:$Q$480)) -> 124 | F20: =SUMPRODUCT(('Project Plan'!$C$5:$C$480=3)*('Project Plan'!$G$5:$G$480=$A20)*('Project Plan'!$R$5:$R$480)) -> 79 | G20: =SUMPRODUCT(('Project Plan'!$C$5:$C$480=3)*('Project Plan'!$G$5:$G$480=$A20)*('Project Plan'!$S$5:$S$480)) -> 9 | H20: =SUMPRODUCT(('Project Plan'!$C$5:$C$480=3)*('Project Plan'!$G$5:$G$480=$A20)*('Project Plan'!$T$5:$T$480)) -> 15 | I20: =SUMPRODUCT(('Project Plan'!$C$5:$C$480=3)*('Project Plan'!$G$5:$G$480=$A20)*('Project Plan'!$U$5:$U$480)) -> 0 | J20: =SUMPRODUCT(('Project Plan'!$C$5:$C$480=3)*('Project Plan'!$G$5:$G$480=$A20)*('Project Plan'!$V$5:$V$480)) -> 50 | K20: =SUMPRODUCT(('Project Plan'!$C$5:$C$480=3)*('Project Plan'!$G$5:$G$480=$A20)*('Project Plan'!$W$5:$W$480)) -> 0 | L20: =SUMPRODUCT(('Project Plan'!$C$5:$C$480=3)*('Project Plan'!$G$5:$G$480=$A20)*('Project Plan'!$X$5:$X$480)) -> 9 | M20: =SUM(B20:L20) -> 333 | N20: =M20*(1+Assumptions!$C$5) -> 382.95 | O20: =(B20*Assumptions!$C$12+C20*Assumptions!$C$13+D20*Assumptions!$C$14+E20*Assumptions!$C$15+F20*Assumptions!$C$16+G20*Assumptions!$C$17+H20*Assumptions!$C$18+I20*Assumptions!$C$19+J20*Assumptions!$C$20+K20*Assumptions!$C$21+L20*Assumptions!$C$22)*(1+Assumptions!$C$5) -> 0
A21: 4 Finance & Accounting | B21: =SUMPRODUCT(('Project Plan'!$C$5:$C$480=3)*('Project Plan'!$G$5:$G$480=$A21)*('Project Plan'!$N$5:$N$480)) -> 1 | C21: =SUMPRODUCT(('Project Plan'!$C$5:$C$480=3)*('Project Plan'!$G$5:$G$480=$A21)*('Project Plan'!$O$5:$O$480)) -> 38 | D21: =SUMPRODUCT(('Project Plan'!$C$5:$C$480=3)*('Project Plan'!$G$5:$G$480=$A21)*('Project Plan'!$P$5:$P$480)) -> 11 | E21: =SUMPRODUCT(('Project Plan'!$C$5:$C$480=3)*('Project Plan'!$G$5:$G$480=$A21)*('Project Plan'!$Q$5:$Q$480)) -> 126 | F21: =SUMPRODUCT(('Project Plan'!$C$5:$C$480=3)*('Project Plan'!$G$5:$G$480=$A21)*('Project Plan'!$R$5:$R$480)) -> 61 | G21: =SUMPRODUCT(('Project Plan'!$C$5:$C$480=3)*('Project Plan'!$G$5:$G$480=$A21)*('Project Plan'!$S$5:$S$480)) -> 0 | H21: =SUMPRODUCT(('Project Plan'!$C$5:$C$480=3)*('Project Plan'!$G$5:$G$480=$A21)*('Project Plan'!$T$5:$T$480)) -> 0 | I21: =SUMPRODUCT(('Project Plan'!$C$5:$C$480=3)*('Project Plan'!$G$5:$G$480=$A21)*('Project Plan'!$U$5:$U$480)) -> 0 | J21: =SUMPRODUCT(('Project Plan'!$C$5:$C$480=3)*('Project Plan'!$G$5:$G$480=$A21)*('Project Plan'!$V$5:$V$480)) -> 49 | K21: =SUMPRODUCT(('Project Plan'!$C$5:$C$480=3)*('Project Plan'!$G$5:$G$480=$A21)*('Project Plan'!$W$5:$W$480)) -> 18 | L21: =SUMPRODUCT(('Project Plan'!$C$5:$C$480=3)*('Project Plan'!$G$5:$G$480=$A21)*('Project Plan'!$X$5:$X$480)) -> 9 | M21: =SUM(B21:L21) -> 313 | N21: =M21*(1+Assumptions!$C$5) -> 359.95 | O21: =(B21*Assumptions!$C$12+C21*Assumptions!$C$13+D21*Assumptions!$C$14+E21*Assumptions!$C$15+F21*Assumptions!$C$16+G21*Assumptions!$C$17+H21*Assumptions!$C$18+I21*Assumptions!$C$19+J21*Assumptions!$C$20+K21*Assumptions!$C$21+L21*Assumptions!$C$22)*(1+Assumptions!$C$5) -> 0
A22: 9 Document Management | B22: =SUMPRODUCT(('Project Plan'!$C$5:$C$480=3)*('Project Plan'!$G$5:$G$480=$A22)*('Project Plan'!$N$5:$N$480)) -> 1 | C22: =SUMPRODUCT(('Project Plan'!$C$5:$C$480=3)*('Project Plan'!$G$5:$G$480=$A22)*('Project Plan'!$O$5:$O$480)) -> 38 | D22: =SUMPRODUCT(('Project Plan'!$C$5:$C$480=3)*('Project Plan'!$G$5:$G$480=$A22)*('Project Plan'!$P$5:$P$480)) -> 11 | E22: =SUMPRODUCT(('Project Plan'!$C$5:$C$480=3)*('Project Plan'!$G$5:$G$480=$A22)*('Project Plan'!$Q$5:$Q$480)) -> 116 | F22: =SUMPRODUCT(('Project Plan'!$C$5:$C$480=3)*('Project Plan'!$G$5:$G$480=$A22)*('Project Plan'!$R$5:$R$480)) -> 79 | G22: =SUMPRODUCT(('Project Plan'!$C$5:$C$480=3)*('Project Plan'!$G$5:$G$480=$A22)*('Project Plan'!$S$5:$S$480)) -> 9 | H22: =SUMPRODUCT(('Project Plan'!$C$5:$C$480=3)*('Project Plan'!$G$5:$G$480=$A22)*('Project Plan'!$T$5:$T$480)) -> 0 | I22: =SUMPRODUCT(('Project Plan'!$C$5:$C$480=3)*('Project Plan'!$G$5:$G$480=$A22)*('Project Plan'!$U$5:$U$480)) -> 0 | J22: =SUMPRODUCT(('Project Plan'!$C$5:$C$480=3)*('Project Plan'!$G$5:$G$480=$A22)*('Project Plan'!$V$5:$V$480)) -> 49 | K22: =SUMPRODUCT(('Project Plan'!$C$5:$C$480=3)*('Project Plan'!$G$5:$G$480=$A22)*('Project Plan'!$W$5:$W$480)) -> 18 | L22: =SUMPRODUCT(('Project Plan'!$C$5:$C$480=3)*('Project Plan'!$G$5:$G$480=$A22)*('Project Plan'!$X$5:$X$480)) -> 9 | M22: =SUM(B22:L22) -> 330 | N22: =M22*(1+Assumptions!$C$5) -> 379.5 | O22: =(B22*Assumptions!$C$12+C22*Assumptions!$C$13+D22*Assumptions!$C$14+E22*Assumptions!$C$15+F22*Assumptions!$C$16+G22*Assumptions!$C$17+H22*Assumptions!$C$18+I22*Assumptions!$C$19+J22*Assumptions!$C$20+K22*Assumptions!$C$21+L22*Assumptions!$C$22)*(1+Assumptions!$C$5) -> 0
A23: 5 Trade Licence | B23: =SUMPRODUCT(('Project Plan'!$C$5:$C$480=3)*('Project Plan'!$G$5:$G$480=$A23)*('Project Plan'!$N$5:$N$480)) -> 1 | C23: =SUMPRODUCT(('Project Plan'!$C$5:$C$480=3)*('Project Plan'!$G$5:$G$480=$A23)*('Project Plan'!$O$5:$O$480)) -> 33 | D23: =SUMPRODUCT(('Project Plan'!$C$5:$C$480=3)*('Project Plan'!$G$5:$G$480=$A23)*('Project Plan'!$P$5:$P$480)) -> 9 | E23: =SUMPRODUCT(('Project Plan'!$C$5:$C$480=3)*('Project Plan'!$G$5:$G$480=$A23)*('Project Plan'!$Q$5:$Q$480)) -> 103 | F23: =SUMPRODUCT(('Project Plan'!$C$5:$C$480=3)*('Project Plan'!$G$5:$G$480=$A23)*('Project Plan'!$R$5:$R$480)) -> 67 | G23: =SUMPRODUCT(('Project Plan'!$C$5:$C$480=3)*('Project Plan'!$G$5:$G$480=$A23)*('Project Plan'!$S$5:$S$480)) -> 24 | H23: =SUMPRODUCT(('Project Plan'!$C$5:$C$480=3)*('Project Plan'!$G$5:$G$480=$A23)*('Project Plan'!$T$5:$T$480)) -> 13 | I23: =SUMPRODUCT(('Project Plan'!$C$5:$C$480=3)*('Project Plan'!$G$5:$G$480=$A23)*('Project Plan'!$U$5:$U$480)) -> 0 | J23: =SUMPRODUCT(('Project Plan'!$C$5:$C$480=3)*('Project Plan'!$G$5:$G$480=$A23)*('Project Plan'!$V$5:$V$480)) -> 40 | K23: =SUMPRODUCT(('Project Plan'!$C$5:$C$480=3)*('Project Plan'!$G$5:$G$480=$A23)*('Project Plan'!$W$5:$W$480)) -> 16 | L23: =SUMPRODUCT(('Project Plan'!$C$5:$C$480=3)*('Project Plan'!$G$5:$G$480=$A23)*('Project Plan'!$X$5:$X$480)) -> 8 | M23: =SUM(B23:L23) -> 314 | N23: =M23*(1+Assumptions!$C$5) -> 361.1 | O23: =(B23*Assumptions!$C$12+C23*Assumptions!$C$13+D23*Assumptions!$C$14+E23*Assumptions!$C$15+F23*Assumptions!$C$16+G23*Assumptions!$C$17+H23*Assumptions!$C$18+I23*Assumptions!$C$19+J23*Assumptions!$C$20+K23*Assumptions!$C$21+L23*Assumptions!$C$22)*(1+Assumptions!$C$5) -> 0
A24: 6 User Charges | B24: =SUMPRODUCT(('Project Plan'!$C$5:$C$480=3)*('Project Plan'!$G$5:$G$480=$A24)*('Project Plan'!$N$5:$N$480)) -> 1 | C24: =SUMPRODUCT(('Project Plan'!$C$5:$C$480=3)*('Project Plan'!$G$5:$G$480=$A24)*('Project Plan'!$O$5:$O$480)) -> 27 | D24: =SUMPRODUCT(('Project Plan'!$C$5:$C$480=3)*('Project Plan'!$G$5:$G$480=$A24)*('Project Plan'!$P$5:$P$480)) -> 8 | E24: =SUMPRODUCT(('Project Plan'!$C$5:$C$480=3)*('Project Plan'!$G$5:$G$480=$A24)*('Project Plan'!$Q$5:$Q$480)) -> 92 | F24: =SUMPRODUCT(('Project Plan'!$C$5:$C$480=3)*('Project Plan'!$G$5:$G$480=$A24)*('Project Plan'!$R$5:$R$480)) -> 59 | G24: =SUMPRODUCT(('Project Plan'!$C$5:$C$480=3)*('Project Plan'!$G$5:$G$480=$A24)*('Project Plan'!$S$5:$S$480)) -> 21 | H24: =SUMPRODUCT(('Project Plan'!$C$5:$C$480=3)*('Project Plan'!$G$5:$G$480=$A24)*('Project Plan'!$T$5:$T$480)) -> 11 | I24: =SUMPRODUCT(('Project Plan'!$C$5:$C$480=3)*('Project Plan'!$G$5:$G$480=$A24)*('Project Plan'!$U$5:$U$480)) -> 0 | J24: =SUMPRODUCT(('Project Plan'!$C$5:$C$480=3)*('Project Plan'!$G$5:$G$480=$A24)*('Project Plan'!$V$5:$V$480)) -> 34 | K24: =SUMPRODUCT(('Project Plan'!$C$5:$C$480=3)*('Project Plan'!$G$5:$G$480=$A24)*('Project Plan'!$W$5:$W$480)) -> 14 | L24: =SUMPRODUCT(('Project Plan'!$C$5:$C$480=3)*('Project Plan'!$G$5:$G$480=$A24)*('Project Plan'!$X$5:$X$480)) -> 7 | M24: =SUM(B24:L24) -> 274 | N24: =M24*(1+Assumptions!$C$5) -> 315.1 | O24: =(B24*Assumptions!$C$12+C24*Assumptions!$C$13+D24*Assumptions!$C$14+E24*Assumptions!$C$15+F24*Assumptions!$C$16+G24*Assumptions!$C$17+H24*Assumptions!$C$18+I24*Assumptions!$C$19+J24*Assumptions!$C$20+K24*Assumptions!$C$21+L24*Assumptions!$C$22)*(1+Assumptions!$C$5) -> 0
A25: 11 Building Permission | B25: =SUMPRODUCT(('Project Plan'!$C$5:$C$480=3)*('Project Plan'!$G$5:$G$480=$A25)*('Project Plan'!$N$5:$N$480)) -> 1 | C25: =SUMPRODUCT(('Project Plan'!$C$5:$C$480=3)*('Project Plan'!$G$5:$G$480=$A25)*('Project Plan'!$O$5:$O$480)) -> 28 | D25: =SUMPRODUCT(('Project Plan'!$C$5:$C$480=3)*('Project Plan'!$G$5:$G$480=$A25)*('Project Plan'!$P$5:$P$480)) -> 8 | E25: =SUMPRODUCT(('Project Plan'!$C$5:$C$480=3)*('Project Plan'!$G$5:$G$480=$A25)*('Project Plan'!$Q$5:$Q$480)) -> 138 | F25: =SUMPRODUCT(('Project Plan'!$C$5:$C$480=3)*('Project Plan'!$G$5:$G$480=$A25)*('Project Plan'!$R$5:$R$480)) -> 61 | G25: =SUMPRODUCT(('Project Plan'!$C$5:$C$480=3)*('Project Plan'!$G$5:$G$480=$A25)*('Project Plan'!$S$5:$S$480)) -> 21 | H25: =SUMPRODUCT(('Project Plan'!$C$5:$C$480=3)*('Project Plan'!$G$5:$G$480=$A25)*('Project Plan'!$T$5:$T$480)) -> 12 | I25: =SUMPRODUCT(('Project Plan'!$C$5:$C$480=3)*('Project Plan'!$G$5:$G$480=$A25)*('Project Plan'!$U$5:$U$480)) -> 0 | J25: =SUMPRODUCT(('Project Plan'!$C$5:$C$480=3)*('Project Plan'!$G$5:$G$480=$A25)*('Project Plan'!$V$5:$V$480)) -> 45 | K25: =SUMPRODUCT(('Project Plan'!$C$5:$C$480=3)*('Project Plan'!$G$5:$G$480=$A25)*('Project Plan'!$W$5:$W$480)) -> 14 | L25: =SUMPRODUCT(('Project Plan'!$C$5:$C$480=3)*('Project Plan'!$G$5:$G$480=$A25)*('Project Plan'!$X$5:$X$480)) -> 7 | M25: =SUM(B25:L25) -> 335 | N25: =M25*(1+Assumptions!$C$5) -> 385.25 | O25: =(B25*Assumptions!$C$12+C25*Assumptions!$C$13+D25*Assumptions!$C$14+E25*Assumptions!$C$15+F25*Assumptions!$C$16+G25*Assumptions!$C$17+H25*Assumptions!$C$18+I25*Assumptions!$C$19+J25*Assumptions!$C$20+K25*Assumptions!$C$21+L25*Assumptions!$C$22)*(1+Assumptions!$C$5) -> 0
A26: 13 Town Planning | B26: =SUMPRODUCT(('Project Plan'!$C$5:$C$480=3)*('Project Plan'!$G$5:$G$480=$A26)*('Project Plan'!$N$5:$N$480)) -> 1 | C26: =SUMPRODUCT(('Project Plan'!$C$5:$C$480=3)*('Project Plan'!$G$5:$G$480=$A26)*('Project Plan'!$O$5:$O$480)) -> 28 | D26: =SUMPRODUCT(('Project Plan'!$C$5:$C$480=3)*('Project Plan'!$G$5:$G$480=$A26)*('Project Plan'!$P$5:$P$480)) -> 8 | E26: =SUMPRODUCT(('Project Plan'!$C$5:$C$480=3)*('Project Plan'!$G$5:$G$480=$A26)*('Project Plan'!$Q$5:$Q$480)) -> 98 | F26: =SUMPRODUCT(('Project Plan'!$C$5:$C$480=3)*('Project Plan'!$G$5:$G$480=$A26)*('Project Plan'!$R$5:$R$480)) -> 61 | G26: =SUMPRODUCT(('Project Plan'!$C$5:$C$480=3)*('Project Plan'!$G$5:$G$480=$A26)*('Project Plan'!$S$5:$S$480)) -> 21 | H26: =SUMPRODUCT(('Project Plan'!$C$5:$C$480=3)*('Project Plan'!$G$5:$G$480=$A26)*('Project Plan'!$T$5:$T$480)) -> 12 | I26: =SUMPRODUCT(('Project Plan'!$C$5:$C$480=3)*('Project Plan'!$G$5:$G$480=$A26)*('Project Plan'!$U$5:$U$480)) -> 0 | J26: =SUMPRODUCT(('Project Plan'!$C$5:$C$480=3)*('Project Plan'!$G$5:$G$480=$A26)*('Project Plan'!$V$5:$V$480)) -> 38 | K26: =SUMPRODUCT(('Project Plan'!$C$5:$C$480=3)*('Project Plan'!$G$5:$G$480=$A26)*('Project Plan'!$W$5:$W$480)) -> 14 | L26: =SUMPRODUCT(('Project Plan'!$C$5:$C$480=3)*('Project Plan'!$G$5:$G$480=$A26)*('Project Plan'!$X$5:$X$480)) -> 7 | M26: =SUM(B26:L26) -> 288 | N26: =M26*(1+Assumptions!$C$5) -> 331.2 | O26: =(B26*Assumptions!$C$12+C26*Assumptions!$C$13+D26*Assumptions!$C$14+E26*Assumptions!$C$15+F26*Assumptions!$C$16+G26*Assumptions!$C$17+H26*Assumptions!$C$18+I26*Assumptions!$C$19+J26*Assumptions!$C$20+K26*Assumptions!$C$21+L26*Assumptions!$C$22)*(1+Assumptions!$C$5) -> 0
A27: 18 Fire NOC | B27: =SUMPRODUCT(('Project Plan'!$C$5:$C$480=3)*('Project Plan'!$G$5:$G$480=$A27)*('Project Plan'!$N$5:$N$480)) -> 1 | C27: =SUMPRODUCT(('Project Plan'!$C$5:$C$480=3)*('Project Plan'!$G$5:$G$480=$A27)*('Project Plan'!$O$5:$O$480)) -> 21 | D27: =SUMPRODUCT(('Project Plan'!$C$5:$C$480=3)*('Project Plan'!$G$5:$G$480=$A27)*('Project Plan'!$P$5:$P$480)) -> 6 | E27: =SUMPRODUCT(('Project Plan'!$C$5:$C$480=3)*('Project Plan'!$G$5:$G$480=$A27)*('Project Plan'!$Q$5:$Q$480)) -> 81 | F27: =SUMPRODUCT(('Project Plan'!$C$5:$C$480=3)*('Project Plan'!$G$5:$G$480=$A27)*('Project Plan'!$R$5:$R$480)) -> 45 | G27: =SUMPRODUCT(('Project Plan'!$C$5:$C$480=3)*('Project Plan'!$G$5:$G$480=$A27)*('Project Plan'!$S$5:$S$480)) -> 15 | H27: =SUMPRODUCT(('Project Plan'!$C$5:$C$480=3)*('Project Plan'!$G$5:$G$480=$A27)*('Project Plan'!$T$5:$T$480)) -> 9 | I27: =SUMPRODUCT(('Project Plan'!$C$5:$C$480=3)*('Project Plan'!$G$5:$G$480=$A27)*('Project Plan'!$U$5:$U$480)) -> 0 | J27: =SUMPRODUCT(('Project Plan'!$C$5:$C$480=3)*('Project Plan'!$G$5:$G$480=$A27)*('Project Plan'!$V$5:$V$480)) -> 29 | K27: =SUMPRODUCT(('Project Plan'!$C$5:$C$480=3)*('Project Plan'!$G$5:$G$480=$A27)*('Project Plan'!$W$5:$W$480)) -> 0 | L27: =SUMPRODUCT(('Project Plan'!$C$5:$C$480=3)*('Project Plan'!$G$5:$G$480=$A27)*('Project Plan'!$X$5:$X$480)) -> 5 | M27: =SUM(B27:L27) -> 212 | N27: =M27*(1+Assumptions!$C$5) -> 243.8 | O27: =(B27*Assumptions!$C$12+C27*Assumptions!$C$13+D27*Assumptions!$C$14+E27*Assumptions!$C$15+F27*Assumptions!$C$16+G27*Assumptions!$C$17+H27*Assumptions!$C$18+I27*Assumptions!$C$19+J27*Assumptions!$C$20+K27*Assumptions!$C$21+L27*Assumptions!$C$22)*(1+Assumptions!$C$5) -> 0
A28: 7 Solid Waste | B28: =SUMPRODUCT(('Project Plan'!$C$5:$C$480=3)*('Project Plan'!$G$5:$G$480=$A28)*('Project Plan'!$N$5:$N$480)) -> 1 | C28: =SUMPRODUCT(('Project Plan'!$C$5:$C$480=3)*('Project Plan'!$G$5:$G$480=$A28)*('Project Plan'!$O$5:$O$480)) -> 21 | D28: =SUMPRODUCT(('Project Plan'!$C$5:$C$480=3)*('Project Plan'!$G$5:$G$480=$A28)*('Project Plan'!$P$5:$P$480)) -> 6 | E28: =SUMPRODUCT(('Project Plan'!$C$5:$C$480=3)*('Project Plan'!$G$5:$G$480=$A28)*('Project Plan'!$Q$5:$Q$480)) -> 86 | F28: =SUMPRODUCT(('Project Plan'!$C$5:$C$480=3)*('Project Plan'!$G$5:$G$480=$A28)*('Project Plan'!$R$5:$R$480)) -> 35 | G28: =SUMPRODUCT(('Project Plan'!$C$5:$C$480=3)*('Project Plan'!$G$5:$G$480=$A28)*('Project Plan'!$S$5:$S$480)) -> 11 | H28: =SUMPRODUCT(('Project Plan'!$C$5:$C$480=3)*('Project Plan'!$G$5:$G$480=$A28)*('Project Plan'!$T$5:$T$480)) -> 9 | I28: =SUMPRODUCT(('Project Plan'!$C$5:$C$480=3)*('Project Plan'!$G$5:$G$480=$A28)*('Project Plan'!$U$5:$U$480)) -> 0 | J28: =SUMPRODUCT(('Project Plan'!$C$5:$C$480=3)*('Project Plan'!$G$5:$G$480=$A28)*('Project Plan'!$V$5:$V$480)) -> 29 | K28: =SUMPRODUCT(('Project Plan'!$C$5:$C$480=3)*('Project Plan'!$G$5:$G$480=$A28)*('Project Plan'!$W$5:$W$480)) -> 0 | L28: =SUMPRODUCT(('Project Plan'!$C$5:$C$480=3)*('Project Plan'!$G$5:$G$480=$A28)*('Project Plan'!$X$5:$X$480)) -> 5 | M28: =SUM(B28:L28) -> 203 | N28: =M28*(1+Assumptions!$C$5) -> 233.45 | O28: =(B28*Assumptions!$C$12+C28*Assumptions!$C$13+D28*Assumptions!$C$14+E28*Assumptions!$C$15+F28*Assumptions!$C$16+G28*Assumptions!$C$17+H28*Assumptions!$C$18+I28*Assumptions!$C$19+J28*Assumptions!$C$20+K28*Assumptions!$C$21+L28*Assumptions!$C$22)*(1+Assumptions!$C$5) -> 0
... A37: Release | B37: =SUMPRODUCT(('Project Plan'!$C$5:$C$480=3)*('Project Plan'!$G$5:$G$480=$A37)*('Project Plan'!$N$5:$N$480)) -> 0 | C37: =SUMPRODUCT(('Project Plan'!$C$5:$C$480=3)*('Project Plan'!$G$5:$G$480=$A37)*('Project Plan'!$O$5:$O$480)) -> 64 | D37: =SUMPRODUCT(('Project Plan'!$C$5:$C$480=3)*('Project Plan'!$G$5:$G$480=$A37)*('Project Plan'!$P$5:$P$480)) -> 12 | E37: =SUMPRODUCT(('Project Plan'!$C$5:$C$480=3)*('Project Plan'!$G$5:$G$480=$A37)*('Project Plan'!$Q$5:$Q$480)) -> 144 | F37: =SUMPRODUCT(('Project Plan'!$C$5:$C$480=3)*('Project Plan'!$G$5:$G$480=$A37)*('Project Plan'!$R$5:$R$480)) -> 16 | G37: =SUMPRODUCT(('Project Plan'!$C$5:$C$480=3)*('Project Plan'!$G$5:$G$480=$A37)*('Project Plan'!$S$5:$S$480)) -> 0 | H37: =SUMPRODUCT(('Project Plan'!$C$5:$C$480=3)*('Project Plan'!$G$5:$G$480=$A37)*('Project Plan'!$T$5:$T$480)) -> 0 | I37: =SUMPRODUCT(('Project Plan'!$C$5:$C$480=3)*('Project Plan'!$G$5:$G$480=$A37)*('Project Plan'!$U$5:$U$480)) -> 80 | J37: =SUMPRODUCT(('Project Plan'!$C$5:$C$480=3)*('Project Plan'!$G$5:$G$480=$A37)*('Project Plan'!$V$5:$V$480)) -> 156 | K37: =SUMPRODUCT(('Project Plan'!$C$5:$C$480=3)*('Project Plan'!$G$5:$G$480=$A37)*('Project Plan'!$W$5:$W$480)) -> 48 | L37: =SUMPRODUCT(('Project Plan'!$C$5:$C$480=3)*('Project Plan'!$G$5:$G$480=$A37)*('Project Plan'!$X$5:$X$480)) -> 60 | M37: =SUM(B37:L37) -> 580 | N37: =M37*(1+Assumptions!$C$5) -> 667 | O37: =(B37*Assumptions!$C$12+C37*Assumptions!$C$13+D37*Assumptions!$C$14+E37*Assumptions!$C$15+F37*Assumptions!$C$16+G37*Assumptions!$C$17+H37*Assumptions!$C$18+I37*Assumptions!$C$19+J37*Assumptions!$C$20+K37*Assumptions!$C$21+L37*Assumptions!$C$22)*(1+Assumptions!$C$5) -> 0
